Workbook

Sheet Matriz de trazabilidad
A2: Matriz de trazabilidad
A4: Seleccione los códigos amarillos. Las descripciones y el estado de cobertura se completan automáticamente desde las hojas de apoyo.
A5: Resumen | B5: Relaciones registradas | C5: =COUNTIF(G8:G85,"?*") -> 78 | D5: Completas | E5: =COUNTIF(B8:B85,"Trazabilidad completa") -> 0 | F5: Con pendientes | G5: =COUNTIF(G8:G85,"?*")-COUNTIF(B8:B85,"Trazabilidad completa") -> 78 | H5: Pruebas aprobadas | I5: =COUNTIF(O8:O85,"Aprobado") -> 0 | J5: Pruebas fallidas | K5: =COUNTIF(O8:O85,"Fallido") -> 0
A7: N.º | B7: Estado de trazabilidad | C7: ID Objetivo | D7: Objetivo | E7: ID Proceso | F7: Proceso / Módulo | G7: ID Requerimiento | H7: Requerimiento | I7: ID HU | J7: Historia de usuario | K7: ID Criterio | L7: Criterio de aceptación | M7: ID Caso de prueba | N7: Caso / Escenario | O7: Estado prueba | P7: ID Evidencia | Q7: Evidencia / Enlace | R7: Observaciones
A8: 1 | B8: =IF($G8="","",IF($K8="","Falta criterio",IFERROR(IF(VLOOKUP($K8,'Historias y criterios'!$A$6:$P$83,3,FALSE)<>$G8,"Revisar relación requisito-criterio",IF($M8="","Falta caso de prueba",IF(VLOOKUP($M8,'Casos y evidencias'!$A$6:$O$83,2,FALSE)<>$K8,"Revisar relación criterio-caso",IF($O8="Aprobado",IF($P8="","Falta evidencia","Trazabilidad completa"),IF($O8="Fallido","Prueba fallida",IF($O8="Bloqueado","Prueba bloqueada","Prueba pendiente")))))),"ID no encontrado"))) -> Prueba pendiente | C8: =IF($G8="","",IFERROR(IF(VLOOKUP($G8,Requerimientos!$A$6:$M$43,2,FALSE)="","",VLOOKUP($G8,Requerimientos!$A$6:$M$43,2,FALSE)),"ID no encontrado")) -> OBJ-001 | D8: =IF($C8="","",IFERROR(IF(VLOOKUP($C8,'Objetivos y procesos'!$A$6:$H$35,2,FALSE)="","",VLOOKUP($C8,'Objetivos y procesos'!$A$6:$H$35,2,FALSE)),"ID no encontrado")) -> Proteger la plataforma y asegurar que cada usuario opere con el perfil, empresa y vendedor correctos. | E8: =IF($G8="","",IFERROR(IF(VLOOKUP($G8,Requerimientos!$A$6:$M$43,3,FALSE)="","",VLOOKUP($G8,Requerimientos!$A$6:$M$43,3,FALSE)),"ID no encontrado")) -> PR-01 | F8: =IF($E8="","",IFERROR(IF(INDEX('Objetivos y procesos'!$D$6:$D$35,MATCH($E8,'Objetivos y procesos'!$C$6:$C$35,0))="","",IF(INDEX('Objetivos y procesos'!$D$6:$D$35,MATCH($E8,'Objetivos y procesos'!$C$6:$C$35,0))=INDEX('Objetivos y procesos'!$E$6:$E$35,MATCH($E8,'Objetivos y procesos'!$C$6:$C$35,0)),INDEX('Objetivos y procesos'!$D$6:$D$35,MATCH($E8,'Objetivos y procesos'!$C$6:$C$35,0)),INDEX('Objetivos y procesos'!$D$6:$D$35,MATCH($E8,'Objetivos y procesos'!$C$6:$C$35,0))&IF(INDEX('Objetivos y procesos'!$E$6:$E$35,MATCH($E8,'Objetivos y procesos'!$C$6:$C$35,0))="",""," / "&INDEX('Objetivos y procesos'!$E$6:$E$35,MATCH($E8,'Objetivos y procesos'!$C$6:$C$35,0))))),"ID no encontrado")) -> Gestión de usuarios, roles y permisos | G8: RF-01 | H8: =IF($G8="","",IFERROR(IF(VLOOKUP($G8,Requerimientos!$A$6:$M$43,7,FALSE)="","",VLOOKUP($G8,Requerimientos!$A$6:$M$43,7,FALSE)),"ID no encontrado")) -> El sistema debe permitir que un usuario se autentique mediante usuario y contraseña. | I8: =IF($K8="","",IFERROR(IF(VLOOKUP($K8,'Historias y criterios'!$A$6:$P$83,2,FALSE)="","",VLOOKUP($K8,'Historias y criterios'!$A$6:$P$83,2,FALSE)),"ID no encontrado")) -> HU-001 | J8: =IF($K8="","",IFERROR(IF(VLOOKUP($K8,'Historias y criterios'!$A$6:$P$83,10,FALSE)="","",VLOOKUP($K8,'Historias y criterios'!$A$6:$P$83,10,FALSE)),"ID no encontrado")) -> Como usuario habilitado, quiero iniciar sesión de forma segura y mantener una sesión controlada, para acceder únicamente a las funciones autorizadas | K8: CA-001 | L8: =IF($K8="","",IFERROR(IF(VLOOKUP($K8,'Historias y criterios'!$A$6:$P$83,11,FALSE)="","",VLOOKUP($K8,'Historias y criterios'!$A$6:$P$83,11,FALSE)),"ID no encontrado")) -> Con credenciales válidas, el usuario activo ingresa a la plataforma. | M8: CP-001 | N8: =IF($M8="","",IFERROR(IF(VLOOKUP($M8,'Casos y evidencias'!$A$6:$O$83,5,FALSE)="","",VLOOKUP($M8,'Casos y evidencias'!$A$6:$O$83,5,FALSE)),"ID no encontrado")) -> Inicio de sesión con credenciales válidas | O8: =IF($M8="","",IFERROR(IF(VLOOKUP($M8,'Casos y evidencias'!$A$6:$O$83,10,FALSE)="","",VLOOKUP($M8,'Casos y evidencias'!$A$6:$O$83,10,FALSE)),"ID no encontrado")) -> No ejecutado | P8: =IF($M8="","",IFERROR(IF(VLOOKUP($M8,'Casos y evidencias'!$A$6:$O$83,11,FALSE)="","",VLOOKUP($M8,'Casos y evidencias'!$A$6:$O$83,11,FALSE)),"ID no encontrado")) | Q8: =IF($M8="","",IFERROR(IF(VLOOKUP($M8,'Casos y evidencias'!$A$6:$O$83,12,FALSE)="","",VLOOKUP($M8,'Casos y evidencias'!$A$6:$O$83,12,FALSE)),"ID no encontrado"))
A9: 2 | B9: =IF($G9="","",IF($K9="","Falta criterio",IFERROR(IF(VLOOKUP($K9,'Historias y criterios'!$A$6:$P$83,3,FALSE)<>$G9,"Revisar relación requisito-criterio",IF($M9="","Falta caso de prueba",IF(VLOOKUP($M9,'Casos y evidencias'!$A$6:$O$83,2,FALSE)<>$K9,"Revisar relación criterio-caso",IF($O9="Aprobado",IF($P9="","Falta evidencia","Trazabilidad completa"),IF($O9="Fallido","Prueba fallida",IF($O9="Bloqueado","Prueba bloqueada","Prueba pendiente")))))),"ID no encontrado"))) -> Prueba pendiente | C9: =IF($G9="","",IFERROR(IF(VLOOKUP($G9,Requerimientos!$A$6:$M$43,2,FALSE)="","",VLOOKUP($G9,Requerimientos!$A$6:$M$43,2,FALSE)),"ID no encontrado")) -> OBJ-001 | D9: =IF($C9="","",IFERROR(IF(VLOOKUP($C9,'Objetivos y procesos'!$A$6:$H$35,2,FALSE)="","",VLOOKUP($C9,'Objetivos y procesos'!$A$6:$H$35,2,FALSE)),"ID no encontrado")) -> Proteger la plataforma y asegurar que cada usuario opere con el perfil, empresa y vendedor correctos. | E9: =IF($G9="","",IFERROR(IF(VLOOKUP($G9,Requerimientos!$A$6:$M$43,3,FALSE)="","",VLOOKUP($G9,Requerimientos!$A$6:$M$43,3,FALSE)),"ID no encontrado")) -> PR-01 | F9: =IF($E9="","",IFERROR(IF(INDEX('Objetivos y procesos'!$D$6:$D$35,MATCH($E9,'Objetivos y procesos'!$C$6:$C$35,0))="","",IF(INDEX('Objetivos y procesos'!$D$6:$D$35,MATCH($E9,'Objetivos y procesos'!$C$6:$C$35,0))=INDEX('Objetivos y procesos'!$E$6:$E$35,MATCH($E9,'Objetivos y procesos'!$C$6:$C$35,0)),INDEX('Objetivos y procesos'!$D$6:$D$35,MATCH($E9,'Objetivos y procesos'!$C$6:$C$35,0)),INDEX('Objetivos y procesos'!$D$6:$D$35,MATCH($E9,'Objetivos y procesos'!$C$6:$C$35,0))&IF(INDEX('Objetivos y procesos'!$E$6:$E$35,MATCH($E9,'Objetivos y procesos'!$C$6:$C$35,0))="",""," / "&INDEX('Objetivos y procesos'!$E$6:$E$35,MATCH($E9,'Objetivos y procesos'!$C$6:$C$35,0))))),"ID no encontrado")) -> Gestión de usuarios, roles y permisos | G9: RF-01 | H9: =IF($G9="","",IFERROR(IF(VLOOKUP($G9,Requerimientos!$A$6:$M$43,7,FALSE)="","",VLOOKUP($G9,Requerimientos!$A$6:$M$43,7,FALSE)),"ID no encontrado")) -> El sistema debe permitir que un usuario se autentique mediante usuario y contraseña. | I9: =IF($K9="","",IFERROR(IF(VLOOKUP($K9,'Historias y criterios'!$A$6:$P$83,2,FALSE)="","",VLOOKUP($K9,'Historias y criterios'!$A$6:$P$83,2,FALSE)),"ID no encontrado")) -> HU-001 | J9: =IF($K9="","",IFERROR(IF(VLOOKUP($K9,'Historias y criterios'!$A$6:$P$83,10,FALSE)="","",VLOOKUP($K9,'Historias y criterios'!$A$6:$P$83,10,FALSE)),"ID no encontrado")) -> Como usuario habilitado, quiero iniciar sesión de forma segura y mantener una sesión controlada, para acceder únicamente a las funciones autorizadas | K9: CA-002 | L9: =IF($K9="","",IFERROR(IF(VLOOKUP($K9,'Historias y criterios'!$A$6:$P$83,11,FALSE)="","",VLOOKUP($K9,'Historias y criterios'!$A$6:$P$83,11,FALSE)),"ID no encontrado")) -> Las credenciales inválidas o de un usuario desactivado impiden el acceso y muestran un mensaje claro. | M9: CP-002 | N9: =IF($M9="","",IFERROR(IF(VLOOKUP($M9,'Casos y evidencias'!$A$6:$O$83,5,FALSE)="","",VLOOKUP($M9,'Casos y evidencias'!$A$6:$O$83,5,FALSE)),"ID no encontrado")) -> Acceso denegado con credenciales inválidas o usuario desactivado | O9: =IF($M9="","",IFERROR(IF(VLOOKUP($M9,'Casos y evidencias'!$A$6:$O$83,10,FALSE)="","",VLOOKUP($M9,'Casos y evidencias'!$A$6:$O$83,10,FALSE)),"ID no encontrado")) -> No ejecutado | P9: =IF($M9="","",IFERROR(IF(VLOOKUP($M9,'Casos y evidencias'!$A$6:$O$83,11,FALSE)="","",VLOOKUP($M9,'Casos y evidencias'!$A$6:$O$83,11,FALSE)),"ID no encontrado")) | Q9: =IF($M9="","",IFERROR(IF(VLOOKUP($M9,'Casos y evidencias'!$A$6:$O$83,12,FALSE)="","",VLOOKUP($M9,'Casos y evidencias'!$A$6:$O$83,12,FALSE)),"ID no encontrado"))
A10: 3 | B10: =IF($G10="","",IF($K10="","Falta criterio",IFERROR(IF(VLOOKUP($K10,'Historias y criterios'!$A$6:$P$83,3,FALSE)<>$G10,"Revisar relación requisito-criterio",IF($M10="","Falta caso de prueba",IF(VLOOKUP($M10,'Casos y evidencias'!$A$6:$O$83,2,FALSE)<>$K10,"Revisar relación criterio-caso",IF($O10="Aprobado",IF($P10="","Falta evidencia","Trazabilidad completa"),IF($O10="Fallido","Prueba fallida",IF($O10="Bloqueado","Prueba bloqueada","Prueba pendiente")))))),"ID no encontrado"))) -> Prueba pendiente | C10: =IF($G10="","",IFERROR(IF(VLOOKUP($G10,Requerimientos!$A$6:$M$43,2,FALSE)="","",VLOOKUP($G10,Requerimientos!$A$6:$M$43,2,FALSE)),"ID no encontrado")) -> OBJ-001 | D10: =IF($C10="","",IFERROR(IF(VLOOKUP($C10,'Objetivos y procesos'!$A$6:$H$35,2,FALSE)="","",VLOOKUP($C10,'Objetivos y procesos'!$A$6:$H$35,2,FALSE)),"ID no encontrado")) -> Proteger la plataforma y asegurar que cada usuario opere con el perfil, empresa y vendedor correctos. | E10: =IF($G10="","",IFERROR(IF(VLOOKUP($G10,Requerimientos!$A$6:$M$43,3,FALSE)="","",VLOOKUP($G10,Requerimientos!$A$6:$M$43,3,FALSE)),"ID no encontrado")) -> PR-01 | F10: =IF($E10="","",IFERROR(IF(INDEX('Objetivos y procesos'!$D$6:$D$35,MATCH($E10,'Objetivos y procesos'!$C$6:$C$35,0))="","",IF(INDEX('Objetivos y procesos'!$D$6:$D$35,MATCH($E10,'Objetivos y procesos'!$C$6:$C$35,0))=INDEX('Objetivos y procesos'!$E$6:$E$35,MATCH($E10,'Objetivos y procesos'!$C$6:$C$35,0)),INDEX('Objetivos y procesos'!$D$6:$D$35,MATCH($E10,'Objetivos y procesos'!$C$6:$C$35,0)),INDEX('Objetivos y procesos'!$D$6:$D$35,MATCH($E10,'Objetivos y procesos'!$C$6:$C$35,0))&IF(INDEX('Objetivos y procesos'!$E$6:$E$35,MATCH($E10,'Objetivos y procesos'!$C$6:$C$35,0))="",""," / "&INDEX('Objetivos y procesos'!$E$6:$E$35,MATCH($E10,'Objetivos y procesos'!$C$6:$C$35,0))))),"ID no encontrado")) -> Gestión de usuarios, roles y permisos | G10: RF-01 | H10: =IF($G10="","",IFERROR(IF(VLOOKUP($G10,Requerimientos!$A$6:$M$43,7,FALSE)="","",VLOOKUP($G10,Requerimientos!$A$6:$M$43,7,FALSE)),"ID no encontrado")) -> El sistema debe permitir que un usuario se autentique mediante usuario y contraseña. | I10: =IF($K10="","",IFERROR(IF(VLOOKUP($K10,'Historias y criterios'!$A$6:$P$83,2,FALSE)="","",VLOOKUP($K10,'Historias y criterios'!$A$6:$P$83,2,FALSE)),"ID no encontrado")) -> HU-001 | J10: =IF($K10="","",IFERROR(IF(VLOOKUP($K10,'Historias y criterios'!$A$6:$P$83,10,FALSE)="","",VLOOKUP($K10,'Historias y criterios'!$A$6:$P$83,10,FALSE)),"ID no encontrado")) -> Como usuario habilitado, quiero iniciar sesión de forma segura y mantener una sesión controlada, para acceder únicamente a las funciones autorizadas | K10: CA-003 | L10: =IF($K10="","",IFERROR(IF(VLOOKUP($K10,'Historias y criterios'!$A$6:$P$83,11,FALSE)="","",VLOOKUP($K10,'Historias y criterios'!$A$6:$P$83,11,FALSE)),"ID no encontrado")) -> La contraseña se almacena mediante hash, la sesión expira por inactividad y los intentos fallidos quedan auditados. | M10: CP-003 | N10: =IF($M10="","",IFERROR(IF(VLOOKUP($M10,'Casos y evidencias'!$A$6:$O$83,5,FALSE)="","",VLOOKUP($M10,'Casos y evidencias'!$A$6:$O$83,5,FALSE)),"ID no encontrado")) -> Hash de contraseña, expiración de sesión y auditoría | O10: =IF($M10="","",IFERROR(IF(VLOOKUP($M10,'Casos y evidencias'!$A$6:$O$83,10,FALSE)="","",VLOOKUP($M10,'Casos y evidencias'!$A$6:$O$83,10,FALSE)),"ID no encontrado")) -> No ejecutado | P10: =IF($M10="","",IFERROR(IF(VLOOKUP($M10,'Casos y evidencias'!$A$6:$O$83,11,FALSE)="","",VLOOKUP($M10,'Casos y evidencias'!$A$6:$O$83,11,FALSE)),"ID no encontrado")) | Q10: =IF($M10="","",IFERROR(IF(VLOOKUP($M10,'Casos y evidencias'!$A$6:$O$83,12,FALSE)="","",VLOOKUP($M10,'Casos y evidencias'!$A$6:$O$83,12,FALSE)),"ID no encontrado"))
A11: 4 | B11: =IF($G11="","",IF($K11="","Falta criterio",IFERROR(IF(VLOOKUP($K11,'Historias y criterios'!$A$6:$P$83,3,FALSE)<>$G11,"Revisar relación requisito-criterio",IF($M11="","Falta caso de prueba",IF(VLOOKUP($M11,'Casos y evidencias'!$A$6:$O$83,2,FALSE)<>$K11,"Revisar relación criterio-caso",IF($O11="Aprobado",IF($P11="","Falta evidencia","Trazabilidad completa"),IF($O11="Fallido","Prueba fallida",IF($O11="Bloqueado","Prueba bloqueada","Prueba pendiente")))))),"ID no encontrado"))) -> Prueba pendiente | C11: =IF($G11="","",IFERROR(IF(VLOOKUP($G11,Requerimientos!$A$6:$M$43,2,FALSE)="","",VLOOKUP($G11,Requerimientos!$A$6:$M$43,2,FALSE)),"ID no encontrado")) -> OBJ-001 | D11: =IF($C11="","",IFERROR(IF(VLOOKUP($C11,'Objetivos y procesos'!$A$6:$H$35,2,FALSE)="","",VLOOKUP($C11,'Objetivos y procesos'!$A$6:$H$35,2,FALSE)),"ID no encontrado")) -> Proteger la plataforma y asegurar que cada usuario opere con el perfil, empresa y vendedor correctos. | E11: =IF($G11="","",IFERROR(IF(VLOOKUP($G11,Requerimientos!$A$6:$M$43,3,FALSE)="","",VLOOKUP($G11,Requerimientos!$A$6:$M$43,3,FALSE)),"ID no encontrado")) -> PR-01 | F11: =IF($E11="","",IFERROR(IF(INDEX('Objetivos y procesos'!$D$6:$D$35,MATCH($E11,'Objetivos y procesos'!$C$6:$C$35,0))="","",IF(INDEX('Objetivos y procesos'!$D$6:$D$35,MATCH($E11,'Objetivos y procesos'!$C$6:$C$35,0))=INDEX('Objetivos y procesos'!$E$6:$E$35,MATCH($E11,'Objetivos y procesos'!$C$6:$C$35,0)),INDEX('Objetivos y procesos'!$D$6:$D$35,MATCH($E11,'Objetivos y procesos'!$C$6:$C$35,0)),INDEX('Objetivos y procesos'!$D$6:$D$35,MATCH($E11,'Objetivos y procesos'!$C$6:$C$35,0))&IF(INDEX('Objetivos y procesos'!$E$6:$E$35,MATCH($E11,'Objetivos y procesos'!$C$6:$C$35,0))="",""," / "&INDEX('Objetivos y procesos'!$E$6:$E$35,MATCH($E11,'Objetivos y procesos'!$C$6:$C$35,0))))),"ID no encontrado")) -> Gestión de usuarios, roles y permisos | G11: RF-02 | H11: =IF($G11="","",IFERROR(IF(VLOOKUP($G11,Requerimientos!$A$6:$M$43,7,FALSE)="","",VLOOKUP($G11,Requerimientos!$A$6:$M$43,7,FALSE)),"ID no encontrado")) -> El sistema debe permitir asignar a cada usuario un área, un cargo y un rol. | I11: =IF($K11="","",IFERROR(IF(VLOOKUP($K11,'Historias y criterios'!$A$6:$P$83,2,FALSE)="","",VLOOKUP($K11,'Historias y criterios'!$A$6:$P$83,2,FALSE)),"ID no encontrado")) -> HU-002 | J11: =IF($K11="","",IFERROR(IF(VLOOKUP($K11,'Historias y criterios'!$A$6:$P$83,10,FALSE)="","",VLOOKUP($K11,'Historias y criterios'!$A$6:$P$83,10,FALSE)),"ID no encontrado")) -> Como administrador, quiero crear, editar, desactivar y reactivar usuarios asignándoles área, cargo y rol, para mantener los accesos alineados con las responsabilidades de cada trabajador | K11: CA-004 | L11: =IF($K11="","",IFERROR(IF(VLOOKUP($K11,'Historias y criterios'!$A$6:$P$83,11,FALSE)="","",VLOOKUP($K11,'Historias y criterios'!$A$6:$P$83,11,FALSE)),"ID no encontrado")) -> El administrador crea y edita usuarios con área, cargo y rol obligatorios. | M11: CP-004 | N11: =IF($M11="","",IFERROR(IF(VLOOKUP($M11,'Casos y evidencias'!$A$6:$O$83,5,FALSE)="","",VLOOKUP($M11,'Casos y evidencias'!$A$6:$O$83,5,FALSE)),"ID no encontrado")) -> Creación y edición de usuario con área, cargo y rol | O11: =IF($M11="","",IFERROR(IF(VLOOKUP($M11,'Casos y evidencias'!$A$6:$O$83,10,FALSE)="","",VLOOKUP($M11,'Casos y evidencias'!$A$6:$O$83,10,FALSE)),"ID no encontrado")) -> No ejecutado | P11: =IF($M11="","",IFERROR(IF(VLOOKUP($M11,'Casos y evidencias'!$A$6:$O$83,11,FALSE)="","",VLOOKUP($M11,'Casos y evidencias'!$A$6:$O$83,11,FALSE)),"ID no encontrado")) | Q11: =IF($M11="","",IFERROR(IF(VLOOKUP($M11,'Casos y evidencias'!$A$6:$O$83,12,FALSE)="","",VLOOKUP($M11,'Casos y evidencias'!$A$6:$O$83,12,FALSE)),"ID no encontrado"))
A12: 5 | B12: =IF($G12="","",IF($K12="","Falta criterio",IFERROR(IF(VLOOKUP($K12,'Historias y criterios'!$A$6:$P$83,3,FALSE)<>$G12,"Revisar relación requisito-criterio",IF($M12="","Falta caso de prueba",IF(VLOOKUP($M12,'Casos y evidencias'!$A$6:$O$83,2,FALSE)<>$K12,"Revisar relación criterio-caso",IF($O12="Aprobado",IF($P12="","Falta evidencia","Trazabilidad completa"),IF($O12="Fallido","Prueba fallida",IF($O12="Bloqueado","Prueba bloqueada","Prueba pendiente")))))),"ID no encontrado"))) -> Prueba pendiente | C12: =IF($G12="","",IFERROR(IF(VLOOKUP($G12,Requerimientos!$A$6:$M$43,2,FALSE)="","",VLOOKUP($G12,Requerimientos!$A$6:$M$43,2,FALSE)),"ID no encontrado")) -> OBJ-001 | D12: =IF($C12="","",IFERROR(IF(VLOOKUP($C12,'Objetivos y procesos'!$A$6:$H$35,2,FALSE)="","",VLOOKUP($C12,'Objetivos y procesos'!$A$6:$H$35,2,FALSE)),"ID no encontrado")) -> Proteger la plataforma y asegurar que cada usuario opere con el perfil, empresa y vendedor correctos. | E12: =IF($G12="","",IFERROR(IF(VLOOKUP($G12,Requerimientos!$A$6:$M$43,3,FALSE)="","",VLOOKUP($G12,Requerimientos!$A$6:$M$43,3,FALSE)),"ID no encontrado")) -> PR-01 | F12: =IF($E12="","",IFERROR(IF(INDEX('Objetivos y procesos'!$D$6:$D$35,MATCH($E12,'Objetivos y procesos'!$C$6:$C$35,0))="","",IF(INDEX('Objetivos y procesos'!$D$6:$D$35,MATCH($E12,'Objetivos y procesos'!$C$6:$C$35,0))=INDEX('Objetivos y procesos'!$E$6:$E$35,MATCH($E12,'Objetivos y procesos'!$C$6:$C$35,0)),INDEX('Objetivos y procesos'!$D$6:$D$35,MATCH($E12,'Objetivos y procesos'!$C$6:$C$35,0)),INDEX('Objetivos y procesos'!$D$6:$D$35,MATCH($E12,'Objetivos y procesos'!$C$6:$C$35,0))&IF(INDEX('Objetivos y procesos'!$E$6:$E$35,MATCH($E12,'Objetivos y procesos'!$C$6:$C$35,0))="",""," / "&INDEX('Objetivos y procesos'!$E$6:$E$35,MATCH($E12,'Objetivos y procesos'!$C$6:$C$35,0))))),"ID no encontrado")) -> Gestión de usuarios, roles y permisos | G12: RF-04 | H12: =IF($G12="","",IFERROR(IF(VLOOKUP($G12,Requerimientos!$A$6:$M$43,7,FALSE)="","",VLOOKUP($G12,Requerimientos!$A$6:$M$43,7,FALSE)),"ID no encontrado")) -> El sistema debe permitir al administrador crear, editar, desactivar y reactivar usuarios. | I12: =IF($K12="","",IFERROR(IF(VLOOKUP($K12,'Historias y criterios'!$A$6:$P$83,2,FALSE)="","",VLOOKUP($K12,'Historias y criterios'!$A$6:$P$83,2,FALSE)),"ID no encontrado")) -> HU-002 | J12: =IF($K12="","",IFERROR(IF(VLOOKUP($K12,'Historias y criterios'!$A$6:$P$83,10,FALSE)="","",VLOOKUP($K12,'Historias y criterios'!$A$6:$P$83,10,FALSE)),"ID no encontrado")) -> Como administrador, quiero crear, editar, desactivar y reactivar usuarios asignándoles área, cargo y rol, para mantener los accesos alineados con las responsabilidades de cada trabajador | K12: CA-005 | L12: =IF($K12="","",IFERROR(IF(VLOOKUP($K12,'Historias y criterios'!$A$6:$P$83,11,FALSE)="","",VLOOKUP($K12,'Historias y criterios'!$A$6:$P$83,11,FALSE)),"ID no encontrado")) -> Un usuario se desactiva o reactiva sin eliminar su historial. | M12: CP-005 | N12: =IF($M12="","",IFERROR(IF(VLOOKUP($M12,'Casos y evidencias'!$A$6:$O$83,5,FALSE)="","",VLOOKUP($M12,'Casos y evidencias'!$A$6:$O$83,5,FALSE)),"ID no encontrado")) -> Desactivación y reactivación sin pérdida de historial | O12: =IF($M12="","",IFERROR(IF(VLOOKUP($M12,'Casos y evidencias'!$A$6:$O$83,10,FALSE)="","",VLOOKUP($M12,'Casos y evidencias'!$A$6:$O$83,10,FALSE)),"ID no encontrado")) -> No ejecutado | P12: =IF($M12="","",IFERROR(IF(VLOOKUP($M12,'Casos y evidencias'!$A$6:$O$83,11,FALSE)="","",VLOOKUP($M12,'Casos y evidencias'!$A$6:$O$83,11,FALSE)),"ID no encontrado")) | Q12: =IF($M12="","",IFERROR(IF(VLOOKUP($M12,'Casos y evidencias'!$A$6:$O$83,12,FALSE)="","",VLOOKUP($M12,'Casos y evidencias'!$A$6:$O$83,12,FALSE)),"ID no encontrado"))
A13: 6 | B13: =IF($G13="","",IF($K13="","Falta criterio",IFERROR(IF(VLOOKUP($K13,'Historias y criterios'!$A$6:$P$83,3,FALSE)<>$G13,"Revisar relación requisito-criterio",IF($M13="","Falta caso de prueba",IF(VLOOKUP($M13,'Casos y evidencias'!$A$6:$O$83,2,FALSE)<>$K13,"Revisar relación criterio-caso",IF($O13="Aprobado",IF($P13="","Falta evidencia","Trazabilidad completa"),IF($O13="Fallido","Prueba fallida",IF($O13="Bloqueado","Prueba bloqueada","Prueba pendiente")))))),"ID no encontrado"))) -> Prueba pendiente | C13: =IF($G13="","",IFERROR(IF(VLOOKUP($G13,Requerimientos!$A$6:$M$43,2,FALSE)="","",VLOOKUP($G13,Requerimientos!$A$6:$M$43,2,FALSE)),"ID no encontrado")) -> OBJ-001 | D13: =IF($C13="","",IFERROR(IF(VLOOKUP($C13,'Objetivos y procesos'!$A$6:$H$35,2,FALSE)="","",VLOOKUP($C13,'Objetivos y procesos'!$A$6:$H$35,2,FALSE)),"ID no encontrado")) -> Proteger la plataforma y asegurar que cada usuario opere con el perfil, empresa y vendedor correctos. | E13: =IF($G13="","",IFERROR(IF(VLOOKUP($G13,Requerimientos!$A$6:$M$43,3,FALSE)="","",VLOOKUP($G13,Requerimientos!$A$6:$M$43,3,FALSE)),"ID no encontrado")) -> PR-01 | F13: =IF($E13="","",IFERROR(IF(INDEX('Objetivos y procesos'!$D$6:$D$35,MATCH($E13,'Objetivos y procesos'!$C$6:$C$35,0))="","",IF(INDEX('Objetivos y procesos'!$D$6:$D$35,MATCH($E13,'Objetivos y procesos'!$C$6:$C$35,0))=INDEX('Objetivos y procesos'!$E$6:$E$35,MATCH($E13,'Objetivos y procesos'!$C$6:$C$35,0)),INDEX('Objetivos y procesos'!$D$6:$D$35,MATCH($E13,'Objetivos y procesos'!$C$6:$C$35,0)),INDEX('Objetivos y procesos'!$D$6:$D$35,MATCH($E13,'Objetivos y procesos'!$C$6:$C$35,0))&IF(INDEX('Objetivos y procesos'!$E$6:$E$35,MATCH($E13,'Objetivos y procesos'!$C$6:$C$35,0))="",""," / "&INDEX('Objetivos y procesos'!$E$6:$E$35,MATCH($E13,'Objetivos y procesos'!$C$6:$C$35,0))))),"ID no encontrado")) -> Gestión de usuarios, roles y permisos | G13: RF-04 | H13: =IF($G13="","",IFERROR(IF(VLOOKUP($G13,Requerimientos!$A$6:$M$43,7,FALSE)="","",VLOOKUP($G13,Requerimientos!$A$6:$M$43,7,FALSE)),"ID no encontrado")) -> El sistema debe permitir al administrador crear, editar, desactivar y reactivar usuarios. | I13: =IF($K13="","",IFERROR(IF(VLOOKUP($K13,'Historias y criterios'!$A$6:$P$83,2,FALSE)="","",VLOOKUP($K13,'Historias y criterios'!$A$6:$P$83,2,FALSE)),"ID no encontrado")) -> HU-002 | J13: =IF($K13="","",IFERROR(IF(VLOOKUP($K13,'Historias y criterios'!$A$6:$P$83,10,FALSE)="","",VLOOKUP($K13,'Historias y criterios'!$A$6:$P$83,10,FALSE)),"ID no encontrado")) -> Como administrador, quiero crear, editar, desactivar y reactivar usuarios asignándoles área, cargo y rol, para mantener los accesos alineados con las responsabilidades de cada trabajador | K13: CA-006 | L13: =IF($K13="","",IFERROR(IF(VLOOKUP($K13,'Historias y criterios'!$A$6:$P$83,11,FALSE)="","",VLOOKUP($K13,'Historias y criterios'!$A$6:$P$83,11,FALSE)),"ID no encontrado")) -> Solo el administrador puede ejecutar estas operaciones y un usuario desactivado no puede iniciar sesión. | M13: CP-006 | N13: =IF($M13="","",IFERROR(IF(VLOOKUP($M13,'Casos y evidencias'!$A$6:$O$83,5,FALSE)="","",VLOOKUP($M13,'Casos y evidencias'!$A$6:$O$83,5,FALSE)),"ID no encontrado")) -> Operaciones exclusivas del administrador | O13: =IF($M13="","",IFERROR(IF(VLOOKUP($M13,'Casos y evidencias'!$A$6:$O$83,10,FALSE)="","",VLOOKUP($M13,'Casos y evidencias'!$A$6:$O$83,10,FALSE)),"ID no encontrado")) -> No ejecutado | P13: =IF($M13="","",IFERROR(IF(VLOOKUP($M13,'Casos y evidencias'!$A$6:$O$83,11,FALSE)="","",VLOOKUP($M13,'Casos y evidencias'!$A$6:$O$83,11,FALSE)),"ID no encontrado")) | Q13: =IF($M13="","",IFERROR(IF(VLOOKUP($M13,'Casos y evidencias'!$A$6:$O$83,12,FALSE)="","",VLOOKUP($M13,'Casos y evidencias'!$A$6:$O$83,12,FALSE)),"ID no encontrado"))
A14: 7 | B14: =IF($G14="","",IF($K14="","Falta criterio",IFERROR(IF(VLOOKUP($K14,'Historias y criterios'!$A$6:$P$83,3,FALSE)<>$G14,"Revisar relación requisito-criterio",IF($M14="","Falta caso de prueba",IF(VLOOKUP($M14,'Casos y evidencias'!$A$6:$O$83,2,FALSE)<>$K14,"Revisar relación criterio-caso",IF($O14="Aprobado",IF($P14="","Falta evidencia","Trazabilidad completa"),IF($O14="Fallido","Prueba fallida",IF($O14="Bloqueado","Prueba bloqueada","Prueba pendiente")))))),"ID no encontrado"))) -> Prueba pendiente | C14: =IF($G14="","",IFERROR(IF(VLOOKUP($G14,Requerimientos!$A$6:$M$43,2,FALSE)="","",VLOOKUP($G14,Requerimientos!$A$6:$M$43,2,FALSE)),"ID no encontrado")) -> OBJ-001 | D14: =IF($C14="","",IFERROR(IF(VLOOKUP($C14,'Objetivos y procesos'!$A$6:$H$35,2,FALSE)="","",VLOOKUP($C14,'Objetivos y procesos'!$A$6:$H$35,2,FALSE)),"ID no encontrado")) -> Proteger la plataforma y asegurar que cada usuario opere con el perfil, empresa y vendedor correctos. | E14: =IF($G14="","",IFERROR(IF(VLOOKUP($G14,Requerimientos!$A$6:$M$43,3,FALSE)="","",VLOOKUP($G14,Requerimientos!$A$6:$M$43,3,FALSE)),"ID no encontrado")) -> PR-01 | F14: =IF($E14="","",IFERROR(IF(INDEX('Objetivos y procesos'!$D$6:$D$35,MATCH($E14,'Objetivos y procesos'!$C$6:$C$35,0))="","",IF(INDEX('Objetivos y procesos'!$D$6:$D$35,MATCH($E14,'Objetivos y procesos'!$C$6:$C$35,0))=INDEX('Objetivos y procesos'!$E$6:$E$35,MATCH($E14,'Objetivos y procesos'!$C$6:$C$35,0)),INDEX('Objetivos y procesos'!$D$6:$D$35,MATCH($E14,'Objetivos y procesos'!$C$6:$C$35,0)),INDEX('Objetivos y procesos'!$D$6:$D$35,MATCH($E14,'Objetivos y procesos'!$C$6:$C$35,0))&IF(INDEX('Objetivos y procesos'!$E$6:$E$35,MATCH($E14,'Objetivos y procesos'!$C$6:$C$35,0))="",""," / "&INDEX('Objetivos y procesos'!$E$6:$E$35,MATCH($E14,'Objetivos y procesos'!$C$6:$C$35,0))))),"ID no encontrado")) -> Gestión de usuarios, roles y permisos | G14: RF-03 | H14: =IF($G14="","",IFERROR(IF(VLOOKUP($G14,Requerimientos!$A$6:$M$43,7,FALSE)="","",VLOOKUP($G14,Requerimientos!$A$6:$M$43,7,FALSE)),"ID no encontrado")) -> El sistema debe restringir las funciones y los datos visibles según el rol, el área y el cargo del usuario. | I14: =IF($K14="","",IFERROR(IF(VLOOKUP($K14,'Historias y criterios'!$A$6:$P$83,2,FALSE)="","",VLOOKUP($K14,'Historias y criterios'!$A$6:$P$83,2,FALSE)),"ID no encontrado")) -> HU-003 | J14: =IF($K14="","",IFERROR(IF(VLOOKUP($K14,'Historias y criterios'!$A$6:$P$83,10,FALSE)="","",VLOOKUP($K14,'Historias y criterios'!$A$6:$P$83,10,FALSE)),"ID no encontrado")) -> Como administrador, quiero definir permisos por rol, área y cargo, además de grupos autorizadores por tipo de solicitud, para controlar qué funciones, datos y decisiones corresponden a cada usuario | K14: CA-007 | L14: =IF($K14="","",IFERROR(IF(VLOOKUP($K14,'Historias y criterios'!$A$6:$P$83,11,FALSE)="","",VLOOKUP($K14,'Historias y criterios'!$A$6:$P$83,11,FALSE)),"ID no encontrado")) -> Los permisos efectivos suman los permisos directos, del área y del cargo. | M14: CP-007 | N14: =IF($M14="","",IFERROR(IF(VLOOKUP($M14,'Casos y evidencias'!$A$6:$O$83,5,FALSE)="","",VLOOKUP($M14,'Casos y evidencias'!$A$6:$O$83,5,FALSE)),"ID no encontrado")) -> Cálculo de permisos efectivos | O14: =IF($M14="","",IFERROR(IF(VLOOKUP($M14,'Casos y evidencias'!$A$6:$O$83,10,FALSE)="","",VLOOKUP($M14,'Casos y evidencias'!$A$6:$O$83,10,FALSE)),"ID no encontrado")) -> No ejecutado | P14: =IF($M14="","",IFERROR(IF(VLOOKUP($M14,'Casos y evidencias'!$A$6:$O$83,11,FALSE)="","",VLOOKUP($M14,'Casos y evidencias'!$A$6:$O$83,11,FALSE)),"ID no encontrado")) | Q14: =IF($M14="","",IFERROR(IF(VLOOKUP($M14,'Casos y evidencias'!$A$6:$O$83,12,FALSE)="","",VLOOKUP($M14,'Casos y evidencias'!$A$6:$O$83,12,FALSE)),"ID no encontrado"))
A15: 8 | B15: =IF($G15="","",IF($K15="","Falta criterio",IFERROR(IF(VLOOKUP($K15,'Historias y criterios'!$A$6:$P$83,3,FALSE)<>$G15,"Revisar relación requisito-criterio",IF($M15="","Falta caso de prueba",IF(VLOOKUP($M15,'Casos y evidencias'!$A$6:$O$83,2,FALSE)<>$K15,"Revisar relación criterio-caso",IF($O15="Aprobado",IF($P15="","Falta evidencia","Trazabilidad completa"),IF($O15="Fallido","Prueba fallida",IF($O15="Bloqueado","Prueba bloqueada","Prueba pendiente")))))),"ID no encontrado"))) -> Prueba pendiente | C15: =IF($G15="","",IFERROR(IF(VLOOKUP($G15,Requerimientos!$A$6:$M$43,2,FALSE)="","",VLOOKUP($G15,Requerimientos!$A$6:$M$43,2,FALSE)),"ID no encontrado")) -> OBJ-001 | D15: =IF($C15="","",IFERROR(IF(VLOOKUP($C15,'Objetivos y procesos'!$A$6:$H$35,2,FALSE)="","",VLOOKUP($C15,'Objetivos y procesos'!$A$6:$H$35,2,FALSE)),"ID no encontrado")) -> Proteger la plataforma y asegurar que cada usuario opere con el perfil, empresa y vendedor correctos. | E15: =IF($G15="","",IFERROR(IF(VLOOKUP($G15,Requerimientos!$A$6:$M$43,3,FALSE)="","",VLOOKUP($G15,Requerimientos!$A$6:$M$43,3,FALSE)),"ID no encontrado")) -> PR-01 | F15: =IF($E15="","",IFERROR(IF(INDEX('Objetivos y procesos'!$D$6:$D$35,MATCH($E15,'Objetivos y procesos'!$C$6:$C$35,0))="","",IF(INDEX('Objetivos y procesos'!$D$6:$D$35,MATCH($E15,'Objetivos y procesos'!$C$6:$C$35,0))=INDEX('Objetivos y procesos'!$E$6:$E$35,MATCH($E15,'Objetivos y procesos'!$C$6:$C$35,0)),INDEX('Objetivos y procesos'!$D$6:$D$35,MATCH($E15,'Objetivos y procesos'!$C$6:$C$35,0)),INDEX('Objetivos y procesos'!$D$6:$D$35,MATCH($E15,'Objetivos y procesos'!$C$6:$C$35,0))&IF(INDEX('Objetivos y procesos'!$E$6:$E$35,MATCH($E15,'Objetivos y procesos'!$C$6:$C$35,0))="",""," / "&INDEX('Objetivos y procesos'!$E$6:$E$35,MATCH($E15,'Objetivos y procesos'!$C$6:$C$35,0))))),"ID no encontrado")) -> Gestión de usuarios, roles y permisos | G15: RF-03 | H15: =IF($G15="","",IFERROR(IF(VLOOKUP($G15,Requerimientos!$A$6:$M$43,7,FALSE)="","",VLOOKUP($G15,Requerimientos!$A$6:$M$43,7,FALSE)),"ID no encontrado")) -> El sistema debe restringir las funciones y los datos visibles según el rol, el área y el cargo del usuario. | I15: =IF($K15="","",IFERROR(IF(VLOOKUP($K15,'Historias y criterios'!$A$6:$P$83,2,FALSE)="","",VLOOKUP($K15,'Historias y criterios'!$A$6:$P$83,2,FALSE)),"ID no encontrado")) -> HU-003 | J15: =IF($K15="","",IFERROR(IF(VLOOKUP($K15,'Historias y criterios'!$A$6:$P$83,10,FALSE)="","",VLOOKUP($K15,'Historias y criterios'!$A$6:$P$83,10,FALSE)),"ID no encontrado")) -> Como administrador, quiero definir permisos por rol, área y cargo, además de grupos autorizadores por tipo de solicitud, para controlar qué funciones, datos y decisiones corresponden a cada usuario | K15: CA-008 | L15: =IF($K15="","",IFERROR(IF(VLOOKUP($K15,'Historias y criterios'!$A$6:$P$83,11,FALSE)="","",VLOOKUP($K15,'Historias y criterios'!$A$6:$P$83,11,FALSE)),"ID no encontrado")) -> Cada operación valida los permisos en el servidor. | M15: CP-008 | N15: =IF($M15="","",IFERROR(IF(VLOOKUP($M15,'Casos y evidencias'!$A$6:$O$83,5,FALSE)="","",VLOOKUP($M15,'Casos y evidencias'!$A$6:$O$83,5,FALSE)),"ID no encontrado")) -> Validación de permisos en el servidor | O15: =IF($M15="","",IFERROR(IF(VLOOKUP($M15,'Casos y evidencias'!$A$6:$O$83,10,FALSE)="","",VLOOKUP($M15,'Casos y evidencias'!$A$6:$O$83,10,FALSE)),"ID no encontrado")) -> No ejecutado | P15: =IF($M15="","",IFERROR(IF(VLOOKUP($M15,'Casos y evidencias'!$A$6:$O$83,11,FALSE)="","",VLOOKUP($M15,'Casos y evidencias'!$A$6:$O$83,11,FALSE)),"ID no encontrado")) | Q15: =IF($M15="","",IFERROR(IF(VLOOKUP($M15,'Casos y evidencias'!$A$6:$O$83,12,FALSE)="","",VLOOKUP($M15,'Casos y evidencias'!$A$6:$O$83,12,FALSE)),"ID no encontrado"))
A16: 9 | B16: =IF($G16="","",IF($K16="","Falta criterio",IFERROR(IF(VLOOKUP($K16,'Historias y criterios'!$A$6:$P$83,3,FALSE)<>$G16,"Revisar relación requisito-criterio",IF($M16="","Falta caso de prueba",IF(VLOOKUP($M16,'Casos y evidencias'!$A$6:$O$83,2,FALSE)<>$K16,"Revisar relación criterio-caso",IF($O16="Aprobado",IF($P16="","Falta evidencia","Trazabilidad completa"),IF($O16="Fallido","Prueba fallida",IF($O16="Bloqueado","Prueba bloqueada","Prueba pendiente")))))),"ID no encontrado"))) -> Prueba pendiente | C16: =IF($G16="","",IFERROR(IF(VLOOKUP($G16,Requerimientos!$A$6:$M$43,2,FALSE)="","",VLOOKUP($G16,Requerimientos!$A$6:$M$43,2,FALSE)),"ID no encontrado")) -> OBJ-001 | D16: =IF($C16="","",IFERROR(IF(VLOOKUP($C16,'Objetivos y procesos'!$A$6:$H$35,2,FALSE)="","",VLOOKUP($C16,'Objetivos y procesos'!$A$6:$H$35,2,FALSE)),"ID no encontrado")) -> Proteger la plataforma y asegurar que cada usuario opere con el perfil, empresa y vendedor correctos. | E16: =IF($G16="","",IFERROR(IF(VLOOKUP($G16,Requerimientos!$A$6:$M$43,3,FALSE)="","",VLOOKUP($G16,Requerimientos!$A$6:$M$43,3,FALSE)),"ID no encontrado")) -> PR-01 | F16: =IF($E16="","",IFERROR(IF(INDEX('Objetivos y procesos'!$D$6:$D$35,MATCH($E16,'Objetivos y procesos'!$C$6:$C$35,0))="","",IF(INDEX('Objetivos y procesos'!$D$6:$D$35,MATCH($E16,'Objetivos y procesos'!$C$6:$C$35,0))=INDEX('Objetivos y procesos'!$E$6:$E$35,MATCH($E16,'Objetivos y procesos'!$C$6:$C$35,0)),INDEX('Objetivos y procesos'!$D$6:$D$35,MATCH($E16,'Objetivos y procesos'!$C$6:$C$35,0)),INDEX('Objetivos y procesos'!$D$6:$D$35,MATCH($E16,'Objetivos y procesos'!$C$6:$C$35,0))&IF(INDEX('Objetivos y procesos'!$E$6:$E$35,MATCH($E16,'Objetivos y procesos'!$C$6:$C$35,0))="",""," / "&INDEX('Objetivos y procesos'!$E$6:$E$35,MATCH($E16,'Objetivos y procesos'!$C$6:$C$35,0))))),"ID no encontrado")) -> Gestión de usuarios, roles y permisos | G16: RF-29 | H16: =IF($G16="","",IFERROR(IF(VLOOKUP($G16,Requerimientos!$A$6:$M$43,7,FALSE)="","",VLOOKUP($G16,Requerimientos!$A$6:$M$43,7,FALSE)),"ID no encontrado")) -> El sistema debe permitir definir grupos de autorizadores por tipo de solicitud. | I16: =IF($K16="","",IFERROR(IF(VLOOKUP($K16,'Historias y criterios'!$A$6:$P$83,2,FALSE)="","",VLOOKUP($K16,'Historias y criterios'!$A$6:$P$83,2,FALSE)),"ID no encontrado")) -> HU-003 | J16: =IF($K16="","",IFERROR(IF(VLOOKUP($K16,'Historias y criterios'!$A$6:$P$83,10,FALSE)="","",VLOOKUP($K16,'Historias y criterios'!$A$6:$P$83,10,FALSE)),"ID no encontrado")) -> Como administrador, quiero definir permisos por rol, área y cargo, además de grupos autorizadores por tipo de solicitud, para controlar qué funciones, datos y decisiones corresponden a cada usuario | K16: CA-009 | L16: =IF($K16="","",IFERROR(IF(VLOOKUP($K16,'Historias y criterios'!$A$6:$P$83,11,FALSE)="","",VLOOKUP($K16,'Historias y criterios'!$A$6:$P$83,11,FALSE)),"ID no encontrado")) -> Es posible crear y modificar grupos por tipo de solicitud, siempre con al menos un integrante activo. | M16: CP-009 | N16: =IF($M16="","",IFERROR(IF(VLOOKUP($M16,'Casos y evidencias'!$A$6:$O$83,5,FALSE)="","",VLOOKUP($M16,'Casos y evidencias'!$A$6:$O$83,5,FALSE)),"ID no encontrado")) -> Gestión de grupos autorizadores por tipo de solicitud | O16: =IF($M16="","",IFERROR(IF(VLOOKUP($M16,'Casos y evidencias'!$A$6:$O$83,10,FALSE)="","",VLOOKUP($M16,'Casos y evidencias'!$A$6:$O$83,10,FALSE)),"ID no encontrado")) -> No ejecutado | P16: =IF($M16="","",IFERROR(IF(VLOOKUP($M16,'Casos y evidencias'!$A$6:$O$83,11,FALSE)="","",VLOOKUP($M16,'Casos y evidencias'!$A$6:$O$83,11,FALSE)),"ID no encontrado")) | Q16: =IF($M16="","",IFERROR(IF(VLOOKUP($M16,'Casos y evidencias'!$A$6:$O$83,12,FALSE)="","",VLOOKUP($M16,'Casos y evidencias'!$A$6:$O$83,12,FALSE)),"ID no encontrado"))
A17: 10 | B17: =IF($G17="","",IF($K17="","Falta criterio",IFERROR(IF(VLOOKUP($K17,'Historias y criterios'!$A$6:$P$83,3,FALSE)<>$G17,"Revisar relación requisito-criterio",IF($M17="","Falta caso de prueba",IF(VLOOKUP($M17,'Casos y evidencias'!$A$6:$O$83,2,FALSE)<>$K17,"Revisar relación criterio-caso",IF($O17="Aprobado",IF($P17="","Falta evidencia","Trazabilidad completa"),IF($O17="Fallido","Prueba fallida",IF($O17="Bloqueado","Prueba bloqueada","Prueba pendiente")))))),"ID no encontrado"))) -> Prueba pendiente | C17: =IF($G17="","",IFERROR(IF(VLOOKUP($G17,Requerimientos!$A$6:$M$43,2,FALSE)="","",VLOOKUP($G17,Requerimientos!$A$6:$M$43,2,FALSE)),"ID no encontrado")) -> OBJ-001 | D17: =IF($C17="","",IFERROR(IF(VLOOKUP($C17,'Objetivos y procesos'!$A$6:$H$35,2,FALSE)="","",VLOOKUP($C17,'Objetivos y procesos'!$A$6:$H$35,2,FALSE)),"ID no encontrado")) -> Proteger la plataforma y asegurar que cada usuario opere con el perfil, empresa y vendedor correctos. | E17: =IF($G17="","",IFERROR(IF(VLOOKUP($G17,Requerimientos!$A$6:$M$43,3,FALSE)="","",VLOOKUP($G17,Requerimientos!$A$6:$M$43,3,FALSE)),"ID no encontrado")) -> PR-01 | F17: =IF($E17="","",IFERROR(IF(INDEX('Objetivos y procesos'!$D$6:$D$35,MATCH($E17,'Objetivos y procesos'!$C$6:$C$35,0))="","",IF(INDEX('Objetivos y procesos'!$D$6:$D$35,MATCH($E17,'Objetivos y procesos'!$C$6:$C$35,0))=INDEX('Objetivos y procesos'!$E$6:$E$35,MATCH($E17,'Objetivos y procesos'!$C$6:$C$35,0)),INDEX('Objetivos y procesos'!$D$6:$D$35,MATCH($E17,'Objetivos y procesos'!$C$6:$C$35,0)),INDEX('Objetivos y procesos'!$D$6:$D$35,MATCH($E17,'Objetivos y procesos'!$C$6:$C$35,0))&IF(INDEX('Objetivos y procesos'!$E$6:$E$35,MATCH($E17,'Objetivos y procesos'!$C$6:$C$35,0))="",""," / "&INDEX('Objetivos y procesos'!$E$6:$E$35,MATCH($E17,'Objetivos y procesos'!$C$6:$C$35,0))))),"ID no encontrado")) -> Gestión de usuarios, roles y permisos | G17: RF-05 | H17: =IF($G17="","",IFERROR(IF(VLOOKUP($G17,Requerimientos!$A$6:$M$43,7,FALSE)="","",VLOOKUP($G17,Requerimientos!$A$6:$M$43,7,FALSE)),"ID no encontrado")) -> El sistema debe permitir al administrador definir y modificar los permisos asociados a cada rol, área y cargo. | I17: =IF($K17="","",IFERROR(IF(VLOOKUP($K17,'Historias y criterios'!$A$6:$P$83,2,FALSE)="","",VLOOKUP($K17,'Historias y criterios'!$A$6:$P$83,2,FALSE)),"ID no encontrado")) -> HU-003 | J17: =IF($K17="","",IFERROR(IF(VLOOKUP($K17,'Historias y criterios'!$A$6:$P$83,10,FALSE)="","",VLOOKUP($K17,'Historias y criterios'!$A$6:$P$83,10,FALSE)),"ID no encontrado")) -> Como administrador, quiero definir permisos por rol, área y cargo, además de grupos autorizadores por tipo de solicitud, para controlar qué funciones, datos y decisiones corresponden a cada usuario | K17: CA-010 | L17: =IF($K17="","",IFERROR(IF(VLOOKUP($K17,'Historias y criterios'!$A$6:$P$83,11,FALSE)="","",VLOOKUP($K17,'Historias y criterios'!$A$6:$P$83,11,FALSE)),"ID no encontrado")) -> Solo el administrador gestiona permisos y grupos. | M17: CP-010 | N17: =IF($M17="","",IFERROR(IF(VLOOKUP($M17,'Casos y evidencias'!$A$6:$O$83,5,FALSE)="","",VLOOKUP($M17,'Casos y evidencias'!$A$6:$O$83,5,FALSE)),"ID no encontrado")) -> Gestión de permisos exclusiva del administrador | O17: =IF($M17="","",IFERROR(IF(VLOOKUP($M17,'Casos y evidencias'!$A$6:$O$83,10,FALSE)="","",VLOOKUP($M17,'Casos y evidencias'!$A$6:$O$83,10,FALSE)),"ID no encontrado")) -> No ejecutado | P17: =IF($M17="","",IFERROR(IF(VLOOKUP($M17,'Casos y evidencias'!$A$6:$O$83,11,FALSE)="","",VLOOKUP($M17,'Casos y evidencias'!$A$6:$O$83,11,FALSE)),"ID no encontrado")) | Q17: =IF($M17="","",IFERROR(IF(VLOOKUP($M17,'Casos y evidencias'!$A$6:$O$83,12,FALSE)="","",VLOOKUP($M17,'Casos y evidencias'!$A$6:$O$83,12,FALSE)),"ID no encontrado"))
A18: 11 | B18: =IF($G18="","",IF($K18="","Falta criterio",IFERROR(IF(VLOOKUP($K18,'Historias y criterios'!$A$6:$P$83,3,FALSE)<>$G18,"Revisar relación requisito-criterio",IF($M18="","Falta caso de prueba",IF(VLOOKUP($M18,'Casos y evidencias'!$A$6:$O$83,2,FALSE)<>$K18,"Revisar relación criterio-caso",IF($O18="Aprobado",IF($P18="","Falta evidencia","Trazabilidad completa"),IF($O18="Fallido","Prueba fallida",IF($O18="Bloqueado","Prueba bloqueada","Prueba pendiente")))))),"ID no encontrado"))) -> Prueba pendiente | C18: =IF($G18="","",IFERROR(IF(VLOOKUP($G18,Requerimientos!$A$6:$M$43,2,FALSE)="","",VLOOKUP($G18,Requerimientos!$A$6:$M$43,2,FALSE)),"ID no encontrado")) -> OBJ-001 | D18: =IF($C18="","",IFERROR(IF(VLOOKUP($C18,'Objetivos y procesos'!$A$6:$H$35,2,FALSE)="","",VLOOKUP($C18,'Objetivos y procesos'!$A$6:$H$35,2,FALSE)),"ID no encontrado")) -> Proteger la plataforma y asegurar que cada usuario opere con el perfil, empresa y vendedor correctos. | E18: =IF($G18="","",IFERROR(IF(VLOOKUP($G18,Requerimientos!$A$6:$M$43,3,FALSE)="","",VLOOKUP($G18,Requerimientos!$A$6:$M$43,3,FALSE)),"ID no encontrado")) -> PR-01 | F18: =IF($E18="","",IFERROR(IF(INDEX('Objetivos y procesos'!$D$6:$D$35,MATCH($E18,'Objetivos y procesos'!$C$6:$C$35,0))="","",IF(INDEX('Objetivos y procesos'!$D$6:$D$35,MATCH($E18,'Objetivos y procesos'!$C$6:$C$35,0))=INDEX('Objetivos y procesos'!$E$6:$E$35,MATCH($E18,'Objetivos y procesos'!$C$6:$C$35,0)),INDEX('Objetivos y procesos'!$D$6:$D$35,MATCH($E18,'Objetivos y procesos'!$C$6:$C$35,0)),INDEX('Objetivos y procesos'!$D$6:$D$35,MATCH($E18,'Objetivos y procesos'!$C$6:$C$35,0))&IF(INDEX('Objetivos y procesos'!$E$6:$E$35,MATCH($E18,'Objetivos y procesos'!$C$6:$C$35,0))="",""," / "&INDEX('Objetivos y procesos'!$E$6:$E$35,MATCH($E18,'Objetivos y procesos'!$C$6:$C$35,0))))),"ID no encontrado")) -> Gestión de usuarios, roles y permisos | G18: RF-35 | H18: =IF($G18="","",IFERROR(IF(VLOOKUP($G18,Requerimientos!$A$6:$M$43,7,FALSE)="","",VLOOKUP($G18,Requerimientos!$A$6:$M$43,7,FALSE)),"ID no encontrado")) -> El sistema debe permitir asociar a cada usuario, sea vendedor o asistente de vendedor, uno o más códigos de vendedor de SAP (SlpCode), cada uno vinculado a su empresa: Ferretería Marsella o Asland. | I18: =IF($K18="","",IFERROR(IF(VLOOKUP($K18,'Historias y criterios'!$A$6:$P$83,2,FALSE)="","",VLOOKUP($K18,'Historias y criterios'!$A$6:$P$83,2,FALSE)),"ID no encontrado")) -> HU-004 | J18: =IF($K18="","",IFERROR(IF(VLOOKUP($K18,'Historias y criterios'!$A$6:$P$83,10,FALSE)="","",VLOOKUP($K18,'Historias y criterios'!$A$6:$P$83,10,FALSE)),"ID no encontrado")) -> Como administrador, quiero asociar SlpCode y escala de comisión por empresa a vendedores y asistentes, para asegurar que cada operación use la empresa y el vendedor correctos | K18: CA-011 | L18: =IF($K18="","",IFERROR(IF(VLOOKUP($K18,'Historias y criterios'!$A$6:$P$83,11,FALSE)="","",VLOOKUP($K18,'Historias y criterios'!$A$6:$P$83,11,FALSE)),"ID no encontrado")) -> Cada SlpCode queda asociado a Marsella o Asland y a los usuarios autorizados. | M18: CP-011 | N18: =IF($M18="","",IFERROR(IF(VLOOKUP($M18,'Casos y evidencias'!$A$6:$O$83,5,FALSE)="","",VLOOKUP($M18,'Casos y evidencias'!$A$6:$O$83,5,FALSE)),"ID no encontrado")) -> Asociación de SlpCode por empresa | O18: =IF($M18="","",IFERROR(IF(VLOOKUP($M18,'Casos y evidencias'!$A$6:$O$83,10,FALSE)="","",VLOOKUP($M18,'Casos y evidencias'!$A$6:$O$83,10,FALSE)),"ID no encontrado")) -> No ejecutado | P18: =IF($M18="","",IFERROR(IF(VLOOKUP($M18,'Casos y evidencias'!$A$6:$O$83,11,FALSE)="","",VLOOKUP($M18,'Casos y evidencias'!$A$6:$O$83,11,FALSE)),"ID no encontrado")) | Q18: =IF($M18="","",IFERROR(IF(VLOOKUP($M18,'Casos y evidencias'!$A$6:$O$83,12,FALSE)="","",VLOOKUP($M18,'Casos y evidencias'!$A$6:$O$83,12,FALSE)),"ID no encontrado"))
A19: 12 | B19: =IF($G19="","",IF($K19="","Falta criterio",IFERROR(IF(VLOOKUP($K19,'Historias y criterios'!$A$6:$P$83,3,FALSE)<>$G19,"Revisar relación requisito-criterio",IF($M19="","Falta caso de prueba",IF(VLOOKUP($M19,'Casos y evidencias'!$A$6:$O$83,2,FALSE)<>$K19,"Revisar relación criterio-caso",IF($O19="Aprobado",IF($P19="","Falta evidencia","Trazabilidad completa"),IF($O19="Fallido","Prueba fallida",IF($O19="Bloqueado","Prueba bloqueada","Prueba pendiente")))))),"ID no encontrado"))) -> Prueba pendiente | C19: =IF($G19="","",IFERROR(IF(VLOOKUP($G19,Requerimientos!$A$6:$M$43,2,FALSE)="","",VLOOKUP($G19,Requerimientos!$A$6:$M$43,2,FALSE)),"ID no encontrado")) -> OBJ-003 | D19: =IF($C19="","",IFERROR(IF(VLOOKUP($C19,'Objetivos y procesos'!$A$6:$H$35,2,FALSE)="","",VLOOKUP($C19,'Objetivos y procesos'!$A$6:$H$35,2,FALSE)),"ID no encontrado")) -> Centralizar consultas, cotizaciones y órdenes de venta, aplicando vendedor, comisión, autorización e integración correctos. | E19: =IF($G19="","",IFERROR(IF(VLOOKUP($G19,Requerimientos!$A$6:$M$43,3,FALSE)="","",VLOOKUP($G19,Requerimientos!$A$6:$M$43,3,FALSE)),"ID no encontrado")) -> PR-03 | F19: =IF($E19="","",IFERROR(IF(INDEX('Objetivos y procesos'!$D$6:$D$35,MATCH($E19,'Objetivos y procesos'!$C$6:$C$35,0))="","",IF(INDEX('Objetivos y procesos'!$D$6:$D$35,MATCH($E19,'Objetivos y procesos'!$C$6:$C$35,0))=INDEX('Objetivos y procesos'!$E$6:$E$35,MATCH($E19,'Objetivos y procesos'!$C$6:$C$35,0)),INDEX('Objetivos y procesos'!$D$6:$D$35,MATCH($E19,'Objetivos y procesos'!$C$6:$C$35,0)),INDEX('Objetivos y procesos'!$D$6:$D$35,MATCH($E19,'Objetivos y procesos'!$C$6:$C$35,0))&IF(INDEX('Objetivos y procesos'!$E$6:$E$35,MATCH($E19,'Objetivos y procesos'!$C$6:$C$35,0))="",""," / "&INDEX('Objetivos y procesos'!$E$6:$E$35,MATCH($E19,'Objetivos y procesos'!$C$6:$C$35,0))))),"ID no encontrado")) -> Gestión comercial, cotizaciones y órdenes de venta | G19: RF-36 | H19: =IF($G19="","",IFERROR(IF(VLOOKUP($G19,Requerimientos!$A$6:$M$43,7,FALSE)="","",VLOOKUP($G19,Requerimientos!$A$6:$M$43,7,FALSE)),"ID no encontrado")) -> El sistema debe permitir al administrador asignar a cada código de vendedor, al editar su perfil, la escala de comisión con que se calcula su comisión. | I19: =IF($K19="","",IFERROR(IF(VLOOKUP($K19,'Historias y criterios'!$A$6:$P$83,2,FALSE)="","",VLOOKUP($K19,'Historias y criterios'!$A$6:$P$83,2,FALSE)),"ID no encontrado")) -> HU-004 | J19: =IF($K19="","",IFERROR(IF(VLOOKUP($K19,'Historias y criterios'!$A$6:$P$83,10,FALSE)="","",VLOOKUP($K19,'Historias y criterios'!$A$6:$P$83,10,FALSE)),"ID no encontrado")) -> Como administrador, quiero asociar SlpCode y escala de comisión por empresa a vendedores y asistentes, para asegurar que cada operación use la empresa y el vendedor correctos | K19: CA-012 | L19: =IF($K19="","",IFERROR(IF(VLOOKUP($K19,'Historias y criterios'!$A$6:$P$83,11,FALSE)="","",VLOOKUP($K19,'Historias y criterios'!$A$6:$P$83,11,FALSE)),"ID no encontrado")) -> Se asigna una escala de comisión o se usa la escala predeterminada. | M19: CP-012 | N19: =IF($M19="","",IFERROR(IF(VLOOKUP($M19,'Casos y evidencias'!$A$6:$O$83,5,FALSE)="","",VLOOKUP($M19,'Casos y evidencias'!$A$6:$O$83,5,FALSE)),"ID no encontrado")) -> Asignación de escala de comisión | O19: =IF($M19="","",IFERROR(IF(VLOOKUP($M19,'Casos y evidencias'!$A$6:$O$83,10,FALSE)="","",VLOOKUP($M19,'Casos y evidencias'!$A$6:$O$83,10,FALSE)),"ID no encontrado")) -> No ejecutado | P19: =IF($M19="","",IFERROR(IF(VLOOKUP($M19,'Casos y evidencias'!$A$6:$O$83,11,FALSE)="","",VLOOKUP($M19,'Casos y evidencias'!$A$6:$O$83,11,FALSE)),"ID no encontrado")) | Q19: =IF($M19="","",IFERROR(IF(VLOOKUP($M19,'Casos y evidencias'!$A$6:$O$83,12,FALSE)="","",VLOOKUP($M19,'Casos y evidencias'!$A$6:$O$83,12,FALSE)),"ID no encontrado"))
... A85: 78 | B85: =IF($G85="","",IF($K85="","Falta criterio",IFERROR(IF(VLOOKUP($K85,'Historias y criterios'!$A$6:$P$83,3,FALSE)<>$G85,"Revisar relación requisito-criterio",IF($M85="","Falta caso de prueba",IF(VLOOKUP($M85,'Casos y evidencias'!$A$6:$O$83,2,FALSE)<>$K85,"Revisar relación criterio-caso",IF($O85="Aprobado",IF($P85="","Falta evidencia","Trazabilidad completa"),IF($O85="Fallido","Prueba fallida",IF($O85="Bloqueado","Prueba bloqueada","Prueba pendiente")))))),"ID no encontrado"))) -> Prueba pendiente | C85: =IF($G85="","",IFERROR(IF(VLOOKUP($G85,Requerimientos!$A$6:$M$43,2,FALSE)="","",VLOOKUP($G85,Requerimientos!$A$6:$M$43,2,FALSE)),"ID no encontrado")) -> OBJ-006 | D85: =IF($C85="","",IFERROR(IF(VLOOKUP($C85,'Objetivos y procesos'!$A$6:$H$35,2,FALSE)="","",VLOOKUP($C85,'Objetivos y procesos'!$A$6:$H$35,2,FALSE)),"ID no encontrado")) -> Centralizar la posventa y ofrecer visibilidad de cada caso, comprobante y decisión a los participantes autorizados. | E85: =IF($G85="","",IFERROR(IF(VLOOKUP($G85,Requerimientos!$A$6:$M$43,3,FALSE)="","",VLOOKUP($G85,Requerimientos!$A$6:$M$43,3,FALSE)),"ID no encontrado")) -> PR-06 | F85: =IF($E85="","",IFERROR(IF(INDEX('Objetivos y procesos'!$D$6:$D$35,MATCH($E85,'Objetivos y procesos'!$C$6:$C$35,0))="","",IF(INDEX('Objetivos y procesos'!$D$6:$D$35,MATCH($E85,'Objetivos y procesos'!$C$6:$C$35,0))=INDEX('Objetivos y procesos'!$E$6:$E$35,MATCH($E85,'Objetivos y procesos'!$C$6:$C$35,0)),INDEX('Objetivos y procesos'!$D$6:$D$35,MATCH($E85,'Objetivos y procesos'!$C$6:$C$35,0)),INDEX('Objetivos y procesos'!$D$6:$D$35,MATCH($E85,'Objetivos y procesos'!$C$6:$C$35,0))&IF(INDEX('Objetivos y procesos'!$E$6:$E$35,MATCH($E85,'Objetivos y procesos'!$C$6:$C$35,0))="",""," / "&INDEX('Objetivos y procesos'!$E$6:$E$35,MATCH($E85,'Objetivos y procesos'!$C$6:$C$35,0))))),"ID no encontrado")) -> Gestión de Posventa | G85: RF-34 | H85: =IF($G85="","",IFERROR(IF(VLOOKUP($G85,Requerimientos!$A$6:$M$43,7,FALSE)="","",VLOOKUP($G85,Requerimientos!$A$6:$M$43,7,FALSE)),"ID no encontrado")) -> El sistema debe permitir al autorizador de posventa cerrar un caso, registrando su resolución final. | I85: =IF($K85="","",IFERROR(IF(VLOOKUP($K85,'Historias y criterios'!$A$6:$P$83,2,FALSE)="","",VLOOKUP($K85,'Historias y criterios'!$A$6:$P$83,2,FALSE)),"ID no encontrado")) -> HU-020 | J85: =IF($K85="","",IFERROR(IF(VLOOKUP($K85,'Historias y criterios'!$A$6:$P$83,10,FALSE)="","",VLOOKUP($K85,'Historias y criterios'!$A$6:$P$83,10,FALSE)),"ID no encontrado")) -> Como autorizador de posventa, quiero actualizar el caso por sus estados y registrar su resolución final, para mantener el seguimiento hasta un cierre controlado | K85: CA-078 | L85: =IF($K85="","",IFERROR(IF(VLOOKUP($K85,'Historias y criterios'!$A$6:$P$83,11,FALSE)="","",VLOOKUP($K85,'Historias y criterios'!$A$6:$P$83,11,FALSE)),"ID no encontrado")) -> Solo el autorizador cierra el caso; un caso cerrado no acepta nuevos cambios. | M85: CP-078 | N85: =IF($M85="","",IFERROR(IF(VLOOKUP($M85,'Casos y evidencias'!$A$6:$O$83,5,FALSE)="","",VLOOKUP($M85,'Casos y evidencias'!$A$6:$O$83,5,FALSE)),"ID no encontrado")) -> Cierre exclusivo y bloqueo posterior | O85: =IF($M85="","",IFERROR(IF(VLOOKUP($M85,'Casos y evidencias'!$A$6:$O$83,10,FALSE)="","",VLOOKUP($M85,'Casos y evidencias'!$A$6:$O$83,10,FALSE)),"ID no encontrado")) -> No ejecutado | P85: =IF($M85="","",IFERROR(IF(VLOOKUP($M85,'Casos y evidencias'!$A$6:$O$83,11,FALSE)="","",VLOOKUP($M85,'Casos y evidencias'!$A$6:$O$83,11,FALSE)),"ID no encontrado")) | Q85: =IF($M85="","",IFERROR(IF(VLOOKUP($M85,'Casos y evidencias'!$A$6:$O$83,12,FALSE)="","",VLOOKUP($M85,'Casos y evidencias'!$A$6:$O$83,12,FALSE)),"ID no encontrado"))

Sheet Objetivos y procesos
A2: Objetivos y procesos
A4: Relacione cada objetivo del proyecto con un proceso AS-IS o TO-BE. Puede repetir un proceso en varias filas si lo necesita.
A5: ID Objetivo | B5: Objetivo | C5: ID Proceso | D5: Proceso | E5: Módulo | F5: Indicador / Resultado esperado | G5: Responsable | H5: Estado
A6: OBJ-001 | B6: Proteger la plataforma y asegurar que cada usuario opere con el perfil, empresa y vendedor correctos. | C6: PR-01 | D6: Gestión de usuarios, roles y permisos | E6: Gestión de usuarios, roles y permisos | F6: HU-001 a HU-004 aceptadas; permisos validados en servidor y trazabilidad de accesos comprobada. | G6: Matías y Alexssander | H6: En revisión
A7: OBJ-002 | B7: Reducir reprocesos y hacer visible la creación, activación o modificación de artículos desde su envío hasta la resolución. | C7: PR-02 | D7: Solicitudes y autorizaciones | E7: Solicitudes y autorizaciones | F7: HU-005 a HU-007 aceptadas; estados, reglas de adjuntos, permisos y resolución trazable verificados. | G7: Millaray y Matías | H7: En revisión
A8: OBJ-003 | B8: Centralizar consultas, cotizaciones y órdenes de venta, aplicando vendedor, comisión, autorización e integración correctos. | C8: PR-03 | D8: Gestión comercial, cotizaciones y órdenes de venta | E8: Gestión comercial, cotizaciones y órdenes de venta | F8: HU-008 a HU-011 aceptadas; documentos y restricciones comerciales probados de extremo a extremo. | G8: Alexssander y Millaray | H8: En revisión
A9: OBJ-004 | B9: Entregar avisos oportunos y una trazabilidad común para todos los procesos incorporados. | C9: PR-04 | D9: Notificaciones y trazabilidad | E9: Notificaciones y trazabilidad | F9: HU-012 a HU-014 aceptadas; privacidad, recordatorios e historial verificados en los procesos integrados. | G9: Millaray y Matías | H9: En revisión
A10: OBJ-005 | B10: Canalizar lecturas por API sobre HANA y escrituras autorizadas por Service Layer sin duplicidad ni operaciones parciales. | C10: PR-05 | D10: Integración con SAP Business One | E10: Integración con SAP Business One | F10: HU-015 a HU-017 aceptadas; seguridad, rendimiento, integridad e idempotencia comprobados. | G10: Alexssander y Matías | H10: En revisión
A11: OBJ-006 | B11: Centralizar la posventa y ofrecer visibilidad de cada caso, comprobante y decisión a los participantes autorizados. | C11: PR-06 | D11: Gestión de Posventa | E11: Gestión de Posventa | F11: HU-018 a HU-020 aceptadas; rutas por guía o factura, QR, permisos, notificaciones y cierre verificados. | G11: Millaray y Alexssander | H11: En revisión
A12: OBJ-007 | H12: Borrador
A13: OBJ-008 | H13: Borrador
A14: OBJ-009 | H14: Borrador
A15: OBJ-010 | H15: Borrador
A16: OBJ-011 | H16: Borrador
A17: OBJ-012 | H17: Borrador
A18: OBJ-013 | H18: Borrador
A19: OBJ-014 | H19: Borrador
A20: OBJ-015 | H20: Borrador
A21: OBJ-016 | H21: Borrador
A22: OBJ-017 | H22: Borrador
A23: OBJ-018 | H23: Borrador
... A35: OBJ-030 | H35: Borrador

Sheet Requerimientos
A2: Requerimientos
A4: Registre cada requerimiento y vincúlelo con su objetivo y proceso mediante los códigos correspondientes.
A5: ID Requerimiento | B5: ID Objetivo | C5: ID Proceso | D5: Tipo | E5: Módulo | F5: Nombre corto | G5: Descripción | H5: Fuente | I5: Prioridad | J5: Dependencias | K5: Estado | L5: Responsable | M5: Versión
A6: RF-01 | B6: OBJ-001 | C6: PR-01 | D6: Funcional | E6: =IF(C6="","",IFERROR(IF(INDEX('Objetivos y procesos'!$E$6:$E$35,MATCH(C6,'Objetivos y procesos'!$C$6:$C$35,0))="","",INDEX('Objetivos y procesos'!$E$6:$E$35,MATCH(C6,'Objetivos y procesos'!$C$6:$C$35,0))),"ID no encontrado")) -> Gestión de usuarios, roles y permisos | F6: Autenticación de usuarios | G6: El sistema debe permitir que un usuario se autentique mediante usuario y contraseña. | H6: ERS v2.0 (Doc. 9) · Carta 7.1 | I6: Alta | J6: RN-02 · RNF-01, RNF-04, RNF-05 | K6: En análisis | L6: Matías y Alexssander | M6: 2.0
A7: RF-02 | B7: OBJ-001 | C7: PR-01 | D7: Funcional | E7: =IF(C7="","",IFERROR(IF(INDEX('Objetivos y procesos'!$E$6:$E$35,MATCH(C7,'Objetivos y procesos'!$C$6:$C$35,0))="","",INDEX('Objetivos y procesos'!$E$6:$E$35,MATCH(C7,'Objetivos y procesos'!$C$6:$C$35,0))),"ID no encontrado")) -> Gestión de usuarios, roles y permisos | F7: Asignación de área, cargo y rol | G7: El sistema debe permitir asignar a cada usuario un área, un cargo y un rol. | H7: ERS v2.0 (Doc. 9) · Carta 7.1 | I7: Alta | J7: RN-01 | K7: En análisis | L7: Matías y Alexssander | M7: 2.0
A8: RF-03 | B8: OBJ-001 | C8: PR-01 | D8: Funcional | E8: =IF(C8="","",IFERROR(IF(INDEX('Objetivos y procesos'!$E$6:$E$35,MATCH(C8,'Objetivos y procesos'!$C$6:$C$35,0))="","",INDEX('Objetivos y procesos'!$E$6:$E$35,MATCH(C8,'Objetivos y procesos'!$C$6:$C$35,0))),"ID no encontrado")) -> Gestión de usuarios, roles y permisos | F8: Restricción por rol, área y cargo | G8: El sistema debe restringir las funciones y los datos visibles según el rol, el área y el cargo del usuario. | H8: ERS v2.0 (Doc. 9) · Carta 7.1 | I8: Alta | J8: RN-03 · RNF-02 | K8: En análisis | L8: Matías y Alexssander | M8: 2.0
A9: RF-04 | B9: OBJ-001 | C9: PR-01 | D9: Funcional | E9: =IF(C9="","",IFERROR(IF(INDEX('Objetivos y procesos'!$E$6:$E$35,MATCH(C9,'Objetivos y procesos'!$C$6:$C$35,0))="","",INDEX('Objetivos y procesos'!$E$6:$E$35,MATCH(C9,'Objetivos y procesos'!$C$6:$C$35,0))),"ID no encontrado")) -> Gestión de usuarios, roles y permisos | F9: Administración de usuarios | G9: El sistema debe permitir al administrador crear, editar, desactivar y reactivar usuarios. | H9: ERS v2.0 (Doc. 9) · Carta 7.1 | I9: Alta | J9: RN-02, RN-04 | K9: En análisis | L9: Matías y Alexssander | M9: 2.0
A10: RF-05 | B10: OBJ-001 | C10: PR-01 | D10: Funcional | E10: =IF(C10="","",IFERROR(IF(INDEX('Objetivos y procesos'!$E$6:$E$35,MATCH(C10,'Objetivos y procesos'!$C$6:$C$35,0))="","",INDEX('Objetivos y procesos'!$E$6:$E$35,MATCH(C10,'Objetivos y procesos'!$C$6:$C$35,0))),"ID no encontrado")) -> Gestión de usuarios, roles y permisos | F10: Definición de permisos | G10: El sistema debe permitir al administrador definir y modificar los permisos asociados a cada rol, área y cargo. | H10: ERS v2.0 (Doc. 9) · Carta 7.1 | I10: Media | J10: RN-03, RN-04 · RNF-02 | K10: En análisis | L10: Matías y Alexssander | M10: 2.0
A11: RF-06 | B11: OBJ-002 | C11: PR-02 | D11: Funcional | E11: =IF(C11="","",IFERROR(IF(INDEX('Objetivos y procesos'!$E$6:$E$35,MATCH(C11,'Objetivos y procesos'!$C$6:$C$35,0))="","",INDEX('Objetivos y procesos'!$E$6:$E$35,MATCH(C11,'Objetivos y procesos'!$C$6:$C$35,0))),"ID no encontrado")) -> Solicitudes y autorizaciones | F11: Creación y envío de solicitud de código | G11: El sistema debe permitir al usuario con permiso de enviar solicitudes de código crear una solicitud de creación, activación o modificación de códigos de producto y enviarla a revisión del grupo autorizador correspondiente. | H11: ERS v2.0 (Doc. 9) · Carta 7.2 | I11: Alta | J11: RN-06, RN-07, RN-11 | K11: En análisis | L11: Millaray y Matías | M11: 2.0
A12: RF-07 | B12: OBJ-002 | C12: PR-02 | D12: Funcional | E12: =IF(C12="","",IFERROR(IF(INDEX('Objetivos y procesos'!$E$6:$E$35,MATCH(C12,'Objetivos y procesos'!$C$6:$C$35,0))="","",INDEX('Objetivos y procesos'!$E$6:$E$35,MATCH(C12,'Objetivos y procesos'!$C$6:$C$35,0))),"ID no encontrado")) -> Solicitudes y autorizaciones | F12: Aprobación o rechazo de solicitudes | G12: El sistema debe permitir al autorizador aprobar o rechazar una solicitud, registrando el motivo cuando la rechaza. | H12: ERS v2.0 (Doc. 9) · Carta 7.2 | I12: Alta | J12: RN-07, RN-08, RN-10 · RNF-14 | K12: En análisis | L12: Millaray y Matías | M12: 2.0
A13: RF-08 | B13: OBJ-002 | C13: PR-02 | D13: Funcional | E13: =IF(C13="","",IFERROR(IF(INDEX('Objetivos y procesos'!$E$6:$E$35,MATCH(C13,'Objetivos y procesos'!$C$6:$C$35,0))="","",INDEX('Objetivos y procesos'!$E$6:$E$35,MATCH(C13,'Objetivos y procesos'!$C$6:$C$35,0))),"ID no encontrado")) -> Solicitudes y autorizaciones | F13: Corrección y reenvío de solicitudes | G13: El sistema debe permitir al vendedor corregir y reenviar una solicitud rechazada por el autorizador. | H13: ERS v2.0 (Doc. 9) · Carta 7.2 | I13: Alta | J13: RN-08, RN-09 | K13: En análisis | L13: Millaray y Matías | M13: 2.0
A14: RF-09 | B14: OBJ-002 | C14: PR-02 | D14: Funcional | E14: =IF(C14="","",IFERROR(IF(INDEX('Objetivos y procesos'!$E$6:$E$35,MATCH(C14,'Objetivos y procesos'!$C$6:$C$35,0))="","",INDEX('Objetivos y procesos'!$E$6:$E$35,MATCH(C14,'Objetivos y procesos'!$C$6:$C$35,0))),"ID no encontrado")) -> Solicitudes y autorizaciones | F14: Consulta del estado de solicitudes | G14: El sistema debe permitir consultar el estado actual, el responsable, la fecha de respuesta y el comentario de cada solicitud. | H14: ERS v2.0 (Doc. 9) · Carta 7.2 | I14: Alta | J14: RN-09, RN-10 | K14: En análisis | L14: Millaray y Matías | M14: 2.0
A15: RF-10 | B15: OBJ-002 | C15: PR-02 | D15: Funcional | E15: =IF(C15="","",IFERROR(IF(INDEX('Objetivos y procesos'!$E$6:$E$35,MATCH(C15,'Objetivos y procesos'!$C$6:$C$35,0))="","",INDEX('Objetivos y procesos'!$E$6:$E$35,MATCH(C15,'Objetivos y procesos'!$C$6:$C$35,0))),"ID no encontrado")) -> Solicitudes y autorizaciones | F15: Filtro y búsqueda de solicitudes | G15: El sistema debe permitir filtrar y buscar solicitudes por estado, fecha, área y responsable. | H15: ERS v2.0 (Doc. 9) · Carta 7.2 | I15: Media | J15: RNF-02 | K15: En análisis | L15: Millaray y Matías | M15: 2.0
A16: RF-11 | B16: OBJ-003 | C16: PR-03 | D16: Funcional | E16: =IF(C16="","",IFERROR(IF(INDEX('Objetivos y procesos'!$E$6:$E$35,MATCH(C16,'Objetivos y procesos'!$C$6:$C$35,0))="","",INDEX('Objetivos y procesos'!$E$6:$E$35,MATCH(C16,'Objetivos y procesos'!$C$6:$C$35,0))),"ID no encontrado")) -> Gestión comercial, cotizaciones y órdenes de venta | F16: Consulta de productos y stock | G16: El sistema debe permitir consultar el catálogo de productos con su disponibilidad de stock. | H16: ERS v2.0 (Doc. 9) · Carta 7.3 | I16: Alta | J16: RN-16, RN-17 · RNF-07, RNF-13 | K16: En análisis | L16: Alexssander y Millaray | M16: 2.0
A17: RF-12 | B17: OBJ-003 | C17: PR-03 | D17: Funcional | E17: =IF(C17="","",IFERROR(IF(INDEX('Objetivos y procesos'!$E$6:$E$35,MATCH(C17,'Objetivos y procesos'!$C$6:$C$35,0))="","",INDEX('Objetivos y procesos'!$E$6:$E$35,MATCH(C17,'Objetivos y procesos'!$C$6:$C$35,0))),"ID no encontrado")) -> Gestión comercial, cotizaciones y órdenes de venta | F17: Consulta de clientes, crédito y bloqueo | G17: El sistema debe permitir consultar los datos del cliente, incluidos su crédito disponible y su estado de bloqueo. | H17: ERS v2.0 (Doc. 9) · Carta 7.3 | I17: Alta | J17: RN-13, RN-16, RN-17 · RNF-13 | K17: En análisis | L17: Alexssander y Millaray | M17: 2.0
... A43: RF-39 | B43: OBJ-002 | C43: PR-02 | D43: Funcional | E43: =IF(C43="","",IFERROR(IF(INDEX('Objetivos y procesos'!$E$6:$E$35,MATCH(C43,'Objetivos y procesos'!$C$6:$C$35,0))="","",INDEX('Objetivos y procesos'!$E$6:$E$35,MATCH(C43,'Objetivos y procesos'!$C$6:$C$35,0))),"ID no encontrado")) -> Solicitudes y autorizaciones | F43: Respaldos de la solicitud de código | G43: El sistema debe permitir adjuntar a la solicitud de código el respaldo de la cotización, como documentos o imágenes de WhatsApp, y, en las solicitudes de creación, un documento y una imagen por cada producto solicitado. | H43: ERS v2.0 (Doc. 9) · Carta 7.2 | I43: Alta | J43: RN-40 | K43: En análisis | L43: Millaray y Matías | M43: 2.0

Sheet Historias y criterios
A2: Historias de usuario y criterios
A4: Use una fila por criterio de aceptación. Si una historia tiene varios criterios, repita su ID HU y asigne un ID CA diferente.
A5: ID Criterio | B5: ID HU | C5: ID Requerimiento | D5: ID Épica | E5: Funcionalidad | F5: Título HU | G5: Como | H5: Quiero | I5: Para | J5: Historia completa | K5: Criterio de aceptación | L5: Prioridad | M5: Estimación SP | N5: Sprint | O5: Estado | P5: Responsable
A6: CA-001 | B6: HU-001 | C6: RF-01 | D6: EP-01 | E6: Acceso seguro | F6: Autenticarse en la plataforma | G6: usuario habilitado | H6: iniciar sesión de forma segura y mantener una sesión controlada | I6: acceder únicamente a las funciones autorizadas | J6: =IF(OR(G6="",H6="",I6=""),"","Como "&G6&", quiero "&H6&", para "&I6) -> Como usuario habilitado, quiero iniciar sesión de forma segura y mantener una sesión controlada, para acceder únicamente a las funciones autorizadas | K6: Con credenciales válidas, el usuario activo ingresa a la plataforma. | L6: Alta | M6: 5 | N6: Sprint 1 · 2 sem. | O6: Propuesto | P6: Matías y Alexssander
A7: CA-002 | B7: HU-001 | C7: RF-01 | D7: EP-01 | E7: Acceso seguro | F7: Autenticarse en la plataforma | G7: usuario habilitado | H7: iniciar sesión de forma segura y mantener una sesión controlada | I7: acceder únicamente a las funciones autorizadas | J7: =IF(OR(G7="",H7="",I7=""),"","Como "&G7&", quiero "&H7&", para "&I7) -> Como usuario habilitado, quiero iniciar sesión de forma segura y mantener una sesión controlada, para acceder únicamente a las funciones autorizadas | K7: Las credenciales inválidas o de un usuario desactivado impiden el acceso y muestran un mensaje claro. | L7: Alta | M7: 5 | N7: Sprint 1 · 2 sem. | O7: Propuesto | P7: Matías y Alexssander
A8: CA-003 | B8: HU-001 | C8: RF-01 | D8: EP-01 | E8: Acceso seguro | F8: Autenticarse en la plataforma | G8: usuario habilitado | H8: iniciar sesión de forma segura y mantener una sesión controlada | I8: acceder únicamente a las funciones autorizadas | J8: =IF(OR(G8="",H8="",I8=""),"","Como "&G8&", quiero "&H8&", para "&I8) -> Como usuario habilitado, quiero iniciar sesión de forma segura y mantener una sesión controlada, para acceder únicamente a las funciones autorizadas | K8: La contraseña se almacena mediante hash, la sesión expira por inactividad y los intentos fallidos quedan auditados. | L8: Alta | M8: 5 | N8: Sprint 1 · 2 sem. | O8: Propuesto | P8: Matías y Alexssander
A9: CA-004 | B9: HU-002 | C9: RF-02 | D9: EP-01 | E9: Administración de usuarios | F9: Administrar usuarios y perfiles | G9: administrador | H9: crear, editar, desactivar y reactivar usuarios asignándoles área, cargo y rol | I9: mantener los accesos alineados con las responsabilidades de cada trabajador | J9: =IF(OR(G9="",H9="",I9=""),"","Como "&G9&", quiero "&H9&", para "&I9) -> Como administrador, quiero crear, editar, desactivar y reactivar usuarios asignándoles área, cargo y rol, para mantener los accesos alineados con las responsabilidades de cada trabajador | K9: El administrador crea y edita usuarios con área, cargo y rol obligatorios. | L9: Alta | M9: 8 | N9: Sprint 1 · 2 sem. | O9: Propuesto | P9: Matías y Alexssander
A10: CA-005 | B10: HU-002 | C10: RF-04 | D10: EP-01 | E10: Administración de usuarios | F10: Administrar usuarios y perfiles | G10: administrador | H10: crear, editar, desactivar y reactivar usuarios asignándoles área, cargo y rol | I10: mantener los accesos alineados con las responsabilidades de cada trabajador | J10: =IF(OR(G10="",H10="",I10=""),"","Como "&G10&", quiero "&H10&", para "&I10) -> Como administrador, quiero crear, editar, desactivar y reactivar usuarios asignándoles área, cargo y rol, para mantener los accesos alineados con las responsabilidades de cada trabajador | K10: Un usuario se desactiva o reactiva sin eliminar su historial. | L10: Alta | M10: 8 | N10: Sprint 1 · 2 sem. | O10: Propuesto | P10: Matías y Alexssander
A11: CA-006 | B11: HU-002 | C11: RF-04 | D11: EP-01 | E11: Administración de usuarios | F11: Administrar usuarios y perfiles | G11: administrador | H11: crear, editar, desactivar y reactivar usuarios asignándoles área, cargo y rol | I11: mantener los accesos alineados con las responsabilidades de cada trabajador | J11: =IF(OR(G11="",H11="",I11=""),"","Como "&G11&", quiero "&H11&", para "&I11) -> Como administrador, quiero crear, editar, desactivar y reactivar usuarios asignándoles área, cargo y rol, para mantener los accesos alineados con las responsabilidades de cada trabajador | K11: Solo el administrador puede ejecutar estas operaciones y un usuario desactivado no puede iniciar sesión. | L11: Alta | M11: 8 | N11: Sprint 1 · 2 sem. | O11: Propuesto | P11: Matías y Alexssander
A12: CA-007 | B12: HU-003 | C12: RF-03 | D12: EP-01 | E12: Permisos y autorizadores | F12: Configurar permisos y grupos de autorización | G12: administrador | H12: definir permisos por rol, área y cargo, además de grupos autorizadores por tipo de solicitud | I12: controlar qué funciones, datos y decisiones corresponden a cada usuario | J12: =IF(OR(G12="",H12="",I12=""),"","Como "&G12&", quiero "&H12&", para "&I12) -> Como administrador, quiero definir permisos por rol, área y cargo, además de grupos autorizadores por tipo de solicitud, para controlar qué funciones, datos y decisiones corresponden a cada usuario | K12: Los permisos efectivos suman los permisos directos, del área y del cargo. | L12: Alta | M12: 8 | N12: Sprint 1 · 2 sem. | O12: Propuesto | P12: Matías y Alexssander
A13: CA-008 | B13: HU-003 | C13: RF-03 | D13: EP-01 | E13: Permisos y autorizadores | F13: Configurar permisos y grupos de autorización | G13: administrador | H13: definir permisos por rol, área y cargo, además de grupos autorizadores por tipo de solicitud | I13: controlar qué funciones, datos y decisiones corresponden a cada usuario | J13: =IF(OR(G13="",H13="",I13=""),"","Como "&G13&", quiero "&H13&", para "&I13) -> Como administrador, quiero definir permisos por rol, área y cargo, además de grupos autorizadores por tipo de solicitud, para controlar qué funciones, datos y decisiones corresponden a cada usuario | K13: Cada operación valida los permisos en el servidor. | L13: Alta | M13: 8 | N13: Sprint 1 · 2 sem. | O13: Propuesto | P13: Matías y Alexssander
A14: CA-009 | B14: HU-003 | C14: RF-29 | D14: EP-01 | E14: Permisos y autorizadores | F14: Configurar permisos y grupos de autorización | G14: administrador | H14: definir permisos por rol, área y cargo, además de grupos autorizadores por tipo de solicitud | I14: controlar qué funciones, datos y decisiones corresponden a cada usuario | J14: =IF(OR(G14="",H14="",I14=""),"","Como "&G14&", quiero "&H14&", para "&I14) -> Como administrador, quiero definir permisos por rol, área y cargo, además de grupos autorizadores por tipo de solicitud, para controlar qué funciones, datos y decisiones corresponden a cada usuario | K14: Es posible crear y modificar grupos por tipo de solicitud, siempre con al menos un integrante activo. | L14: Alta | M14: 8 | N14: Sprint 1 · 2 sem. | O14: Propuesto | P14: Matías y Alexssander
A15: CA-010 | B15: HU-003 | C15: RF-05 | D15: EP-01 | E15: Permisos y autorizadores | F15: Configurar permisos y grupos de autorización | G15: administrador | H15: definir permisos por rol, área y cargo, además de grupos autorizadores por tipo de solicitud | I15: controlar qué funciones, datos y decisiones corresponden a cada usuario | J15: =IF(OR(G15="",H15="",I15=""),"","Como "&G15&", quiero "&H15&", para "&I15) -> Como administrador, quiero definir permisos por rol, área y cargo, además de grupos autorizadores por tipo de solicitud, para controlar qué funciones, datos y decisiones corresponden a cada usuario | K15: Solo el administrador gestiona permisos y grupos. | L15: Alta | M15: 8 | N15: Sprint 1 · 2 sem. | O15: Propuesto | P15: Matías y Alexssander
A16: CA-011 | B16: HU-004 | C16: RF-35 | D16: EP-01 | E16: Contexto de empresa y vendedor | F16: Configurar empresas, vendedores y comisiones | G16: administrador | H16: asociar SlpCode y escala de comisión por empresa a vendedores y asistentes | I16: asegurar que cada operación use la empresa y el vendedor correctos | J16: =IF(OR(G16="",H16="",I16=""),"","Como "&G16&", quiero "&H16&", para "&I16) -> Como administrador, quiero asociar SlpCode y escala de comisión por empresa a vendedores y asistentes, para asegurar que cada operación use la empresa y el vendedor correctos | K16: Cada SlpCode queda asociado a Marsella o Asland y a los usuarios autorizados. | L16: Alta | M16: 8 | N16: Sprint 1 · 2 sem. | O16: Propuesto | P16: Matías y Alexssander
A17: CA-012 | B17: HU-004 | C17: RF-36 | D17: EP-01 | E17: Contexto de empresa y vendedor | F17: Configurar empresas, vendedores y comisiones | G17: administrador | H17: asociar SlpCode y escala de comisión por empresa a vendedores y asistentes | I17: asegurar que cada operación use la empresa y el vendedor correctos | J17: =IF(OR(G17="",H17="",I17=""),"","Como "&G17&", quiero "&H17&", para "&I17) -> Como administrador, quiero asociar SlpCode y escala de comisión por empresa a vendedores y asistentes, para asegurar que cada operación use la empresa y el vendedor correctos | K17: Se asigna una escala de comisión o se usa la escala predeterminada. | L17: Alta | M17: 8 | N17: Sprint 1 · 2 sem. | O17: Propuesto | P17: Matías y Alexssander
... A83: CA-078 | B83: HU-020 | C83: RF-34 | D83: EP-06 | E83: Seguimiento y cierre | F83: Gestionar el avance y cierre de posventa | G83: autorizador de posventa | H83: actualizar el caso por sus estados y registrar su resolución final | I83: mantener el seguimiento hasta un cierre controlado | J83: =IF(OR(G83="",H83="",I83=""),"","Como "&G83&", quiero "&H83&", para "&I83) -> Como autorizador de posventa, quiero actualizar el caso por sus estados y registrar su resolución final, para mantener el seguimiento hasta un cierre controlado | K83: Solo el autorizador cierra el caso; un caso cerrado no acepta nuevos cambios. | L83: Alta | M83: 8 | N83: Sprint 6 · 1 sem. | O83: Propuesto | P83: Millaray y Alexssander

Sheet Casos y evidencias
A2: Casos de prueba y evidencias
A4: Registre la ejecución de cada prueba y agregue el identificador y enlace o ruta de la evidencia cuando esté disponible.
A5: ID Caso prueba | B5: ID Criterio | C5: ID HU | D5: ID Requerimiento | E5: Caso / Escenario | F5: Precondiciones | G5: Pasos | H5: Resultado esperado | I5: Resultado obtenido | J5: Estado prueba | K5: ID Evidencia | L5: Evidencia / Enlace / Ruta | M5: Fecha | N5: Responsable | O5: Observaciones
A6: CP-001 | B6: CA-001 | C6: =IF($B6="","",IFERROR(IF(VLOOKUP($B6,'Historias y criterios'!$A$6:$P$83,2,FALSE)="","",VLOOKUP($B6,'Historias y criterios'!$A$6:$P$83,2,FALSE)),"ID no encontrado")) -> HU-001 | D6: =IF($B6="","",IFERROR(IF(VLOOKUP($B6,'Historias y criterios'!$A$6:$P$83,3,FALSE)="","",VLOOKUP($B6,'Historias y criterios'!$A$6:$P$83,3,FALSE)),"ID no encontrado")) -> RF-01 | E6: Inicio de sesión con credenciales válidas | F6: Usuario activo con área, cargo y rol asignados (datos ficticios). | G6: 1. Abrir la página de inicio de sesión. 2. Ingresar usuario y contraseña válidos. 3. Presionar Ingresar. | H6: El usuario accede a la plataforma y ve solo las opciones correspondientes a sus permisos. | J6: No ejecutado | N6: Matías y Alexssander
A7: CP-002 | B7: CA-002 | C7: =IF($B7="","",IFERROR(IF(VLOOKUP($B7,'Historias y criterios'!$A$6:$P$83,2,FALSE)="","",VLOOKUP($B7,'Historias y criterios'!$A$6:$P$83,2,FALSE)),"ID no encontrado")) -> HU-001 | D7: =IF($B7="","",IFERROR(IF(VLOOKUP($B7,'Historias y criterios'!$A$6:$P$83,3,FALSE)="","",VLOOKUP($B7,'Historias y criterios'!$A$6:$P$83,3,FALSE)),"ID no encontrado")) -> RF-01 | E7: Acceso denegado con credenciales inválidas o usuario desactivado | F7: Existe un usuario activo y otro desactivado. | G7: 1. Intentar ingresar con una contraseña incorrecta. 2. Intentar ingresar con el usuario desactivado. | H7: En ambos casos se impide el acceso y se muestra un mensaje claro. | J7: No ejecutado | N7: Matías y Alexssander
A8: CP-003 | B8: CA-003 | C8: =IF($B8="","",IFERROR(IF(VLOOKUP($B8,'Historias y criterios'!$A$6:$P$83,2,FALSE)="","",VLOOKUP($B8,'Historias y criterios'!$A$6:$P$83,2,FALSE)),"ID no encontrado")) -> HU-001 | D8: =IF($B8="","",IFERROR(IF(VLOOKUP($B8,'Historias y criterios'!$A$6:$P$83,3,FALSE)="","",VLOOKUP($B8,'Historias y criterios'!$A$6:$P$83,3,FALSE)),"ID no encontrado")) -> RF-01 | E8: Hash de contraseña, expiración de sesión y auditoría | F8: Usuario de prueba creado; tiempo de inactividad configurado. | G8: 1. Revisar en la base de datos el campo de contraseña. 2. Dejar una sesión inactiva más allá del tiempo definido. 3. Realizar un intento fallido y revisar el registro de auditoría. | H8: La contraseña está almacenada como hash, la sesión expira y el intento fallido queda registrado con usuario, fecha y hora. | J8: No ejecutado | N8: Matías y Alexssander
A9: CP-004 | B9: CA-004 | C9: =IF($B9="","",IFERROR(IF(VLOOKUP($B9,'Historias y criterios'!$A$6:$P$83,2,FALSE)="","",VLOOKUP($B9,'Historias y criterios'!$A$6:$P$83,2,FALSE)),"ID no encontrado")) -> HU-002 | D9: =IF($B9="","",IFERROR(IF(VLOOKUP($B9,'Historias y criterios'!$A$6:$P$83,3,FALSE)="","",VLOOKUP($B9,'Historias y criterios'!$A$6:$P$83,3,FALSE)),"ID no encontrado")) -> RF-02 | E9: Creación y edición de usuario con área, cargo y rol | F9: Sesión como administrador; existen áreas, cargos y roles. | G9: 1. Ir a Usuarios > Nuevo. 2. Intentar guardar sin área, cargo o rol. 3. Completar los campos y guardar. 4. Editar el cargo del usuario. | H9: El sistema exige área, cargo y rol; con datos completos el usuario se crea y la edición se guarda. | J9: No ejecutado | N9: Matías y Alexssander
A10: CP-005 | B10: CA-005 | C10: =IF($B10="","",IFERROR(IF(VLOOKUP($B10,'Historias y criterios'!$A$6:$P$83,2,FALSE)="","",VLOOKUP($B10,'Historias y criterios'!$A$6:$P$83,2,FALSE)),"ID no encontrado")) -> HU-002 | D10: =IF($B10="","",IFERROR(IF(VLOOKUP($B10,'Historias y criterios'!$A$6:$P$83,3,FALSE)="","",VLOOKUP($B10,'Historias y criterios'!$A$6:$P$83,3,FALSE)),"ID no encontrado")) -> RF-04 | E10: Desactivación y reactivación sin pérdida de historial | F10: Usuario con registros e historial existentes. | G10: 1. Desactivar el usuario. 2. Revisar su historial. 3. Reactivarlo. | H10: El usuario pasa a Inactivo y luego a Activo; su historial y registros se conservan. | J10: No ejecutado | N10: Matías y Alexssander
A11: CP-006 | B11: CA-006 | C11: =IF($B11="","",IFERROR(IF(VLOOKUP($B11,'Historias y criterios'!$A$6:$P$83,2,FALSE)="","",VLOOKUP($B11,'Historias y criterios'!$A$6:$P$83,2,FALSE)),"ID no encontrado")) -> HU-002 | D11: =IF($B11="","",IFERROR(IF(VLOOKUP($B11,'Historias y criterios'!$A$6:$P$83,3,FALSE)="","",VLOOKUP($B11,'Historias y criterios'!$A$6:$P$83,3,FALSE)),"ID no encontrado")) -> RF-04 | E11: Operaciones exclusivas del administrador | F11: Usuario vendedor activo; usuario desactivado. | G11: 1. Con sesión de vendedor, intentar acceder a la gestión de usuarios por menú y por URL directa. 2. Intentar iniciar sesión con el usuario desactivado. | H11: El vendedor recibe acceso denegado validado en el servidor y el usuario desactivado no puede iniciar sesión. | J11: No ejecutado | N11: Matías y Alexssander
A12: CP-007 | B12: CA-007 | C12: =IF($B12="","",IFERROR(IF(VLOOKUP($B12,'Historias y criterios'!$A$6:$P$83,2,FALSE)="","",VLOOKUP($B12,'Historias y criterios'!$A$6:$P$83,2,FALSE)),"ID no encontrado")) -> HU-003 | D12: =IF($B12="","",IFERROR(IF(VLOOKUP($B12,'Historias y criterios'!$A$6:$P$83,3,FALSE)="","",VLOOKUP($B12,'Historias y criterios'!$A$6:$P$83,3,FALSE)),"ID no encontrado")) -> RF-03 | E12: Cálculo de permisos efectivos | F12: Usuario con un permiso directo, uno por área y otro por cargo. | G12: 1. Iniciar sesión con el usuario y revisar las funciones disponibles. 2. Quitar el permiso del área y volver a ingresar. | H12: El usuario dispone de la suma de los tres permisos; al quitar el del área deja de ver esa función. | J12: No ejecutado | N12: Matías y Alexssander
A13: CP-008 | B13: CA-008 | C13: =IF($B13="","",IFERROR(IF(VLOOKUP($B13,'Historias y criterios'!$A$6:$P$83,2,FALSE)="","",VLOOKUP($B13,'Historias y criterios'!$A$6:$P$83,2,FALSE)),"ID no encontrado")) -> HU-003 | D13: =IF($B13="","",IFERROR(IF(VLOOKUP($B13,'Historias y criterios'!$A$6:$P$83,3,FALSE)="","",VLOOKUP($B13,'Historias y criterios'!$A$6:$P$83,3,FALSE)),"ID no encontrado")) -> RF-03 | E13: Validación de permisos en el servidor | F13: Usuario sin permiso para una función determinada. | G13: 1. Iniciar sesión con el usuario. 2. Invocar directamente la URL o endpoint de la función restringida. | H13: El servidor rechaza la operación aunque la opción esté oculta en la interfaz. | J13: No ejecutado | N13: Matías y Alexssander
A14: CP-009 | B14: CA-009 | C14: =IF($B14="","",IFERROR(IF(VLOOKUP($B14,'Historias y criterios'!$A$6:$P$83,2,FALSE)="","",VLOOKUP($B14,'Historias y criterios'!$A$6:$P$83,2,FALSE)),"ID no encontrado")) -> HU-003 | D14: =IF($B14="","",IFERROR(IF(VLOOKUP($B14,'Historias y criterios'!$A$6:$P$83,3,FALSE)="","",VLOOKUP($B14,'Historias y criterios'!$A$6:$P$83,3,FALSE)),"ID no encontrado")) -> RF-29 | E14: Gestión de grupos autorizadores por tipo de solicitud | F14: Sesión como administrador; existen usuarios activos. | G14: 1. Crear un grupo para 'Creación de artículo' con un integrante. 2. Modificar sus integrantes. 3. Intentar dejar el grupo sin integrantes activos. | H14: El grupo se crea y modifica; el sistema impide guardarlo sin al menos un integrante activo. | J14: No ejecutado | N14: Matías y Alexssander
A15: CP-010 | B15: CA-010 | C15: =IF($B15="","",IFERROR(IF(VLOOKUP($B15,'Historias y criterios'!$A$6:$P$83,2,FALSE)="","",VLOOKUP($B15,'Historias y criterios'!$A$6:$P$83,2,FALSE)),"ID no encontrado")) -> HU-003 | D15: =IF($B15="","",IFERROR(IF(VLOOKUP($B15,'Historias y criterios'!$A$6:$P$83,3,FALSE)="","",VLOOKUP($B15,'Historias y criterios'!$A$6:$P$83,3,FALSE)),"ID no encontrado")) -> RF-05 | E15: Gestión de permisos exclusiva del administrador | F15: Usuario administrador y usuario no administrador. | G15: 1. Como administrador, modificar los permisos de un rol. 2. Como no administrador, intentar modificar permisos o grupos. | H15: El administrador guarda los cambios; el no administrador recibe acceso denegado. | J15: No ejecutado | N15: Matías y Alexssander
A16: CP-011 | B16: CA-011 | C16: =IF($B16="","",IFERROR(IF(VLOOKUP($B16,'Historias y criterios'!$A$6:$P$83,2,FALSE)="","",VLOOKUP($B16,'Historias y criterios'!$A$6:$P$83,2,FALSE)),"ID no encontrado")) -> HU-004 | D16: =IF($B16="","",IFERROR(IF(VLOOKUP($B16,'Historias y criterios'!$A$6:$P$83,3,FALSE)="","",VLOOKUP($B16,'Historias y criterios'!$A$6:$P$83,3,FALSE)),"ID no encontrado")) -> RF-35 | E16: Asociación de SlpCode por empresa | F16: Sesión como administrador; usuario vendedor creado. | G16: 1. Editar el perfil del vendedor. 2. Asociar un SlpCode de Marsella y otro de Asland. 3. Guardar. | H16: Cada SlpCode queda vinculado a su empresa y al usuario. | J16: No ejecutado | N16: Matías y Alexssander
A17: CP-012 | B17: CA-012 | C17: =IF($B17="","",IFERROR(IF(VLOOKUP($B17,'Historias y criterios'!$A$6:$P$83,2,FALSE)="","",VLOOKUP($B17,'Historias y criterios'!$A$6:$P$83,2,FALSE)),"ID no encontrado")) -> HU-004 | D17: =IF($B17="","",IFERROR(IF(VLOOKUP($B17,'Historias y criterios'!$A$6:$P$83,3,FALSE)="","",VLOOKUP($B17,'Historias y criterios'!$A$6:$P$83,3,FALSE)),"ID no encontrado")) -> RF-36 | E17: Asignación de escala de comisión | F17: Existen Escala 1 y Escala 2, una marcada como predeterminada. | G17: 1. Asignar Escala 2 a un vendedor. 2. Dejar a otro vendedor sin escala. 3. Consultar la escala efectiva de ambos. | H17: El primero usa Escala 2 y el segundo la escala predeterminada. | J17: No ejecutado | N17: Matías y Alexssander
... A83: CP-078 | B83: CA-078 | C83: =IF($B83="","",IFERROR(IF(VLOOKUP($B83,'Historias y criterios'!$A$6:$P$83,2,FALSE)="","",VLOOKUP($B83,'Historias y criterios'!$A$6:$P$83,2,FALSE)),"ID no encontrado")) -> HU-020 | D83: =IF($B83="","",IFERROR(IF(VLOOKUP($B83,'Historias y criterios'!$A$6:$P$83,3,FALSE)="","",VLOOKUP($B83,'Historias y criterios'!$A$6:$P$83,3,FALSE)),"ID no encontrado")) -> RF-34 | E83: Cierre exclusivo y bloqueo posterior | F83: Caso listo para cierre. | G83: 1. Intentar cerrarlo con un vendedor. 2. Cerrarlo con el autorizador registrando la resolución. 3. Intentar un nuevo cambio de estado. | H83: Solo el autorizador cierra el caso y, una vez cerrado, no acepta cambios. | J83: No ejecutado | N83: Millaray y Alexssander
