Workbook

Sheet Resumen
A1: Planificación de sprints · Plataforma Integrada GGH
A2: Resumen del avance. Actualice el estado de cada tarea en la hoja Tareas y la aceptación de cada historia en la hoja Historias; el resto se recalcula.
B4: Avance global | E4: Story Points terminados | G4: Historias terminadas | I4: Sprint actual | L4: Fecha de hoy
B5: =L14 -> 0.59163987 | E5: =J14&" de "&I14 -> 84 de 145 | G5: =COUNTIF(Historias!$P:$P,"Terminada")&" de "&COUNTA(Historias!$A$5:$A$200) -> 12 de 20 | I5: =IFERROR(LOOKUP(2,1/((TODAY()>=C8:C13)*(TODAY()<=D8:D13)),B8:B13),"Entre sprints") -> Entre sprints | L5: =TODAY() -> 46307
B7: Sprint | C7: Inicio | D7: Término | E7: Días hábiles | F7: Tema | G7: Sprint Goal | H7: Historias | I7: SP planificados | J7: SP terminados | K7: Horas planificadas | L7: % avance | M7: Product Owner | N7: Scrum Master | O7: Integración | P7: Versión | Q7: Estado
B8: Sprint 1 | C8: 46265 | D8: 46276 | E8: =NETWORKDAYS(C8,D8,Feriados) -> 10 | F8: Usuarios, roles y permisos | G8: Habilitar el acceso seguro a la plataforma con usuarios, roles, permisos y contexto de empresa y vendedor, como base para operar los demás módulos. | H8: HU-001, HU-002, HU-003, HU-004 | I8: =SUMIFS(Historias!$E:$E,Historias!$D:$D,B8) -> 29 | J8: =SUMIFS(Historias!$E:$E,Historias!$D:$D,B8,Historias!$P:$P,"Terminada") -> 29 | K8: =SUMIFS(Tareas!$F:$F,Tareas!$B:$B,B8) -> 69 | L8: =IFERROR(SUMIFS(Tareas!$L:$L,Tareas!$B:$B,B8)/K8,0) -> 1 | M8: Matías Orellana | N8: Millaray Espósito | O8: Alexssander López | P8: v0.1.0 | Q8: =IF(TODAY()<C8,"Planificado",IF(TODAY()<=D8,"En curso",IF(L8>=1,"Cerrado","Cerrado con pendientes"))) -> Cerrado
B9: Sprint 2 | C9: 46279 | D9: 46290 | E9: =NETWORKDAYS(C9,D9,Feriados) -> 9 | F9: Solicitudes y autorizaciones | G9: Permitir que un vendedor cree y envíe una solicitud de código con sus respaldos, y que el grupo autorizador la reciba, resuelva y notifique, con seguimiento completo de su estado. | H9: HU-005, HU-006, HU-007, HU-012 | I9: =SUMIFS(Historias!$E:$E,Historias!$D:$D,B9) -> 26 | J9: =SUMIFS(Historias!$E:$E,Historias!$D:$D,B9,Historias!$P:$P,"Terminada") -> 26 | K9: =SUMIFS(Tareas!$F:$F,Tareas!$B:$B,B9) -> 56 | L9: =IFERROR(SUMIFS(Tareas!$L:$L,Tareas!$B:$B,B9)/K9,0) -> 1 | M9: Millaray Espósito | N9: Alexssander López | O9: Matías Orellana | P9: v0.2.0 | Q9: =IF(TODAY()<C9,"Planificado",IF(TODAY()<=D9,"En curso",IF(L9>=1,"Cerrado","Cerrado con pendientes"))) -> Cerrado
B10: Sprint 3 | C10: 46293 | D10: 46304 | E10: =NETWORKDAYS(C10,D10,Feriados) -> 10 | F10: Lectura SAP, consultas y cotizaciones | G10: Conectar la plataforma con SAP Business One en modo lectura para consultar productos, stock y clientes, y crear cotizaciones con el vendedor y la comisión correctos, informando al participante cada cambio de estado. | H10: HU-015, HU-008, HU-009, HU-013 | I10: =SUMIFS(Historias!$E:$E,Historias!$D:$D,B10) -> 29 | J10: =SUMIFS(Historias!$E:$E,Historias!$D:$D,B10,Historias!$P:$P,"Terminada") -> 29 | K10: =SUMIFS(Tareas!$F:$F,Tareas!$B:$B,B10) -> 59 | L10: =IFERROR(SUMIFS(Tareas!$L:$L,Tareas!$B:$B,B10)/K10,0) -> 1 | M10: Alexssander López | N10: Matías Orellana | O10: Millaray Espósito | P10: v0.3.0 | Q10: =IF(TODAY()<C10,"Planificado",IF(TODAY()<=D10,"En curso",IF(L10>=1,"Cerrado","Cerrado con pendientes"))) -> Cerrado
B11: Sprint 4 | C11: 46308 | D11: 46318 | E11: =NETWORKDAYS(C11,D11,Feriados) -> 9 | F11: Órdenes de venta e integración SAP | G11: Completar el flujo comercial desde la cotización aceptada hasta la orden de venta autorizada y enviada al ERP por Service Layer, con registro de resultados y reintentos sin duplicidad. | H11: HU-010, HU-016, HU-017, HU-011 | I11: =SUMIFS(Historias!$E:$E,Historias!$D:$D,B11) -> 29 | J11: =SUMIFS(Historias!$E:$E,Historias!$D:$D,B11,Historias!$P:$P,"Terminada") -> 0 | K11: =SUMIFS(Tareas!$F:$F,Tareas!$B:$B,B11) -> 55 | L11: =IFERROR(SUMIFS(Tareas!$L:$L,Tareas!$B:$B,B11)/K11,0) -> 0 | M11: Matías Orellana | N11: Millaray Espósito | O11: Alexssander López | P11: v0.4.0 | Q11: =IF(TODAY()<C11,"Planificado",IF(TODAY()<=D11,"En curso",IF(L11>=1,"Cerrado","Cerrado con pendientes"))) -> Planificado
B12: Sprint 5 | C12: 46321 | D12: 46332 | E12: =NETWORKDAYS(C12,D12,Feriados) -> 10 | F12: Posventa y trazabilidad | G12: Registrar, evaluar y autorizar casos de posventa con evidencias y comprobante QR, y ofrecer una consulta de trazabilidad común para todos los procesos. | H12: HU-018, HU-019, HU-014 | I12: =SUMIFS(Historias!$E:$E,Historias!$D:$D,B12) -> 24 | J12: =SUMIFS(Historias!$E:$E,Historias!$D:$D,B12,Historias!$P:$P,"Terminada") -> 0 | K12: =SUMIFS(Tareas!$F:$F,Tareas!$B:$B,B12) -> 51 | L12: =IFERROR(SUMIFS(Tareas!$L:$L,Tareas!$B:$B,B12)/K12,0) -> 0 | M12: Millaray Espósito | N12: Alexssander López | O12: Matías Orellana | P12: v0.5.0 | Q12: =IF(TODAY()<C12,"Planificado",IF(TODAY()<=D12,"En curso",IF(L12>=1,"Cerrado","Cerrado con pendientes"))) -> Planificado
B13: Sprint 6 | C13: 46335 | D13: 46339 | E13: =NETWORKDAYS(C13,D13,Feriados) -> 5 | F13: Cierre de posventa e integración final | G13: Cerrar el ciclo de posventa con el seguimiento de estados hasta su resolución final y dejar el producto integrado y estabilizado para la validación final. | H13: HU-020 | I13: =SUMIFS(Historias!$E:$E,Historias!$D:$D,B13) -> 8 | J13: =SUMIFS(Historias!$E:$E,Historias!$D:$D,B13,Historias!$P:$P,"Terminada") -> 0 | K13: =SUMIFS(Tareas!$F:$F,Tareas!$B:$B,B13) -> 21 | L13: =IFERROR(SUMIFS(Tareas!$L:$L,Tareas!$B:$B,B13)/K13,0) -> 0 | M13: Alexssander López | N13: Matías Orellana | O13: Millaray Espósito | P13: v0.6.0 | Q13: =IF(TODAY()<C13,"Planificado",IF(TODAY()<=D13,"En curso",IF(L13>=1,"Cerrado","Cerrado con pendientes"))) -> Planificado
B14: Total | I14: =SUM(I8:I13) -> 145 | J14: =SUM(J8:J13) -> 84 | K14: =SUM(K8:K13) -> 311 | L14: =IFERROR(SUMPRODUCT(K8:K13,L8:L13)/K14,0) -> 0.59163987
B16: Cómo usar este archivo
B17: 1. En la hoja Tareas, cambie el Estado de cada tarea (Por hacer, En curso, En revisión, En pruebas, Terminado). El avance de historias, sprints y la Carta Gantt se actualiza solo.
B18: 2. En la hoja Historias, marque «Aceptada por PO» = Sí cuando el Product Owner acepte la historia en la Sprint Review. Solo entonces cuenta como Terminada.
B19: 3. Si cambian las fechas de un sprint, edite Inicio y Término en esta hoja (celdas azules): las tareas, eventos y barras se mueven automáticamente.
B20: 4. En la Carta Gantt use los botones 1, 2 y 3 del margen izquierdo para ver solo sprints, sprints e historias, o todas las tareas.

Sheet Carta Gantt
A1: Carta Gantt de sprints
A2: Barras calculadas desde las fechas de cada tarea. Leyenda de eventos: P = Sprint Planning · F = Refinamiento · C = Congelamiento · R = Review y Retrospective. Gris = feriado; borde rojo = hoy.
K3: Sprint | O3: Historia | S3: Tarea | W3: Avance | AA3: Evento | AE3: Hito | AI3: Feriado
K4: Septiembre 2026 | AG4: Octubre 2026 | BC4: Noviembre 2026 | BX4: Diciembre 2026
J5: Sprint 1 | T5: Sprint 2 | AD5: Sprint 3 | AO5: Sprint 4 | AX5: Sprint 5 | BH5: Sprint 6 | BM5: Cierre del proyecto
A6: ID | B6: Actividad | C6: Tipo | D6: Responsable | E6: Inicio | F6: Fin | G6: Días | H6: % avance | I6: Estado | J6: 46265 | K6: 46266 | L6: 46267 | M6: 46268 | N6: 46269 | O6: 46272 | P6: 46273 | Q6: 46274 | R6: 46275 | S6: 46276 | T6: 46279 | U6: 46280 | V6: 46281 | W6: 46282 | X6: 46283 | Y6: 46286 | Z6: 46287 | AA6: 46288 | AB6: 46289 | AC6: 46290 | AD6: 46293 | AE6: 46294 | AF6: 46295 | AG6: 46296 | AH6: 46297 | AI6: 46300 | AJ6: 46301 | AK6: 46302 | AL6: 46303 | AM6: 46304 | AN6: 46307 | AO6: 46308 | AP6: 46309 | AQ6: 46310 | AR6: 46311 | AS6: 46314 | AT6: 46315 | AU6: 46316 | AV6: 46317 | AW6: 46318 | AX6: 46321 | AY6: 46322 | AZ6: 46323 | BA6: 46324 | BB6: 46325 | BC6: 46328 | BD6: 46329 | BE6: 46330 | BF6: 46331 | BG6: 46332 | BH6: 46335 | BI6: 46336 | BJ6: 46337 | BK6: 46338 | BL6: 46339 | BM6: 46342 | BN6: 46343 | BO6: 46344 | BP6: 46345 | BQ6: 46346 | BR6: 46349 | BS6: 46350 | BT6: 46351 | BU6: 46352 | BV6: 46353 | BW6: 46356 | BX6: 46357 | BY6: 46358 | BZ6: 46359 | CA6: 46360 | CB6: 46363 | CC6: 46364 | CD6: 46365 | CE6: 46366 | CF6: 46367
J7: =MID("LMMJV",WEEKDAY(J6,2),1) -> L | K7: =MID("LMMJV",WEEKDAY(K6,2),1) -> M | L7: =MID("LMMJV",WEEKDAY(L6,2),1) -> M | M7: =MID("LMMJV",WEEKDAY(M6,2),1) -> J | N7: =MID("LMMJV",WEEKDAY(N6,2),1) -> V | O7: =MID("LMMJV",WEEKDAY(O6,2),1) -> L | P7: =MID("LMMJV",WEEKDAY(P6,2),1) -> M | Q7: =MID("LMMJV",WEEKDAY(Q6,2),1) -> M | ... CF7: =MID("LMMJV",WEEKDAY(CF6,2),1) -> V
A8: S1 | B8: Sprint 1 · Usuarios, roles y permisos | C8: Sprint | D8: PO: Matías · SM: Millaray | E8: =Resumen!C8 -> 46265 | F8: =Resumen!D8 -> 46276 | G8: =NETWORKDAYS(E8,F8,Feriados) -> 10 | H8: =Resumen!L8 -> 1 | I8: =Resumen!Q8 -> Cerrado
B9: Eventos Scrum | C9: Eventos | D9: Scrum Team | J9: =IF(J$6=Eventos!$C$6,"F",IF(J$6=Eventos!$C$5,"P",IF(J$6=Eventos!$C$7,"C",IF(J$6=Eventos!$C$8,"R","")))) -> P | K9: =IF(K$6=Eventos!$C$6,"F",IF(K$6=Eventos!$C$5,"P",IF(K$6=Eventos!$C$7,"C",IF(K$6=Eventos!$C$8,"R","")))) | L9: =IF(L$6=Eventos!$C$6,"F",IF(L$6=Eventos!$C$5,"P",IF(L$6=Eventos!$C$7,"C",IF(L$6=Eventos!$C$8,"R","")))) | M9: =IF(M$6=Eventos!$C$6,"F",IF(M$6=Eventos!$C$5,"P",IF(M$6=Eventos!$C$7,"C",IF(M$6=Eventos!$C$8,"R","")))) | N9: =IF(N$6=Eventos!$C$6,"F",IF(N$6=Eventos!$C$5,"P",IF(N$6=Eventos!$C$7,"C",IF(N$6=Eventos!$C$8,"R","")))) | O9: =IF(O$6=Eventos!$C$6,"F",IF(O$6=Eventos!$C$5,"P",IF(O$6=Eventos!$C$7,"C",IF(O$6=Eventos!$C$8,"R","")))) -> F | P9: =IF(P$6=Eventos!$C$6,"F",IF(P$6=Eventos!$C$5,"P",IF(P$6=Eventos!$C$7,"C",IF(P$6=Eventos!$C$8,"R","")))) | Q9: =IF(Q$6=Eventos!$C$6,"F",IF(Q$6=Eventos!$C$5,"P",IF(Q$6=Eventos!$C$7,"C",IF(Q$6=Eventos!$C$8,"R","")))) | ... CF9: =IF(CF$6=Eventos!$C$6,"F",IF(CF$6=Eventos!$C$5,"P",IF(CF$6=Eventos!$C$7,"C",IF(CF$6=Eventos!$C$8,"R",""))))
A10: HU-001 | B10: Autenticarse en la plataforma | C10: Historia | D10: Matías y Alexssander | E10: =Historias!J5 -> 46265 | F10: =Historias!K5 -> 46269 | G10: =NETWORKDAYS(E10,F10,Feriados) -> 5 | H10: =Historias!N5 -> 1 | I10: =Historias!P5 -> Terminada
A11: T-1.01 | B11: Configurar el inicio y cierre de sesión con la autenticación de Django y la pantalla de acceso | C11: Tarea | D11: Matías | E11: =Tareas!H5 -> 46265 | F11: =Tareas!I5 -> 46269 | G11: =NETWORKDAYS(E11,F11,Feriados) -> 5 | H11: =Tareas!K5 -> 1 | I11: =Tareas!J5 -> Terminado
A12: T-1.02 | B12: Bloquear el acceso de usuarios desactivados y mostrar mensajes de error claros | C12: Tarea | D12: Matías | E12: =Tareas!H6 -> 46265 | F12: =Tareas!I6 -> 46269 | G12: =NETWORKDAYS(E12,F12,Feriados) -> 5 | H12: =Tareas!K6 -> 1 | I12: =Tareas!J6 -> Terminado
A13: T-1.03 | B13: Configurar el hash de contraseñas y la expiración de la sesión por inactividad | C13: Tarea | D13: Alexssander | E13: =Tareas!H7 -> 46265 | F13: =Tareas!I7 -> 46269 | G13: =NETWORKDAYS(E13,F13,Feriados) -> 5 | H13: =Tareas!K7 -> 1 | I13: =Tareas!J7 -> Terminado
A14: T-1.04 | B14: Registrar la auditoría de accesos e intentos fallidos | C14: Tarea | D14: Alexssander | E14: =Tareas!H8 -> 46265 | F14: =Tareas!I8 -> 46269 | G14: =NETWORKDAYS(E14,F14,Feriados) -> 5 | H14: =Tareas!K8 -> 1 | I14: =Tareas!J8 -> Terminado
A15: T-1.05 | B15: Pruebas automatizadas y ejecución de CP-001 a CP-003 | C15: Tarea | D15: Millaray | E15: =Tareas!H9 -> 46265 | F15: =Tareas!I9 -> 46269 | G15: =NETWORKDAYS(E15,F15,Feriados) -> 5 | H15: =Tareas!K9 -> 1 | I15: =Tareas!J9 -> Terminado
A16: HU-002 | B16: Administrar usuarios y perfiles | C16: Historia | D16: Matías y Alexssander | E16: =Historias!J6 -> 46265 | F16: =Historias!K6 -> 46269 | G16: =NETWORKDAYS(E16,F16,Feriados) -> 5 | H16: =Historias!N6 -> 1 | I16: =Historias!P6 -> Terminada
A17: T-1.06 | B17: Modelos de área, cargo, rol y perfil de usuario, con sus migraciones | C17: Tarea | D17: Alexssander | E17: =Tareas!H10 -> 46265 | F17: =Tareas!I10 -> 46269 | G17: =NETWORKDAYS(E17,F17,Feriados) -> 5 | H17: =Tareas!K10 -> 1 | I17: =Tareas!J10 -> Terminado
A18: T-1.07 | B18: Mantenedor de usuarios con área, cargo y rol obligatorios | C18: Tarea | D18: Matías | E18: =Tareas!H11 -> 46265 | F18: =Tareas!I11 -> 46269 | G18: =NETWORKDAYS(E18,F18,Feriados) -> 5 | H18: =Tareas!K11 -> 1 | I18: =Tareas!J11 -> Terminado
A19: T-1.08 | B19: Desactivación y reactivación de usuarios conservando su historial | C19: Tarea | D19: Matías | E19: =Tareas!H12 -> 46265 | F19: =Tareas!I12 -> 46269 | G19: =NETWORKDAYS(E19,F19,Feriados) -> 5 | H19: =Tareas!K12 -> 1 | I19: =Tareas!J12 -> Terminado
A20: T-1.09 | B20: Restringir la administración de usuarios al administrador, validado en el servidor | C20: Tarea | D20: Alexssander | E20: =Tareas!H13 -> 46265 | F20: =Tareas!I13 -> 46269 | G20: =NETWORKDAYS(E20,F20,Feriados) -> 5 | H20: =Tareas!K13 -> 1 | I20: =Tareas!J13 -> Terminado
A21: T-1.10 | B21: Pruebas automatizadas y ejecución de CP-004 a CP-006 | C21: Tarea | D21: Millaray | E21: =Tareas!H14 -> 46265 | F21: =Tareas!I14 -> 46269 | G21: =NETWORKDAYS(E21,F21,Feriados) -> 5 | H21: =Tareas!K14 -> 1 | I21: =Tareas!J14 -> Terminado
A22: HU-003 | B22: Configurar permisos y grupos de autorización | C22: Historia | D22: Matías y Alexssander | E22: =Historias!J7 -> 46272 | F22: =Historias!K7 -> 46276 | G22: =NETWORKDAYS(E22,F22,Feriados) -> 5 | H22: =Historias!N7 -> 1 | I22: =Historias!P7 -> Terminada
A23: T-1.11 | B23: Modelo de permisos directos, por área y por cargo, y cálculo de permisos efectivos | C23: Tarea | D23: Alexssander | E23: =Tareas!H15 -> 46272 | F23: =Tareas!I15 -> 46276 | G23: =NETWORKDAYS(E23,F23,Feriados) -> 5 | H23: =Tareas!K15 -> 1 | I23: =Tareas!J15 -> Terminado
A24: T-1.12 | B24: Validación centralizada de permisos en el servidor para cada vista | C24: Tarea | D24: Matías | E24: =Tareas!H16 -> 46272 | F24: =Tareas!I16 -> 46276 | G24: =NETWORKDAYS(E24,F24,Feriados) -> 5 | H24: =Tareas!K16 -> 1 | I24: =Tareas!J16 -> Terminado
A25: T-1.13 | B25: Grupos autorizadores por tipo de solicitud con al menos un integrante activo | C25: Tarea | D25: Matías | E25: =Tareas!H17 -> 46272 | F25: =Tareas!I17 -> 46276 | G25: =NETWORKDAYS(E25,F25,Feriados) -> 5 | H25: =Tareas!K17 -> 1 | I25: =Tareas!J17 -> Terminado
A26: T-1.14 | B26: Pantallas de administración de permisos y grupos | C26: Tarea | D26: Millaray | E26: =Tareas!H18 -> 46272 | F26: =Tareas!I18 -> 46276 | G26: =NETWORKDAYS(E26,F26,Feriados) -> 5 | H26: =Tareas!K18 -> 1 | I26: =Tareas!J18 -> Terminado
A27: T-1.15 | B27: Pruebas automatizadas y ejecución de CP-007 a CP-010 | C27: Tarea | D27: Millaray | E27: =Tareas!H19 -> 46272 | F27: =Tareas!I19 -> 46276 | G27: =NETWORKDAYS(E27,F27,Feriados) -> 5 | H27: =Tareas!K19 -> 1 | I27: =Tareas!J19 -> Terminado
A28: HU-004 | B28: Configurar empresas, vendedores y comisiones | C28: Historia | D28: Matías y Alexssander | E28: =Historias!J8 -> 46272 | F28: =Historias!K8 -> 46276 | G28: =NETWORKDAYS(E28,F28,Feriados) -> 5 | H28: =Historias!N8 -> 1 | I28: =Historias!P8 -> Terminada
A29: T-1.16 | B29: Modelos de SlpCode por empresa y escala de comisión, con sus migraciones | C29: Tarea | D29: Alexssander | E29: =Tareas!H20 -> 46272 | F29: =Tareas!I20 -> 46276 | G29: =NETWORKDAYS(E29,F29,Feriados) -> 5 | H29: =Tareas!K20 -> 1 | I29: =Tareas!J20 -> Terminado
A30: T-1.17 | B30: Asignación de SlpCode y escala de comisión en el perfil del vendedor | C30: Tarea | D30: Matías | E30: =Tareas!H21 -> 46272 | F30: =Tareas!I21 -> 46276 | G30: =NETWORKDAYS(E30,F30,Feriados) -> 5 | H30: =Tareas!K21 -> 1 | I30: =Tareas!J21 -> Terminado
A31: T-1.18 | B31: Selector de empresa activa en la barra de navegación y colores por empresa | C31: Tarea | D31: Millaray | E31: =Tareas!H22 -> 46272 | F31: =Tareas!I22 -> 46276 | G31: =NETWORKDAYS(E31,F31,Feriados) -> 5 | H31: =Tareas!K22 -> 1 | I31: =Tareas!J22 -> Terminado
A32: T-1.19 | B32: Pruebas automatizadas y ejecución de CP-011 a CP-014 | C32: Tarea | D32: Alexssander | E32: =Tareas!H23 -> 46272 | F32: =Tareas!I23 -> 46276 | G32: =NETWORKDAYS(E32,F32,Feriados) -> 5 | H32: =Tareas!K23 -> 1 | I32: =Tareas!J23 -> Terminado
B33: Tareas transversales del sprint | C33: Historia | D33: Scrum Team | E33: =_xlfn.MINIFS(Tareas!$H:$H,Tareas!$B:$B,"Sprint 1",Tareas!$C:$C,"Transversal") -> 46265 | F33: =_xlfn.MAXIFS(Tareas!$I:$I,Tareas!$B:$B,"Sprint 1",Tareas!$C:$C,"Transversal") -> 46276 | G33: =NETWORKDAYS(E33,F33,Feriados) -> 10 | H33: =IFERROR(SUMIFS(Tareas!$L:$L,Tareas!$B:$B,"Sprint 1",Tareas!$C:$C,"Transversal")/SUMIFS(Tareas!$F:$F,Tareas!$B:$B,"Sprint 1",Tareas!$C:$C,"Transversal"),0) -> 1
A34: T-1.20 | B34: Configurar el repositorio privado, las ramas protegidas, el tablero y el archivo .env.example | C34: Tarea | D34: Alexssander | E34: =Tareas!H24 -> 46265 | F34: =Tareas!I24 -> 46269 | G34: =NETWORKDAYS(E34,F34,Feriados) -> 5 | H34: =Tareas!K24 -> 1 | I34: =Tareas!J24 -> Terminado
A35: T-1.21 | B35: Cargar datos ficticios de demostración: usuarios, áreas, cargos y empresas | C35: Tarea | D35: Millaray | E35: =Tareas!H25 -> 46265 | F35: =Tareas!I25 -> 46269 | G35: =NETWORKDAYS(E35,F35,Feriados) -> 5 | H35: =Tareas!K25 -> 1 | I35: =Tareas!J25 -> Terminado
A36: T-1.22 | B36: Integrar develop en main, etiquetar v0.1.0 y preparar la demostración | C36: Tarea | D36: Alexssander | E36: =Tareas!H26 -> 46272 | F36: =Tareas!I26 -> 46276 | G36: =NETWORKDAYS(E36,F36,Feriados) -> 5 | H36: =Tareas!K26 -> 1 | I36: =Tareas!J26 -> Terminado
A37: T-1.23 | B37: Actualizar la matriz de trazabilidad y el Expediente de Sprint | C37: Tarea | D37: Millaray | E37: =Tareas!H27 -> 46272 | F37: =Tareas!I27 -> 46276 | G37: =NETWORKDAYS(E37,F37,Feriados) -> 5 | H37: =Tareas!K27 -> 1 | I37: =Tareas!J27 -> Terminado
A38: S2 | B38: Sprint 2 · Solicitudes y autorizaciones | C38: Sprint | D38: PO: Millaray · SM: Alexssander | E38: =Resumen!C9 -> 46279 | F38: =Resumen!D9 -> 46290 | G38: =NETWORKDAYS(E38,F38,Feriados) -> 9 | H38: =Resumen!L9 -> 1 | I38: =Resumen!Q9 -> Cerrado
B39: Eventos Scrum | C39: Eventos | D39: Scrum Team | J39: =IF(J$6=Eventos!$C$11,"F",IF(J$6=Eventos!$C$10,"P",IF(J$6=Eventos!$C$12,"C",IF(J$6=Eventos!$C$13,"R","")))) | K39: =IF(K$6=Eventos!$C$11,"F",IF(K$6=Eventos!$C$10,"P",IF(K$6=Eventos!$C$12,"C",IF(K$6=Eventos!$C$13,"R","")))) | L39: =IF(L$6=Eventos!$C$11,"F",IF(L$6=Eventos!$C$10,"P",IF(L$6=Eventos!$C$12,"C",IF(L$6=Eventos!$C$13,"R","")))) | M39: =IF(M$6=Eventos!$C$11,"F",IF(M$6=Eventos!$C$10,"P",IF(M$6=Eventos!$C$12,"C",IF(M$6=Eventos!$C$13,"R","")))) | N39: =IF(N$6=Eventos!$C$11,"F",IF(N$6=Eventos!$C$10,"P",IF(N$6=Eventos!$C$12,"C",IF(N$6=Eventos!$C$13,"R","")))) | O39: =IF(O$6=Eventos!$C$11,"F",IF(O$6=Eventos!$C$10,"P",IF(O$6=Eventos!$C$12,"C",IF(O$6=Eventos!$C$13,"R","")))) | P39: =IF(P$6=Eventos!$C$11,"F",IF(P$6=Eventos!$C$10,"P",IF(P$6=Eventos!$C$12,"C",IF(P$6=Eventos!$C$13,"R","")))) | Q39: =IF(Q$6=Eventos!$C$11,"F",IF(Q$6=Eventos!$C$10,"P",IF(Q$6=Eventos!$C$12,"C",IF(Q$6=Eventos!$C$13,"R","")))) | ... CF39: =IF(CF$6=Eventos!$C$11,"F",IF(CF$6=Eventos!$C$10,"P",IF(CF$6=Eventos!$C$12,"C",IF(CF$6=Eventos!$C$13,"R",""))))
A40: HU-005 | B40: Crear y enviar solicitudes de código | C40: Historia | D40: Millaray y Matías | E40: =Historias!J9 -> 46279 | F40: =Historias!K9 -> 46283 | G40: =NETWORKDAYS(E40,F40,Feriados) -> 4 | H40: =Historias!N9 -> 1 | I40: =Historias!P9 -> Terminada
A41: T-2.01 | B41: Modelos de solicitud, productos solicitados y adjuntos, con estados y migraciones | C41: Tarea | D41: Matías | E41: =Tareas!H28 -> 46279 | F41: =Tareas!I28 -> 46283 | G41: =NETWORKDAYS(E41,F41,Feriados) -> 4 | H41: =Tareas!K28 -> 1 | I41: =Tareas!J28 -> Terminado
A42: T-2.02 | B42: Formulario de solicitud por tipo (creación, activación o modificación) con uno o más productos | C42: Tarea | D42: Millaray | E42: =Tareas!H29 -> 46279 | F42: =Tareas!I29 -> 46283 | G42: =NETWORKDAYS(E42,F42,Feriados) -> 4 | H42: =Tareas!K29 -> 1 | I42: =Tareas!J29 -> Terminado
A43: T-2.03 | B43: Validación y almacenamiento de respaldos fuera de la base de datos, según los formatos permitidos | C43: Tarea | D43: Matías | E43: =Tareas!H30 -> 46279 | F43: =Tareas!I30 -> 46283 | G43: =NETWORKDAYS(E43,F43,Feriados) -> 4 | H43: =Tareas!K30 -> 1 | I43: =Tareas!J30 -> Terminado
A44: T-2.04 | B44: Envío de la solicitud a la bandeja del grupo autorizador correspondiente | C44: Tarea | D44: Matías | E44: =Tareas!H31 -> 46279 | F44: =Tareas!I31 -> 46283 | G44: =NETWORKDAYS(E44,F44,Feriados) -> 4 | H44: =Tareas!K31 -> 1 | I44: =Tareas!J31 -> Terminado
A45: T-2.05 | B45: Pruebas automatizadas y ejecución de CP-015 a CP-018 | C45: Tarea | D45: Alexssander | E45: =Tareas!H32 -> 46279 | F45: =Tareas!I32 -> 46283 | G45: =NETWORKDAYS(E45,F45,Feriados) -> 4 | H45: =Tareas!K32 -> 1 | I45: =Tareas!J32 -> Terminado
A46: HU-006 | B46: Aprobar o rechazar solicitudes | C46: Historia | D46: Millaray y Matías | E46: =Historias!J10 -> 46279 | F46: =Historias!K10 -> 46283 | G46: =NETWORKDAYS(E46,F46,Feriados) -> 4 | H46: =Historias!N10 -> 1 | I46: =Historias!P10 -> Terminada
A47: T-2.06 | B47: Bandeja compartida del grupo y acción para tomar la solicitud | C47: Tarea | D47: Millaray | E47: =Tareas!H33 -> 46279 | F47: =Tareas!I33 -> 46283 | G47: =NETWORKDAYS(E47,F47,Feriados) -> 4 | H47: =Tareas!K33 -> 1 | I47: =Tareas!J33 -> Terminado
A48: T-2.07 | B48: Aprobación y rechazo con motivo obligatorio; bloqueo de edición después de aprobar | C48: Tarea | D48: Matías | E48: =Tareas!H34 -> 46279 | F48: =Tareas!I34 -> 46283 | G48: =NETWORKDAYS(E48,F48,Feriados) -> 4 | H48: =Tareas!K34 -> 1 | I48: =Tareas!J34 -> Terminado
A49: T-2.08 | B49: Registro de usuario, fecha, hora y comentario de la resolución | C49: Tarea | D49: Alexssander | E49: =Tareas!H35 -> 46279 | F49: =Tareas!I35 -> 46283 | G49: =NETWORKDAYS(E49,F49,Feriados) -> 4 | H49: =Tareas!K35 -> 1 | I49: =Tareas!J35 -> Terminado
A50: T-2.09 | B50: Pruebas automatizadas y ejecución de CP-019 a CP-022 | C50: Tarea | D50: Alexssander | E50: =Tareas!H36 -> 46279 | F50: =Tareas!I36 -> 46283 | G50: =NETWORKDAYS(E50,F50,Feriados) -> 4 | H50: =Tareas!K36 -> 1 | I50: =Tareas!J36 -> Terminado
A51: HU-007 | B51: Corregir, reenviar y consultar solicitudes | C51: Historia | D51: Millaray y Matías | E51: =Historias!J11 -> 46286 | F51: =Historias!K11 -> 46290 | G51: =NETWORKDAYS(E51,F51,Feriados) -> 5 | H51: =Historias!N11 -> 1 | I51: =Historias!P11 -> Terminada
A52: T-2.10 | B52: Corrección y reenvío por el creador, con retorno a estado Pendiente | C52: Tarea | D52: Matías | E52: =Tareas!H37 -> 46286 | F52: =Tareas!I37 -> 46290 | G52: =NETWORKDAYS(E52,F52,Feriados) -> 5 | H52: =Tareas!K37 -> 1 | I52: =Tareas!J37 -> Terminado
A53: T-2.11 | B53: Vista de seguimiento con estado, responsable, fecha y comentario | C53: Tarea | D53: Millaray | E53: =Tareas!H38 -> 46286 | F53: =Tareas!I38 -> 46290 | G53: =NETWORKDAYS(E53,F53,Feriados) -> 5 | H53: =Tareas!K38 -> 1 | I53: =Tareas!J38 -> Terminado
A54: T-2.12 | B54: Filtros y búsqueda por estado, fecha, área y responsable, según permisos | C54: Tarea | D54: Millaray | E54: =Tareas!H39 -> 46286 | F54: =Tareas!I39 -> 46290 | G54: =NETWORKDAYS(E54,F54,Feriados) -> 5 | H54: =Tareas!K39 -> 1 | I54: =Tareas!J39 -> Terminado
A55: T-2.13 | B55: Pruebas automatizadas y ejecución de CP-023 a CP-026 | C55: Tarea | D55: Alexssander | E55: =Tareas!H40 -> 46286 | F55: =Tareas!I40 -> 46290 | G55: =NETWORKDAYS(E55,F55,Feriados) -> 5 | H55: =Tareas!K40 -> 1 | I55: =Tareas!J40 -> Terminado
A56: HU-012 | B56: Notificar pendientes y recordatorios | C56: Historia | D56: Millaray y Matías | E56: =Historias!J12 -> 46286 | F56: =Historias!K12 -> 46290 | G56: =NETWORKDAYS(E56,F56,Feriados) -> 5 | H56: =Historias!N12 -> 1 | I56: =Historias!P12 -> Terminada
A57: T-2.14 | B57: Modelo de notificación con destinatario, categoría, emisor, nivel y enlace | C57: Tarea | D57: Alexssander | E57: =Tareas!H41 -> 46286 | F57: =Tareas!I41 -> 46290 | G57: =NETWORKDAYS(E57,F57,Feriados) -> 5 | H57: =Tareas!K41 -> 1 | I57: =Tareas!J41 -> Terminado
A58: T-2.15 | B58: Notificación a los integrantes del grupo al enviar un proceso | C58: Tarea | D58: Alexssander | E58: =Tareas!H42 -> 46286 | F58: =Tareas!I42 -> 46290 | G58: =NETWORKDAYS(E58,F58,Feriados) -> 5 | H58: =Tareas!K42 -> 1 | I58: =Tareas!J42 -> Terminado
A59: T-2.16 | B59: Tarea programada de recordatorio para procesos pendientes por más de una hora | C59: Tarea | D59: Matías | E59: =Tareas!H43 -> 46286 | F59: =Tareas!I43 -> 46290 | G59: =NETWORKDAYS(E59,F59,Feriados) -> 5 | H59: =Tareas!K43 -> 1 | I59: =Tareas!J43 -> Terminado
A60: T-2.17 | B60: Campana general en la barra superior con restricción de notificaciones ajenas | C60: Tarea | D60: Millaray | E60: =Tareas!H44 -> 46286 | F60: =Tareas!I44 -> 46290 | G60: =NETWORKDAYS(E60,F60,Feriados) -> 5 | H60: =Tareas!K44 -> 1 | I60: =Tareas!J44 -> Terminado
A61: T-2.18 | B61: Pruebas automatizadas y ejecución de CP-043 a CP-046 | C61: Tarea | D61: Matías | E61: =Tareas!H45 -> 46286 | F61: =Tareas!I45 -> 46290 | G61: =NETWORKDAYS(E61,F61,Feriados) -> 5 | H61: =Tareas!K45 -> 1 | I61: =Tareas!J45 -> Terminado
B62: Tareas transversales del sprint | C62: Historia | D62: Scrum Team | E62: =_xlfn.MINIFS(Tareas!$H:$H,Tareas!$B:$B,"Sprint 2",Tareas!$C:$C,"Transversal") -> 46286 | F62: =_xlfn.MAXIFS(Tareas!$I:$I,Tareas!$B:$B,"Sprint 2",Tareas!$C:$C,"Transversal") -> 46290 | G62: =NETWORKDAYS(E62,F62,Feriados) -> 5 | H62: =IFERROR(SUMIFS(Tareas!$L:$L,Tareas!$B:$B,"Sprint 2",Tareas!$C:$C,"Transversal")/SUMIFS(Tareas!$F:$F,Tareas!$B:$B,"Sprint 2",Tareas!$C:$C,"Transversal"),0) -> 1
A63: T-2.19 | B63: Validar el flujo de solicitudes con usuarios clave antes de la Sprint Review | C63: Tarea | D63: Millaray | E63: =Tareas!H46 -> 46286 | F63: =Tareas!I46 -> 46290 | G63: =NETWORKDAYS(E63,F63,Feriados) -> 5 | H63: =Tareas!K46 -> 1 | I63: =Tareas!J46 -> Terminado
A64: T-2.20 | B64: Integrar develop en main, etiquetar v0.2.0 y preparar la demostración | C64: Tarea | D64: Matías | E64: =Tareas!H47 -> 46286 | F64: =Tareas!I47 -> 46290 | G64: =NETWORKDAYS(E64,F64,Feriados) -> 5 | H64: =Tareas!K47 -> 1 | I64: =Tareas!J47 -> Terminado
A65: T-2.21 | B65: Actualizar la matriz de trazabilidad y el Expediente de Sprint | C65: Tarea | D65: Alexssander | E65: =Tareas!H48 -> 46286 | F65: =Tareas!I48 -> 46290 | G65: =NETWORKDAYS(E65,F65,Feriados) -> 5 | H65: =Tareas!K48 -> 1 | I65: =Tareas!J48 -> Terminado
A66: S3 | B66: Sprint 3 · Lectura SAP, consultas y cotizaciones | C66: Sprint | D66: PO: Alexssander · SM: Matías | E66: =Resumen!C10 -> 46293 | F66: =Resumen!D10 -> 46304 | G66: =NETWORKDAYS(E66,F66,Feriados) -> 10 | H66: =Resumen!L10 -> 1 | I66: =Resumen!Q10 -> Cerrado
B67: Eventos Scrum | C67: Eventos | D67: Scrum Team | J67: =IF(J$6=Eventos!$C$16,"F",IF(J$6=Eventos!$C$15,"P",IF(J$6=Eventos!$C$17,"C",IF(J$6=Eventos!$C$18,"R","")))) | K67: =IF(K$6=Eventos!$C$16,"F",IF(K$6=Eventos!$C$15,"P",IF(K$6=Eventos!$C$17,"C",IF(K$6=Eventos!$C$18,"R","")))) | L67: =IF(L$6=Eventos!$C$16,"F",IF(L$6=Eventos!$C$15,"P",IF(L$6=Eventos!$C$17,"C",IF(L$6=Eventos!$C$18,"R","")))) | M67: =IF(M$6=Eventos!$C$16,"F",IF(M$6=Eventos!$C$15,"P",IF(M$6=Eventos!$C$17,"C",IF(M$6=Eventos!$C$18,"R","")))) | N67: =IF(N$6=Eventos!$C$16,"F",IF(N$6=Eventos!$C$15,"P",IF(N$6=Eventos!$C$17,"C",IF(N$6=Eventos!$C$18,"R","")))) | O67: =IF(O$6=Eventos!$C$16,"F",IF(O$6=Eventos!$C$15,"P",IF(O$6=Eventos!$C$17,"C",IF(O$6=Eventos!$C$18,"R","")))) | P67: =IF(P$6=Eventos!$C$16,"F",IF(P$6=Eventos!$C$15,"P",IF(P$6=Eventos!$C$17,"C",IF(P$6=Eventos!$C$18,"R","")))) | Q67: =IF(Q$6=Eventos!$C$16,"F",IF(Q$6=Eventos!$C$15,"P",IF(Q$6=Eventos!$C$17,"C",IF(Q$6=Eventos!$C$18,"R","")))) | ... CF67: =IF(CF$6=Eventos!$C$16,"F",IF(CF$6=Eventos!$C$15,"P",IF(CF$6=Eventos!$C$17,"C",IF(CF$6=Eventos!$C$18,"R",""))))
A68: HU-015 | B68: Consultar SAP mediante una API segura | C68: Historia | D68: Alexssander y Matías | E68: =Historias!J13 -> 46293 | F68: =Historias!K13 -> 46297 | G68: =NETWORKDAYS(E68,F68,Feriados) -> 5 | H68: =Historias!N13 -> 1 | I68: =Historias!P13 -> Terminada
A69: T-3.01 | B69: API de lectura en FastAPI con usuario de solo lectura sobre SAP HANA y respuestas JSON | C69: Tarea | D69: Alexssander | E69: =Tareas!H49 -> 46293 | F69: =Tareas!I49 -> 46297 | G69: =NETWORKDAYS(E69,F69,Feriados) -> 5 | H69: =Tareas!K49 -> 1 | I69: =Tareas!J49 -> Terminado
A70: T-3.02 | B70: Firma de peticiones entre la plataforma y la API, con rechazo de firmas inválidas | C70: Tarea | D70: Alexssander | E70: =Tareas!H50 -> 46293 | F70: =Tareas!I50 -> 46297 | G70: =NETWORKDAYS(E70,F70,Feriados) -> 5 | H70: =Tareas!K50 -> 1 | I70: =Tareas!J50 -> Terminado
A71: T-3.03 | B71: Credenciales de conexión en variables de entorno | C71: Tarea | D71: Matías | E71: =Tareas!H51 -> 46293 | F71: =Tareas!I51 -> 46297 | G71: =NETWORKDAYS(E71,F71,Feriados) -> 5 | H71: =Tareas!K51 -> 1 | I71: =Tareas!J51 -> Terminado
A72: T-3.04 | B72: Paginación, tiempo límite, reintentos y servicio simulado con datos ficticios | C72: Tarea | D72: Matías | E72: =Tareas!H52 -> 46293 | F72: =Tareas!I52 -> 46297 | G72: =NETWORKDAYS(E72,F72,Feriados) -> 5 | H72: =Tareas!K52 -> 1 | I72: =Tareas!J52 -> Terminado
A73: T-3.05 | B73: Registro de consultas para medir la carga sobre el ERP | C73: Tarea | D73: Matías | E73: =Tareas!H53 -> 46293 | F73: =Tareas!I53 -> 46297 | G73: =NETWORKDAYS(E73,F73,Feriados) -> 5 | H73: =Tareas!K53 -> 1 | I73: =Tareas!J53 -> Terminado
A74: T-3.06 | B74: Pruebas, medición de tiempos y ejecución de CP-055 a CP-058 | C74: Tarea | D74: Matías | E74: =Tareas!H54 -> 46293 | F74: =Tareas!I54 -> 46297 | G74: =NETWORKDAYS(E74,F74,Feriados) -> 5 | H74: =Tareas!K54 -> 1 | I74: =Tareas!J54 -> Terminado
A75: HU-008 | B75: Consultar productos, stock y clientes | C75: Historia | D75: Alexssander y Millaray | E75: =Historias!J14 -> 46293 | F75: =Historias!K14 -> 46297 | G75: =NETWORKDAYS(E75,F75,Feriados) -> 5 | H75: =Historias!N14 -> 1 | I75: =Historias!P14 -> Terminada
A76: T-3.07 | B76: Cliente de la API en la plataforma para productos, stock y clientes de la empresa activa | C76: Tarea | D76: Alexssander | E76: =Tareas!H55 -> 46293 | F76: =Tareas!I55 -> 46297 | G76: =NETWORKDAYS(E76,F76,Feriados) -> 5 | H76: =Tareas!K55 -> 1 | I76: =Tareas!J55 -> Terminado
A77: T-3.08 | B77: Pantallas de consulta de productos y stock | C77: Tarea | D77: Millaray | E77: =Tareas!H56 -> 46293 | F77: =Tareas!I56 -> 46297 | G77: =NETWORKDAYS(E77,F77,Feriados) -> 5 | H77: =Tareas!K56 -> 1 | I77: =Tareas!J56 -> Terminado
A78: T-3.09 | B78: Consulta de clientes con crédito y bloqueo, según la cartera del vendedor o asistente | C78: Tarea | D78: Millaray | E78: =Tareas!H57 -> 46293 | F78: =Tareas!I57 -> 46297 | G78: =NETWORKDAYS(E78,F78,Feriados) -> 5 | H78: =Tareas!K57 -> 1 | I78: =Tareas!J57 -> Terminado
A79: T-3.10 | B79: Indicador visible de cliente bloqueado | C79: Tarea | D79: Millaray | E79: =Tareas!H58 -> 46293 | F79: =Tareas!I58 -> 46297 | G79: =NETWORKDAYS(E79,F79,Feriados) -> 5 | H79: =Tareas!K58 -> 1 | I79: =Tareas!J58 -> Terminado
A80: T-3.11 | B80: Pruebas automatizadas y ejecución de CP-027 a CP-030 | C80: Tarea | D80: Matías | E80: =Tareas!H59 -> 46293 | F80: =Tareas!I59 -> 46297 | G80: =NETWORKDAYS(E80,F80,Feriados) -> 5 | H80: =Tareas!K59 -> 1 | I80: =Tareas!J59 -> Terminado
A81: HU-009 | B81: Crear y administrar cotizaciones | C81: Historia | D81: Millaray y Alexssander | E81: =Historias!J15 -> 46300 | F81: =Historias!K15 -> 46304 | G81: =NETWORKDAYS(E81,F81,Feriados) -> 5 | H81: =Historias!N15 -> 1 | I81: =Historias!P15 -> Terminada
A82: T-3.12 | B82: Modelos de cotización y líneas, con sus migraciones | C82: Tarea | D82: Alexssander | E82: =Tareas!H60 -> 46300 | F82: =Tareas!I60 -> 46304 | G82: =NETWORKDAYS(E82,F82,Feriados) -> 5 | H82: =Tareas!K60 -> 1 | I82: =Tareas!J60 -> Terminado
A83: T-3.13 | B83: Formulario de cotización con validación de cliente y líneas | C83: Tarea | D83: Millaray | E83: =Tareas!H61 -> 46300 | F83: =Tareas!I61 -> 46304 | G83: =NETWORKDAYS(E83,F83,Feriados) -> 5 | H83: =Tareas!K61 -> 1 | I83: =Tareas!J61 -> Terminado
A84: T-3.14 | B84: Selección de SlpCode por el asistente y registro de creador y vendedor | C84: Tarea | D84: Alexssander | E84: =Tareas!H62 -> 46300 | F84: =Tareas!I62 -> 46304 | G84: =NETWORKDAYS(E84,F84,Feriados) -> 5 | H84: =Tareas!K62 -> 1 | I84: =Tareas!J62 -> Terminado
A85: T-3.15 | B85: Cálculo de la comisión con la escala del vendedor o la predeterminada | C85: Tarea | D85: Alexssander | E85: =Tareas!H63 -> 46300 | F85: =Tareas!I63 -> 46304 | G85: =NETWORKDAYS(E85,F85,Feriados) -> 5 | H85: =Tareas!K63 -> 1 | I85: =Tareas!J63 -> Terminado
A86: T-3.16 | B86: Pruebas automatizadas y ejecución de CP-031 a CP-034 | C86: Tarea | D86: Matías | E86: =Tareas!H64 -> 46300 | F86: =Tareas!I64 -> 46304 | G86: =NETWORKDAYS(E86,F86,Feriados) -> 5 | H86: =Tareas!K64 -> 1 | I86: =Tareas!J64 -> Terminado
A87: HU-013 | B87: Informar cambios de estado al solicitante | C87: Historia | D87: Millaray y Matías | E87: =Historias!J16 -> 46300 | F87: =Historias!K16 -> 46304 | G87: =NETWORKDAYS(E87,F87,Feriados) -> 5 | H87: =Historias!N16 -> 1 | I87: =Historias!P16 -> Terminada
A88: T-3.17 | B88: Notificaciones al participante ante aprobaciones, rechazos, observaciones y cambios de estado | C88: Tarea | D88: Matías | E88: =Tareas!H65 -> 46300 | F88: =Tareas!I65 -> 46304 | G88: =NETWORKDAYS(E88,F88,Feriados) -> 5 | H88: =Tareas!K65 -> 1 | I88: =Tareas!J65 -> Terminado
A89: T-3.18 | B89: Campana de autorizaciones de órdenes de venta | C89: Tarea | D89: Millaray | E89: =Tareas!H66 -> 46300 | F89: =Tareas!I66 -> 46304 | G89: =NETWORKDAYS(E89,F89,Feriados) -> 5 | H89: =Tareas!K66 -> 1 | I89: =Tareas!J66 -> Terminado
A90: T-3.19 | B90: Página de notificaciones: abrir, marcar como leída, marcar todas y eliminar, con fecha de lectura | C90: Tarea | D90: Millaray | E90: =Tareas!H67 -> 46300 | F90: =Tareas!I67 -> 46304 | G90: =NETWORKDAYS(E90,F90,Feriados) -> 5 | H90: =Tareas!K67 -> 1 | I90: =Tareas!J67 -> Terminado
A91: T-3.20 | B91: Pruebas automatizadas y ejecución de CP-047 a CP-050 | C91: Tarea | D91: Alexssander | E91: =Tareas!H68 -> 46300 | F91: =Tareas!I68 -> 46304 | G91: =NETWORKDAYS(E91,F91,Feriados) -> 5 | H91: =Tareas!K68 -> 1 | I91: =Tareas!J68 -> Terminado
B92: Tareas transversales del sprint | C92: Historia | D92: Scrum Team | E92: =_xlfn.MINIFS(Tareas!$H:$H,Tareas!$B:$B,"Sprint 3",Tareas!$C:$C,"Transversal") -> 46300 | F92: =_xlfn.MAXIFS(Tareas!$I:$I,Tareas!$B:$B,"Sprint 3",Tareas!$C:$C,"Transversal") -> 46304 | G92: =NETWORKDAYS(E92,F92,Feriados) -> 5 | H92: =IFERROR(SUMIFS(Tareas!$L:$L,Tareas!$B:$B,"Sprint 3",Tareas!$C:$C,"Transversal")/SUMIFS(Tareas!$F:$F,Tareas!$B:$B,"Sprint 3",Tareas!$C:$C,"Transversal"),0) -> 1
A93: T-3.21 | B93: Pruebas de regresión de los módulos de usuarios y solicitudes | C93: Tarea | D93: Matías | E93: =Tareas!H69 -> 46300 | F93: =Tareas!I69 -> 46304 | G93: =NETWORKDAYS(E93,F93,Feriados) -> 5 | H93: =Tareas!K69 -> 1 | I93: =Tareas!J69 -> Terminado
A94: T-3.22 | B94: Validar consultas y cotizaciones con la Jefatura Comercial y los ejecutivos comerciales | C94: Tarea | D94: Alexssander | E94: =Tareas!H70 -> 46300 | F94: =Tareas!I70 -> 46304 | G94: =NETWORKDAYS(E94,F94,Feriados) -> 5 | H94: =Tareas!K70 -> 1 | I94: =Tareas!J70 -> Terminado
A95: T-3.23 | B95: Integrar develop en main, etiquetar v0.3.0 y preparar la demostración | C95: Tarea | D95: Millaray | E95: =Tareas!H71 -> 46300 | F95: =Tareas!I71 -> 46304 | G95: =NETWORKDAYS(E95,F95,Feriados) -> 5 | H95: =Tareas!K71 -> 1 | I95: =Tareas!J71 -> Terminado
A96: T-3.24 | B96: Actualizar la matriz de trazabilidad y el Expediente de Sprint | C96: Tarea | D96: Matías | E96: =Tareas!H72 -> 46300 | F96: =Tareas!I72 -> 46304 | G96: =NETWORKDAYS(E96,F96,Feriados) -> 5 | H96: =Tareas!K72 -> 1 | I96: =Tareas!J72 -> Terminado
A97: S4 | B97: Sprint 4 · Órdenes de venta e integración SAP | C97: Sprint | D97: PO: Matías · SM: Millaray | E97: =Resumen!C11 -> 46308 | F97: =Resumen!D11 -> 46318 | G97: =NETWORKDAYS(E97,F97,Feriados) -> 9 | H97: =Resumen!L11 -> 0 | I97: =Resumen!Q11 -> Planificado
B98: Eventos Scrum | C98: Eventos | D98: Scrum Team | J98: =IF(J$6=Eventos!$C$21,"F",IF(J$6=Eventos!$C$20,"P",IF(J$6=Eventos!$C$22,"C",IF(J$6=Eventos!$C$23,"R","")))) | K98: =IF(K$6=Eventos!$C$21,"F",IF(K$6=Eventos!$C$20,"P",IF(K$6=Eventos!$C$22,"C",IF(K$6=Eventos!$C$23,"R","")))) | L98: =IF(L$6=Eventos!$C$21,"F",IF(L$6=Eventos!$C$20,"P",IF(L$6=Eventos!$C$22,"C",IF(L$6=Eventos!$C$23,"R","")))) | M98: =IF(M$6=Eventos!$C$21,"F",IF(M$6=Eventos!$C$20,"P",IF(M$6=Eventos!$C$22,"C",IF(M$6=Eventos!$C$23,"R","")))) | N98: =IF(N$6=Eventos!$C$21,"F",IF(N$6=Eventos!$C$20,"P",IF(N$6=Eventos!$C$22,"C",IF(N$6=Eventos!$C$23,"R","")))) | O98: =IF(O$6=Eventos!$C$21,"F",IF(O$6=Eventos!$C$20,"P",IF(O$6=Eventos!$C$22,"C",IF(O$6=Eventos!$C$23,"R","")))) | P98: =IF(P$6=Eventos!$C$21,"F",IF(P$6=Eventos!$C$20,"P",IF(P$6=Eventos!$C$22,"C",IF(P$6=Eventos!$C$23,"R","")))) | Q98: =IF(Q$6=Eventos!$C$21,"F",IF(Q$6=Eventos!$C$20,"P",IF(Q$6=Eventos!$C$22,"C",IF(Q$6=Eventos!$C$23,"R","")))) | ... CF98: =IF(CF$6=Eventos!$C$21,"F",IF(CF$6=Eventos!$C$20,"P",IF(CF$6=Eventos!$C$22,"C",IF(CF$6=Eventos!$C$23,"R",""))))
A99: HU-010 | B99: Emitir la cotización y solicitar la orden de venta | C99: Historia | D99: Millaray y Alexssander | E99: =Historias!J17 -> 46308 | F99: =Historias!K17 -> 46311 | G99: =NETWORKDAYS(E99,F99,Feriados) -> 4 | H99: =Historias!N17 -> 0 | I99: =Historias!P17 -> Por hacer
A100: T-4.01 | B100: Generación de la cotización en formato imprimible o descargable | C100: Tarea | D100: Millaray | E100: =Tareas!H73 -> 46308 | F100: =Tareas!I73 -> 46311 | G100: =NETWORKDAYS(E100,F100,Feriados) -> 4 | H100: =Tareas!K73 -> 0 | I100: =Tareas!J73 -> Por hacer
...

Sheet Tareas
A1: Tareas del Sprint Backlog
A2: Lista maestra de tareas de todos los sprints. Actualice la columna Estado; las fechas se calculan desde las fechas del sprint.
A4: ID | B4: Sprint | C4: Historia | D4: Tarea | E4: Responsable | F4: Horas | G4: Semana | H4: Inicio | I4: Término | J4: Estado | K4: % avance | L4: Horas avanzadas | M4: Observaciones
A5: T-1.01 | B5: Sprint 1 | C5: HU-001 | D5: Configurar el inicio y cierre de sesión con la autenticación de Django y la pantalla de acceso | E5: Matías Orellana | F5: 3 | G5: 1 | H5: =IF($G5=1,INDEX(SprintInicio,MATCH($B5,SprintNombres,0)),INDEX(SprintInicio,MATCH($B5,SprintNombres,0))+8-WEEKDAY(INDEX(SprintInicio,MATCH($B5,SprintNombres,0)),2)) -> 46265 | I5: =IF($G5=1,MIN(INDEX(SprintInicio,MATCH($B5,SprintNombres,0))+5-WEEKDAY(INDEX(SprintInicio,MATCH($B5,SprintNombres,0)),2),INDEX(SprintFin,MATCH($B5,SprintNombres,0))),INDEX(SprintFin,MATCH($B5,SprintNombres,0))) -> 46269 | J5: Terminado | K5: =IFERROR(VLOOKUP($J5,EstadosAvance,2,FALSE()),0) -> 1 | L5: =F5*K5 -> 3
A6: T-1.02 | B6: Sprint 1 | C6: HU-001 | D6: Bloquear el acceso de usuarios desactivados y mostrar mensajes de error claros | E6: Matías Orellana | F6: 2 | G6: 1 | H6: =IF($G6=1,INDEX(SprintInicio,MATCH($B6,SprintNombres,0)),INDEX(SprintInicio,MATCH($B6,SprintNombres,0))+8-WEEKDAY(INDEX(SprintInicio,MATCH($B6,SprintNombres,0)),2)) -> 46265 | I6: =IF($G6=1,MIN(INDEX(SprintInicio,MATCH($B6,SprintNombres,0))+5-WEEKDAY(INDEX(SprintInicio,MATCH($B6,SprintNombres,0)),2),INDEX(SprintFin,MATCH($B6,SprintNombres,0))),INDEX(SprintFin,MATCH($B6,SprintNombres,0))) -> 46269 | J6: Terminado | K6: =IFERROR(VLOOKUP($J6,EstadosAvance,2,FALSE()),0) -> 1 | L6: =F6*K6 -> 2
A7: T-1.03 | B7: Sprint 1 | C7: HU-001 | D7: Configurar el hash de contraseñas y la expiración de la sesión por inactividad | E7: Alexssander López | F7: 2 | G7: 1 | H7: =IF($G7=1,INDEX(SprintInicio,MATCH($B7,SprintNombres,0)),INDEX(SprintInicio,MATCH($B7,SprintNombres,0))+8-WEEKDAY(INDEX(SprintInicio,MATCH($B7,SprintNombres,0)),2)) -> 46265 | I7: =IF($G7=1,MIN(INDEX(SprintInicio,MATCH($B7,SprintNombres,0))+5-WEEKDAY(INDEX(SprintInicio,MATCH($B7,SprintNombres,0)),2),INDEX(SprintFin,MATCH($B7,SprintNombres,0))),INDEX(SprintFin,MATCH($B7,SprintNombres,0))) -> 46269 | J7: Terminado | K7: =IFERROR(VLOOKUP($J7,EstadosAvance,2,FALSE()),0) -> 1 | L7: =F7*K7 -> 2
A8: T-1.04 | B8: Sprint 1 | C8: HU-001 | D8: Registrar la auditoría de accesos e intentos fallidos | E8: Alexssander López | F8: 3 | G8: 1 | H8: =IF($G8=1,INDEX(SprintInicio,MATCH($B8,SprintNombres,0)),INDEX(SprintInicio,MATCH($B8,SprintNombres,0))+8-WEEKDAY(INDEX(SprintInicio,MATCH($B8,SprintNombres,0)),2)) -> 46265 | I8: =IF($G8=1,MIN(INDEX(SprintInicio,MATCH($B8,SprintNombres,0))+5-WEEKDAY(INDEX(SprintInicio,MATCH($B8,SprintNombres,0)),2),INDEX(SprintFin,MATCH($B8,SprintNombres,0))),INDEX(SprintFin,MATCH($B8,SprintNombres,0))) -> 46269 | J8: Terminado | K8: =IFERROR(VLOOKUP($J8,EstadosAvance,2,FALSE()),0) -> 1 | L8: =F8*K8 -> 3
A9: T-1.05 | B9: Sprint 1 | C9: HU-001 | D9: Pruebas automatizadas y ejecución de CP-001 a CP-003 | E9: Millaray Espósito | F9: 2 | G9: 1 | H9: =IF($G9=1,INDEX(SprintInicio,MATCH($B9,SprintNombres,0)),INDEX(SprintInicio,MATCH($B9,SprintNombres,0))+8-WEEKDAY(INDEX(SprintInicio,MATCH($B9,SprintNombres,0)),2)) -> 46265 | I9: =IF($G9=1,MIN(INDEX(SprintInicio,MATCH($B9,SprintNombres,0))+5-WEEKDAY(INDEX(SprintInicio,MATCH($B9,SprintNombres,0)),2),INDEX(SprintFin,MATCH($B9,SprintNombres,0))),INDEX(SprintFin,MATCH($B9,SprintNombres,0))) -> 46269 | J9: Terminado | K9: =IFERROR(VLOOKUP($J9,EstadosAvance,2,FALSE()),0) -> 1 | L9: =F9*K9 -> 2
A10: T-1.06 | B10: Sprint 1 | C10: HU-002 | D10: Modelos de área, cargo, rol y perfil de usuario, con sus migraciones | E10: Alexssander López | F10: 4 | G10: 1 | H10: =IF($G10=1,INDEX(SprintInicio,MATCH($B10,SprintNombres,0)),INDEX(SprintInicio,MATCH($B10,SprintNombres,0))+8-WEEKDAY(INDEX(SprintInicio,MATCH($B10,SprintNombres,0)),2)) -> 46265 | I10: =IF($G10=1,MIN(INDEX(SprintInicio,MATCH($B10,SprintNombres,0))+5-WEEKDAY(INDEX(SprintInicio,MATCH($B10,SprintNombres,0)),2),INDEX(SprintFin,MATCH($B10,SprintNombres,0))),INDEX(SprintFin,MATCH($B10,SprintNombres,0))) -> 46269 | J10: Terminado | K10: =IFERROR(VLOOKUP($J10,EstadosAvance,2,FALSE()),0) -> 1 | L10: =F10*K10 -> 4
A11: T-1.07 | B11: Sprint 1 | C11: HU-002 | D11: Mantenedor de usuarios con área, cargo y rol obligatorios | E11: Matías Orellana | F11: 5 | G11: 1 | H11: =IF($G11=1,INDEX(SprintInicio,MATCH($B11,SprintNombres,0)),INDEX(SprintInicio,MATCH($B11,SprintNombres,0))+8-WEEKDAY(INDEX(SprintInicio,MATCH($B11,SprintNombres,0)),2)) -> 46265 | I11: =IF($G11=1,MIN(INDEX(SprintInicio,MATCH($B11,SprintNombres,0))+5-WEEKDAY(INDEX(SprintInicio,MATCH($B11,SprintNombres,0)),2),INDEX(SprintFin,MATCH($B11,SprintNombres,0))),INDEX(SprintFin,MATCH($B11,SprintNombres,0))) -> 46269 | J11: Terminado | K11: =IFERROR(VLOOKUP($J11,EstadosAvance,2,FALSE()),0) -> 1 | L11: =F11*K11 -> 5
A12: T-1.08 | B12: Sprint 1 | C12: HU-002 | D12: Desactivación y reactivación de usuarios conservando su historial | E12: Matías Orellana | F12: 2 | G12: 1 | H12: =IF($G12=1,INDEX(SprintInicio,MATCH($B12,SprintNombres,0)),INDEX(SprintInicio,MATCH($B12,SprintNombres,0))+8-WEEKDAY(INDEX(SprintInicio,MATCH($B12,SprintNombres,0)),2)) -> 46265 | I12: =IF($G12=1,MIN(INDEX(SprintInicio,MATCH($B12,SprintNombres,0))+5-WEEKDAY(INDEX(SprintInicio,MATCH($B12,SprintNombres,0)),2),INDEX(SprintFin,MATCH($B12,SprintNombres,0))),INDEX(SprintFin,MATCH($B12,SprintNombres,0))) -> 46269 | J12: Terminado | K12: =IFERROR(VLOOKUP($J12,EstadosAvance,2,FALSE()),0) -> 1 | L12: =F12*K12 -> 2
A13: T-1.09 | B13: Sprint 1 | C13: HU-002 | D13: Restringir la administración de usuarios al administrador, validado en el servidor | E13: Alexssander López | F13: 2 | G13: 1 | H13: =IF($G13=1,INDEX(SprintInicio,MATCH($B13,SprintNombres,0)),INDEX(SprintInicio,MATCH($B13,SprintNombres,0))+8-WEEKDAY(INDEX(SprintInicio,MATCH($B13,SprintNombres,0)),2)) -> 46265 | I13: =IF($G13=1,MIN(INDEX(SprintInicio,MATCH($B13,SprintNombres,0))+5-WEEKDAY(INDEX(SprintInicio,MATCH($B13,SprintNombres,0)),2),INDEX(SprintFin,MATCH($B13,SprintNombres,0))),INDEX(SprintFin,MATCH($B13,SprintNombres,0))) -> 46269 | J13: Terminado | K13: =IFERROR(VLOOKUP($J13,EstadosAvance,2,FALSE()),0) -> 1 | L13: =F13*K13 -> 2
A14: T-1.10 | B14: Sprint 1 | C14: HU-002 | D14: Pruebas automatizadas y ejecución de CP-004 a CP-006 | E14: Millaray Espósito | F14: 3 | G14: 1 | H14: =IF($G14=1,INDEX(SprintInicio,MATCH($B14,SprintNombres,0)),INDEX(SprintInicio,MATCH($B14,SprintNombres,0))+8-WEEKDAY(INDEX(SprintInicio,MATCH($B14,SprintNombres,0)),2)) -> 46265 | I14: =IF($G14=1,MIN(INDEX(SprintInicio,MATCH($B14,SprintNombres,0))+5-WEEKDAY(INDEX(SprintInicio,MATCH($B14,SprintNombres,0)),2),INDEX(SprintFin,MATCH($B14,SprintNombres,0))),INDEX(SprintFin,MATCH($B14,SprintNombres,0))) -> 46269 | J14: Terminado | K14: =IFERROR(VLOOKUP($J14,EstadosAvance,2,FALSE()),0) -> 1 | L14: =F14*K14 -> 3
A15: T-1.11 | B15: Sprint 1 | C15: HU-003 | D15: Modelo de permisos directos, por área y por cargo, y cálculo de permisos efectivos | E15: Alexssander López | F15: 5 | G15: 2 | H15: =IF($G15=1,INDEX(SprintInicio,MATCH($B15,SprintNombres,0)),INDEX(SprintInicio,MATCH($B15,SprintNombres,0))+8-WEEKDAY(INDEX(SprintInicio,MATCH($B15,SprintNombres,0)),2)) -> 46272 | I15: =IF($G15=1,MIN(INDEX(SprintInicio,MATCH($B15,SprintNombres,0))+5-WEEKDAY(INDEX(SprintInicio,MATCH($B15,SprintNombres,0)),2),INDEX(SprintFin,MATCH($B15,SprintNombres,0))),INDEX(SprintFin,MATCH($B15,SprintNombres,0))) -> 46276 | J15: Terminado | K15: =IFERROR(VLOOKUP($J15,EstadosAvance,2,FALSE()),0) -> 1 | L15: =F15*K15 -> 5
A16: T-1.12 | B16: Sprint 1 | C16: HU-003 | D16: Validación centralizada de permisos en el servidor para cada vista | E16: Matías Orellana | F16: 3 | G16: 2 | H16: =IF($G16=1,INDEX(SprintInicio,MATCH($B16,SprintNombres,0)),INDEX(SprintInicio,MATCH($B16,SprintNombres,0))+8-WEEKDAY(INDEX(SprintInicio,MATCH($B16,SprintNombres,0)),2)) -> 46272 | I16: =IF($G16=1,MIN(INDEX(SprintInicio,MATCH($B16,SprintNombres,0))+5-WEEKDAY(INDEX(SprintInicio,MATCH($B16,SprintNombres,0)),2),INDEX(SprintFin,MATCH($B16,SprintNombres,0))),INDEX(SprintFin,MATCH($B16,SprintNombres,0))) -> 46276 | J16: Terminado | K16: =IFERROR(VLOOKUP($J16,EstadosAvance,2,FALSE()),0) -> 1 | L16: =F16*K16 -> 3
... A124: T-6.10 | B124: Sprint 6 | C124: Transversal | D124: Actualizar la matriz de trazabilidad y el Expediente de Sprint | E124: Matías Orellana | F124: 1 | G124: 1 | H124: =IF($G124=1,INDEX(SprintInicio,MATCH($B124,SprintNombres,0)),INDEX(SprintInicio,MATCH($B124,SprintNombres,0))+8-WEEKDAY(INDEX(SprintInicio,MATCH($B124,SprintNombres,0)),2)) -> 46335 | I124: =IF($G124=1,MIN(INDEX(SprintInicio,MATCH($B124,SprintNombres,0))+5-WEEKDAY(INDEX(SprintInicio,MATCH($B124,SprintNombres,0)),2),INDEX(SprintFin,MATCH($B124,SprintNombres,0))),INDEX(SprintFin,MATCH($B124,SprintNombres,0))) -> 46339 | J124: Por hacer | K124: =IFERROR(VLOOKUP($J124,EstadosAvance,2,FALSE()),0) -> 0 | L124: =F124*K124 -> 0

Sheet Historias
A1: Historias de usuario por sprint
A2: Fechas y avance calculados desde la hoja Tareas. Marque «Aceptada por PO» en la Sprint Review.
A4: ID | B4: Título | C4: Épica | D4: Sprint | E4: SP | F4: Prioridad | G4: Dependencias | H4: Responsables | I4: Casos de prueba | J4: Inicio | K4: Término | L4: Horas | M4: Horas avanzadas | N4: % avance | O4: Aceptada por PO | P4: Estado
A5: HU-001 | B5: Autenticarse en la plataforma | C5: EP-01 | D5: Sprint 1 | E5: 5 | F5: Alta | G5: Ninguna | H5: Matías y Alexssander | I5: CP-001 a CP-003 | J5: =_xlfn.MINIFS(Tareas!$H:$H,Tareas!$C:$C,$A5) -> 46265 | K5: =_xlfn.MAXIFS(Tareas!$I:$I,Tareas!$C:$C,$A5) -> 46269 | L5: =SUMIFS(Tareas!$F:$F,Tareas!$C:$C,$A5) -> 12 | M5: =SUMIFS(Tareas!$L:$L,Tareas!$C:$C,$A5) -> 12 | N5: =IFERROR(M5/L5,0) -> 1 | O5: Sí | P5: =IF(AND(N5>=1,O5="Sí"),"Terminada",IF(N5>=1,"Por aceptar",IF(N5>0,"En curso","Por hacer"))) -> Terminada
A6: HU-002 | B6: Administrar usuarios y perfiles | C6: EP-01 | D6: Sprint 1 | E6: 8 | F6: Alta | G6: HU-001 | H6: Matías y Alexssander | I6: CP-004 a CP-006 | J6: =_xlfn.MINIFS(Tareas!$H:$H,Tareas!$C:$C,$A6) -> 46265 | K6: =_xlfn.MAXIFS(Tareas!$I:$I,Tareas!$C:$C,$A6) -> 46269 | L6: =SUMIFS(Tareas!$F:$F,Tareas!$C:$C,$A6) -> 16 | M6: =SUMIFS(Tareas!$L:$L,Tareas!$C:$C,$A6) -> 16 | N6: =IFERROR(M6/L6,0) -> 1 | O6: Sí | P6: =IF(AND(N6>=1,O6="Sí"),"Terminada",IF(N6>=1,"Por aceptar",IF(N6>0,"En curso","Por hacer"))) -> Terminada
A7: HU-003 | B7: Configurar permisos y grupos de autorización | C7: EP-01 | D7: Sprint 1 | E7: 8 | F7: Alta | G7: HU-002 | H7: Matías y Alexssander | I7: CP-007 a CP-010 | J7: =_xlfn.MINIFS(Tareas!$H:$H,Tareas!$C:$C,$A7) -> 46272 | K7: =_xlfn.MAXIFS(Tareas!$I:$I,Tareas!$C:$C,$A7) -> 46276 | L7: =SUMIFS(Tareas!$F:$F,Tareas!$C:$C,$A7) -> 18 | M7: =SUMIFS(Tareas!$L:$L,Tareas!$C:$C,$A7) -> 18 | N7: =IFERROR(M7/L7,0) -> 1 | O7: Sí | P7: =IF(AND(N7>=1,O7="Sí"),"Terminada",IF(N7>=1,"Por aceptar",IF(N7>0,"En curso","Por hacer"))) -> Terminada
A8: HU-004 | B8: Configurar empresas, vendedores y comisiones | C8: EP-01 | D8: Sprint 1 | E8: 8 | F8: Alta | G8: HU-002, HU-003 | H8: Matías y Alexssander | I8: CP-011 a CP-014 | J8: =_xlfn.MINIFS(Tareas!$H:$H,Tareas!$C:$C,$A8) -> 46272 | K8: =_xlfn.MAXIFS(Tareas!$I:$I,Tareas!$C:$C,$A8) -> 46276 | L8: =SUMIFS(Tareas!$F:$F,Tareas!$C:$C,$A8) -> 14 | M8: =SUMIFS(Tareas!$L:$L,Tareas!$C:$C,$A8) -> 14 | N8: =IFERROR(M8/L8,0) -> 1 | O8: Sí | P8: =IF(AND(N8>=1,O8="Sí"),"Terminada",IF(N8>=1,"Por aceptar",IF(N8>0,"En curso","Por hacer"))) -> Terminada
A9: HU-005 | B9: Crear y enviar solicitudes de código | C9: EP-02 | D9: Sprint 2 | E9: 8 | F9: Alta | G9: HU-003, HU-004 | H9: Millaray y Matías | I9: CP-015 a CP-018 | J9: =_xlfn.MINIFS(Tareas!$H:$H,Tareas!$C:$C,$A9) -> 46279 | K9: =_xlfn.MAXIFS(Tareas!$I:$I,Tareas!$C:$C,$A9) -> 46283 | L9: =SUMIFS(Tareas!$F:$F,Tareas!$C:$C,$A9) -> 17 | M9: =SUMIFS(Tareas!$L:$L,Tareas!$C:$C,$A9) -> 17 | N9: =IFERROR(M9/L9,0) -> 1 | O9: Sí | P9: =IF(AND(N9>=1,O9="Sí"),"Terminada",IF(N9>=1,"Por aceptar",IF(N9>0,"En curso","Por hacer"))) -> Terminada
A10: HU-006 | B10: Aprobar o rechazar solicitudes | C10: EP-02 | D10: Sprint 2 | E10: 5 | F10: Alta | G10: HU-005 | H10: Millaray y Matías | I10: CP-019 a CP-022 | J10: =_xlfn.MINIFS(Tareas!$H:$H,Tareas!$C:$C,$A10) -> 46279 | K10: =_xlfn.MAXIFS(Tareas!$I:$I,Tareas!$C:$C,$A10) -> 46283 | L10: =SUMIFS(Tareas!$F:$F,Tareas!$C:$C,$A10) -> 10 | M10: =SUMIFS(Tareas!$L:$L,Tareas!$C:$C,$A10) -> 10 | N10: =IFERROR(M10/L10,0) -> 1 | O10: Sí | P10: =IF(AND(N10>=1,O10="Sí"),"Terminada",IF(N10>=1,"Por aceptar",IF(N10>0,"En curso","Por hacer"))) -> Terminada
A11: HU-007 | B11: Corregir, reenviar y consultar solicitudes | C11: EP-02 | D11: Sprint 2 | E11: 8 | F11: Alta | G11: HU-006 | H11: Millaray y Matías | I11: CP-023 a CP-026 | J11: =_xlfn.MINIFS(Tareas!$H:$H,Tareas!$C:$C,$A11) -> 46286 | K11: =_xlfn.MAXIFS(Tareas!$I:$I,Tareas!$C:$C,$A11) -> 46290 | L11: =SUMIFS(Tareas!$F:$F,Tareas!$C:$C,$A11) -> 12 | M11: =SUMIFS(Tareas!$L:$L,Tareas!$C:$C,$A11) -> 12 | N11: =IFERROR(M11/L11,0) -> 1 | O11: Sí | P11: =IF(AND(N11>=1,O11="Sí"),"Terminada",IF(N11>=1,"Por aceptar",IF(N11>0,"En curso","Por hacer"))) -> Terminada
A12: HU-012 | B12: Notificar pendientes y recordatorios | C12: EP-04 | D12: Sprint 2 | E12: 5 | F12: Alta | G12: HU-005, HU-006 | H12: Millaray y Matías | I12: CP-043 a CP-046 | J12: =_xlfn.MINIFS(Tareas!$H:$H,Tareas!$C:$C,$A12) -> 46286 | K12: =_xlfn.MAXIFS(Tareas!$I:$I,Tareas!$C:$C,$A12) -> 46290 | L12: =SUMIFS(Tareas!$F:$F,Tareas!$C:$C,$A12) -> 11 | M12: =SUMIFS(Tareas!$L:$L,Tareas!$C:$C,$A12) -> 11 | N12: =IFERROR(M12/L12,0) -> 1 | O12: Sí | P12: =IF(AND(N12>=1,O12="Sí"),"Terminada",IF(N12>=1,"Por aceptar",IF(N12>0,"En curso","Por hacer"))) -> Terminada
A13: HU-015 | B13: Consultar SAP mediante una API segura | C13: EP-05 | D13: Sprint 3 | E13: 8 | F13: Alta | G13: HU-003, HU-004 | H13: Alexssander y Matías | I13: CP-055 a CP-058 | J13: =_xlfn.MINIFS(Tareas!$H:$H,Tareas!$C:$C,$A13) -> 46293 | K13: =_xlfn.MAXIFS(Tareas!$I:$I,Tareas!$C:$C,$A13) -> 46297 | L13: =SUMIFS(Tareas!$F:$F,Tareas!$C:$C,$A13) -> 16 | M13: =SUMIFS(Tareas!$L:$L,Tareas!$C:$C,$A13) -> 16 | N13: =IFERROR(M13/L13,0) -> 1 | O13: Sí | P13: =IF(AND(N13>=1,O13="Sí"),"Terminada",IF(N13>=1,"Por aceptar",IF(N13>0,"En curso","Por hacer"))) -> Terminada
A14: HU-008 | B14: Consultar productos, stock y clientes | C14: EP-03 | D14: Sprint 3 | E14: 8 | F14: Alta | G14: HU-004, HU-015 | H14: Alexssander y Millaray | I14: CP-027 a CP-030 | J14: =_xlfn.MINIFS(Tareas!$H:$H,Tareas!$C:$C,$A14) -> 46293 | K14: =_xlfn.MAXIFS(Tareas!$I:$I,Tareas!$C:$C,$A14) -> 46297 | L14: =SUMIFS(Tareas!$F:$F,Tareas!$C:$C,$A14) -> 12 | M14: =SUMIFS(Tareas!$L:$L,Tareas!$C:$C,$A14) -> 12 | N14: =IFERROR(M14/L14,0) -> 1 | O14: Sí | P14: =IF(AND(N14>=1,O14="Sí"),"Terminada",IF(N14>=1,"Por aceptar",IF(N14>0,"En curso","Por hacer"))) -> Terminada
A15: HU-009 | B15: Crear y administrar cotizaciones | C15: EP-03 | D15: Sprint 3 | E15: 8 | F15: Alta | G15: HU-004, HU-008 | H15: Millaray y Alexssander | I15: CP-031 a CP-034 | J15: =_xlfn.MINIFS(Tareas!$H:$H,Tareas!$C:$C,$A15) -> 46300 | K15: =_xlfn.MAXIFS(Tareas!$I:$I,Tareas!$C:$C,$A15) -> 46304 | L15: =SUMIFS(Tareas!$F:$F,Tareas!$C:$C,$A15) -> 14 | M15: =SUMIFS(Tareas!$L:$L,Tareas!$C:$C,$A15) -> 14 | N15: =IFERROR(M15/L15,0) -> 1 | O15: Sí | P15: =IF(AND(N15>=1,O15="Sí"),"Terminada",IF(N15>=1,"Por aceptar",IF(N15>0,"En curso","Por hacer"))) -> Terminada
A16: HU-013 | B16: Informar cambios de estado al solicitante | C16: EP-04 | D16: Sprint 3 | E16: 5 | F16: Alta | G16: HU-006, HU-012 | H16: Millaray y Matías | I16: CP-047 a CP-050 | J16: =_xlfn.MINIFS(Tareas!$H:$H,Tareas!$C:$C,$A16) -> 46300 | K16: =_xlfn.MAXIFS(Tareas!$I:$I,Tareas!$C:$C,$A16) -> 46304 | L16: =SUMIFS(Tareas!$F:$F,Tareas!$C:$C,$A16) -> 9 | M16: =SUMIFS(Tareas!$L:$L,Tareas!$C:$C,$A16) -> 9 | N16: =IFERROR(M16/L16,0) -> 1 | O16: Sí | P16: =IF(AND(N16>=1,O16="Sí"),"Terminada",IF(N16>=1,"Por aceptar",IF(N16>0,"En curso","Por hacer"))) -> Terminada
... A24: HU-020 | B24: Gestionar el avance y cierre de posventa | C24: EP-06 | D24: Sprint 6 | E24: 8 | F24: Alta | G24: HU-019, HU-014 | H24: Millaray y Alexssander | I24: CP-075 a CP-078 | J24: =_xlfn.MINIFS(Tareas!$H:$H,Tareas!$C:$C,$A24) -> 46335 | K24: =_xlfn.MAXIFS(Tareas!$I:$I,Tareas!$C:$C,$A24) -> 46339 | L24: =SUMIFS(Tareas!$F:$F,Tareas!$C:$C,$A24) -> 11 | M24: =SUMIFS(Tareas!$L:$L,Tareas!$C:$C,$A24) -> 0 | N24: =IFERROR(M24/L24,0) -> 0 | O24: No | P24: =IF(AND(N24>=1,O24="Sí"),"Terminada",IF(N24>=1,"Por aceptar",IF(N24>0,"En curso","Por hacer"))) -> Por hacer

Sheet Eventos
A1: Eventos Scrum
A2: Fechas calculadas desde las fechas de cada sprint. El Daily Scrum se realiza de lunes a viernes a las 21:00 (15 min).
A4: Sprint | B4: Evento | C4: Fecha | D4: Duración máxima | E4: Participantes | F4: Registro | G4: Realizado
A5: Sprint 1 | B5: Sprint Planning | C5: =Resumen!$C$8 -> 46265 | D5: 2 h | E5: Scrum Team | F5: Secciones 1 a 7 del Expediente | G5: No
A6: Sprint 1 | B6: Refinamiento del Product Backlog | C6: =Resumen!$C$8+8-WEEKDAY(Resumen!$C$8,2) -> 46272 | D6: 45 min | E6: Scrum Team y usuarios clave | F6: Product Backlog actualizado | G6: No
A7: Sprint 1 | B7: Integración y congelamiento | C7: =WORKDAY(Resumen!$D$8,-1,Feriados) -> 46275 | D7: — | E7: Developers | F7: develop estable para la demostración | G7: No
A8: Sprint 1 | B8: Sprint Review | C8: =Resumen!$D$8 -> 46276 | D8: 1 h | E8: Scrum Team y stakeholders | F8: Secciones 11 a 13 del Expediente | G8: No
A9: Sprint 1 | B9: Sprint Retrospective | C9: =Resumen!$D$8 -> 46276 | D9: 45 min | E9: Scrum Team | F9: Secciones 14 y 15 del Expediente | G9: No
A10: Sprint 2 | B10: Sprint Planning | C10: =Resumen!$C$9 -> 46279 | D10: 2 h | E10: Scrum Team | F10: Secciones 1 a 7 del Expediente | G10: No
A11: Sprint 2 | B11: Refinamiento del Product Backlog | C11: =Resumen!$C$9+8-WEEKDAY(Resumen!$C$9,2) -> 46286 | D11: 45 min | E11: Scrum Team y usuarios clave | F11: Product Backlog actualizado | G11: No
A12: Sprint 2 | B12: Integración y congelamiento | C12: =WORKDAY(Resumen!$D$9,-1,Feriados) -> 46289 | D12: — | E12: Developers | F12: develop estable para la demostración | G12: No
A13: Sprint 2 | B13: Sprint Review | C13: =Resumen!$D$9 -> 46290 | D13: 1 h | E13: Scrum Team y stakeholders | F13: Secciones 11 a 13 del Expediente | G13: No
A14: Sprint 2 | B14: Sprint Retrospective | C14: =Resumen!$D$9 -> 46290 | D14: 45 min | E14: Scrum Team | F14: Secciones 14 y 15 del Expediente | G14: No
A15: Sprint 3 | B15: Sprint Planning | C15: =Resumen!$C$10 -> 46293 | D15: 2 h | E15: Scrum Team | F15: Secciones 1 a 7 del Expediente | G15: No
A16: Sprint 3 | B16: Refinamiento del Product Backlog | C16: =Resumen!$C$10+8-WEEKDAY(Resumen!$C$10,2) -> 46300 | D16: 45 min | E16: Scrum Team y usuarios clave | F16: Product Backlog actualizado | G16: No
A17: Sprint 3 | B17: Integración y congelamiento | C17: =WORKDAY(Resumen!$D$10,-1,Feriados) -> 46303 | D17: — | E17: Developers | F17: develop estable para la demostración | G17: No
A18: Sprint 3 | B18: Sprint Review | C18: =Resumen!$D$10 -> 46304 | D18: 1 h | E18: Scrum Team y stakeholders | F18: Secciones 11 a 13 del Expediente | G18: No
A19: Sprint 3 | B19: Sprint Retrospective | C19: =Resumen!$D$10 -> 46304 | D19: 45 min | E19: Scrum Team | F19: Secciones 14 y 15 del Expediente | G19: No
A20: Sprint 4 | B20: Sprint Planning | C20: =Resumen!$C$11 -> 46308 | D20: 2 h | E20: Scrum Team | F20: Secciones 1 a 7 del Expediente | G20: No
A21: Sprint 4 | B21: Refinamiento del Product Backlog | C21: =Resumen!$C$11+8-WEEKDAY(Resumen!$C$11,2) -> 46314 | D21: 45 min | E21: Scrum Team y usuarios clave | F21: Product Backlog actualizado | G21: No
A22: Sprint 4 | B22: Integración y congelamiento | C22: =WORKDAY(Resumen!$D$11,-1,Feriados) -> 46317 | D22: — | E22: Developers | F22: develop estable para la demostración | G22: No
A23: Sprint 4 | B23: Sprint Review | C23: =Resumen!$D$11 -> 46318 | D23: 1 h | E23: Scrum Team y stakeholders | F23: Secciones 11 a 13 del Expediente | G23: No
A24: Sprint 4 | B24: Sprint Retrospective | C24: =Resumen!$D$11 -> 46318 | D24: 45 min | E24: Scrum Team | F24: Secciones 14 y 15 del Expediente | G24: No
A25: Sprint 5 | B25: Sprint Planning | C25: =Resumen!$C$12 -> 46321 | D25: 2 h | E25: Scrum Team | F25: Secciones 1 a 7 del Expediente | G25: No
A26: Sprint 5 | B26: Refinamiento del Product Backlog | C26: =Resumen!$C$12+8-WEEKDAY(Resumen!$C$12,2) -> 46328 | D26: 45 min | E26: Scrum Team y usuarios clave | F26: Product Backlog actualizado | G26: No
A27: Sprint 5 | B27: Integración y congelamiento | C27: =WORKDAY(Resumen!$D$12,-1,Feriados) -> 46331 | D27: — | E27: Developers | F27: develop estable para la demostración | G27: No
A28: Sprint 5 | B28: Sprint Review | C28: =Resumen!$D$12 -> 46332 | D28: 1 h | E28: Scrum Team y stakeholders | F28: Secciones 11 a 13 del Expediente | G28: No
A29: Sprint 5 | B29: Sprint Retrospective | C29: =Resumen!$D$12 -> 46332 | D29: 45 min | E29: Scrum Team | F29: Secciones 14 y 15 del Expediente | G29: No
A30: Sprint 6 | B30: Sprint Planning | C30: =Resumen!$C$13 -> 46335 | D30: 1 h | E30: Scrum Team | F30: Secciones 1 a 7 del Expediente | G30: No
A31: Sprint 6 | B31: Integración y congelamiento | C31: =WORKDAY(Resumen!$D$13,-1,Feriados) -> 46338 | D31: — | E31: Developers | F31: develop estable para la demostración | G31: No
A32: Sprint 6 | B32: Sprint Review | C32: =Resumen!$D$13 -> 46339 | D32: 30 min | E32: Scrum Team y stakeholders | F32: Secciones 11 a 13 del Expediente | G32: No
A33: Sprint 6 | B33: Sprint Retrospective | C33: =Resumen!$D$13 -> 46339 | D33: 30 min | E33: Scrum Team | F33: Secciones 14 y 15 del Expediente | G33: No
A34: Cierre | B34: Elaboración de evidencias sanitizadas | C34: 46342 | D34: — | E34: Scrum Team | F34: — | G34: No
A35: Cierre | B35: Fin del período del proyecto | C35: 46363 | D35: — | E35: Scrum Team | F35: — | G35: No

Sheet Capacidad
A1: Capacidad por sprint e integrante
A2: Horas disponibles = dedicación (3 h por día hábil + 3 h el sábado) − eventos Scrum − rol de PO o SM. Comprometido y avanzado se calculan desde Tareas.
A4: Sprint | B4: Integrante | C4: Rol | D4: Disponible (h) | E4: Comprometido (h) | F4: % de uso | G4: Avanzado (h)
A5: Sprint 1 | B5: Matías Orellana | C5: Product Owner | D5: 26 | E5: =SUMIFS(Tareas!$F:$F,Tareas!$B:$B,$A5,Tareas!$E:$E,$B5) -> 21 | F5: =IFERROR(E5/D5,0) -> 0.80769231 | G5: =SUMIFS(Tareas!$L:$L,Tareas!$B:$B,$A5,Tareas!$E:$E,$B5) -> 21
A6: Sprint 1 | B6: Millaray Espósito | C6: Scrum Master | D6: 26 | E6: =SUMIFS(Tareas!$F:$F,Tareas!$B:$B,$A6,Tareas!$E:$E,$B6) -> 21 | F6: =IFERROR(E6/D6,0) -> 0.80769231 | G6: =SUMIFS(Tareas!$L:$L,Tareas!$B:$B,$A6,Tareas!$E:$E,$B6) -> 21
A7: Sprint 1 | B7: Alexssander López | C7: Integración | D7: 29 | E7: =SUMIFS(Tareas!$F:$F,Tareas!$B:$B,$A7,Tareas!$E:$E,$B7) -> 27 | F7: =IFERROR(E7/D7,0) -> 0.93103448 | G7: =SUMIFS(Tareas!$L:$L,Tareas!$B:$B,$A7,Tareas!$E:$E,$B7) -> 27
A8: Sprint 2 | B8: Matías Orellana | C8: Integración | D8: 26 | E8: =SUMIFS(Tareas!$F:$F,Tareas!$B:$B,$A8,Tareas!$E:$E,$B8) -> 22 | F8: =IFERROR(E8/D8,0) -> 0.84615385 | G8: =SUMIFS(Tareas!$L:$L,Tareas!$B:$B,$A8,Tareas!$E:$E,$B8) -> 22
A9: Sprint 2 | B9: Millaray Espósito | C9: Product Owner | D9: 23 | E9: =SUMIFS(Tareas!$F:$F,Tareas!$B:$B,$A9,Tareas!$E:$E,$B9) -> 18 | F9: =IFERROR(E9/D9,0) -> 0.7826087 | G9: =SUMIFS(Tareas!$L:$L,Tareas!$B:$B,$A9,Tareas!$E:$E,$B9) -> 18
A10: Sprint 2 | B10: Alexssander López | C10: Scrum Master | D10: 23 | E10: =SUMIFS(Tareas!$F:$F,Tareas!$B:$B,$A10,Tareas!$E:$E,$B10) -> 16 | F10: =IFERROR(E10/D10,0) -> 0.69565217 | G10: =SUMIFS(Tareas!$L:$L,Tareas!$B:$B,$A10,Tareas!$E:$E,$B10) -> 16
A11: Sprint 3 | B11: Matías Orellana | C11: Scrum Master | D11: 26 | E11: =SUMIFS(Tareas!$F:$F,Tareas!$B:$B,$A11,Tareas!$E:$E,$B11) -> 19 | F11: =IFERROR(E11/D11,0) -> 0.73076923 | G11: =SUMIFS(Tareas!$L:$L,Tareas!$B:$B,$A11,Tareas!$E:$E,$B11) -> 19
A12: Sprint 3 | B12: Millaray Espósito | C12: Integración | D12: 29 | E12: =SUMIFS(Tareas!$F:$F,Tareas!$B:$B,$A12,Tareas!$E:$E,$B12) -> 18 | F12: =IFERROR(E12/D12,0) -> 0.62068966 | G12: =SUMIFS(Tareas!$L:$L,Tareas!$B:$B,$A12,Tareas!$E:$E,$B12) -> 18
A13: Sprint 3 | B13: Alexssander López | C13: Product Owner | D13: 26 | E13: =SUMIFS(Tareas!$F:$F,Tareas!$B:$B,$A13,Tareas!$E:$E,$B13) -> 22 | F13: =IFERROR(E13/D13,0) -> 0.84615385 | G13: =SUMIFS(Tareas!$L:$L,Tareas!$B:$B,$A13,Tareas!$E:$E,$B13) -> 22
A14: Sprint 4 | B14: Matías Orellana | C14: Product Owner | D14: 23 | E14: =SUMIFS(Tareas!$F:$F,Tareas!$B:$B,$A14,Tareas!$E:$E,$B14) -> 18 | F14: =IFERROR(E14/D14,0) -> 0.7826087 | G14: =SUMIFS(Tareas!$L:$L,Tareas!$B:$B,$A14,Tareas!$E:$E,$B14) -> 0
A15: Sprint 4 | B15: Millaray Espósito | C15: Scrum Master | D15: 23 | E15: =SUMIFS(Tareas!$F:$F,Tareas!$B:$B,$A15,Tareas!$E:$E,$B15) -> 16 | F15: =IFERROR(E15/D15,0) -> 0.69565217 | G15: =SUMIFS(Tareas!$L:$L,Tareas!$B:$B,$A15,Tareas!$E:$E,$B15) -> 0
A16: Sprint 4 | B16: Alexssander López | C16: Integración | D16: 26 | E16: =SUMIFS(Tareas!$F:$F,Tareas!$B:$B,$A16,Tareas!$E:$E,$B16) -> 21 | F16: =IFERROR(E16/D16,0) -> 0.80769231 | G16: =SUMIFS(Tareas!$L:$L,Tareas!$B:$B,$A16,Tareas!$E:$E,$B16) -> 0
... A22: Sprint 6 | B22: Alexssander López | C22: Product Owner | D22: 13.25 | E22: =SUMIFS(Tareas!$F:$F,Tareas!$B:$B,$A22,Tareas!$E:$E,$B22) -> 6 | F22: =IFERROR(E22/D22,0) -> 0.45283019 | G22: =SUMIFS(Tareas!$L:$L,Tareas!$B:$B,$A22,Tareas!$E:$E,$B22) -> 0

Sheet Config
A1: Configuración
A2: Listas usadas por las fórmulas. Los valores en azul pueden editarse.
A4: Feriado | B4: Descripción | D4: Estado de tarea | E4: % de avance
A5: 46283 | B5: Fiestas Patrias | D5: Por hacer | E5: 0
A6: 46284 | B6: Día de las Glorias del Ejército | D6: En curso | E6: 0.5
A7: 46307 | B7: Encuentro de Dos Mundos | D7: En revisión | E7: 0.75
A8: 46326 | B8: Día de las Iglesias Evangélicas | D8: En pruebas | E8: 0.9
A9: 46327 | B9: Día de Todos los Santos | D9: Terminado | E9: 1
A10: 46364 | B10: Inmaculada Concepción
