Workbook

Sheet Product Backlog
A2: Product Backlog
A4: Vista priorizada de las historias de usuario, ordenada mediante la columna Orden.
A5: Orden | B5: ID HU | C5: Épica | D5: Funcionalidad | E5: Título | F5: Historia de usuario | G5: Criterios de aceptación | H5: Prioridad | I5: Estimación SP | J5: Dependencias | K5: Estado | L5: Sprint | M5: Responsable
A6: 1 | B6: HU-001 | C6: =IF($B6="","",IFERROR(IF(VLOOKUP($B6,'Historias de usuario'!$A$6:$P$25,2,FALSE)="","",VLOOKUP($B6,'Historias de usuario'!$A$6:$P$25,2,FALSE)),"")) -> EP-01 | D6: =IF($B6="","",IFERROR(IF(VLOOKUP($B6,'Historias de usuario'!$A$6:$P$25,3,FALSE)="","",VLOOKUP($B6,'Historias de usuario'!$A$6:$P$25,3,FALSE)),"")) -> Acceso seguro | E6: =IF($B6="","",IFERROR(IF(VLOOKUP($B6,'Historias de usuario'!$A$6:$P$25,4,FALSE)="","",VLOOKUP($B6,'Historias de usuario'!$A$6:$P$25,4,FALSE)),"")) -> Autenticarse en la plataforma | F6: =IF($B6="","",IFERROR(IF(VLOOKUP($B6,'Historias de usuario'!$A$6:$P$25,8,FALSE)="","",VLOOKUP($B6,'Historias de usuario'!$A$6:$P$25,8,FALSE)),"")) -> Como usuario habilitado, quiero iniciar sesión de forma segura y mantener una sesión controlada, para acceder únicamente a las funciones autorizadas | G6: =IF($B6="","",IFERROR(IF(VLOOKUP($B6,'Historias de usuario'!$A$6:$P$25,9,FALSE)="","",VLOOKUP($B6,'Historias de usuario'!$A$6:$P$25,9,FALSE)),"")) -> 1. Con credenciales válidas, el usuario activo ingresa a la plataforma. 2. Las credenciales inválidas o de un usuario desactivado impiden el acceso y muestran un mensaje claro. 3. La contraseña se almacena mediante hash, la sesión expira por inactividad y los intentos fallidos quedan auditados. | H6: =IF($B6="","",IFERROR(IF(VLOOKUP($B6,'Historias de usuario'!$A$6:$P$25,10,FALSE)="","",VLOOKUP($B6,'Historias de usuario'!$A$6:$P$25,10,FALSE)),"")) -> Alta | I6: =IF($B6="","",IFERROR(IF(VLOOKUP($B6,'Historias de usuario'!$A$6:$P$25,11,FALSE)="","",VLOOKUP($B6,'Historias de usuario'!$A$6:$P$25,11,FALSE)),"")) -> 5 | J6: =IF($B6="","",IFERROR(IF(VLOOKUP($B6,'Historias de usuario'!$A$6:$P$25,12,FALSE)="","",VLOOKUP($B6,'Historias de usuario'!$A$6:$P$25,12,FALSE)),"")) -> Ninguna | K6: =IF($B6="","",IFERROR(IF(VLOOKUP($B6,'Historias de usuario'!$A$6:$P$25,13,FALSE)="","",VLOOKUP($B6,'Historias de usuario'!$A$6:$P$25,13,FALSE)),"")) -> Propuesto | L6: =IF($B6="","",IFERROR(IF(VLOOKUP($B6,'Historias de usuario'!$A$6:$P$25,14,FALSE)="","",VLOOKUP($B6,'Historias de usuario'!$A$6:$P$25,14,FALSE)),"")) -> Sprint 1 · 2 sem. | M6: =IF($B6="","",IFERROR(IF(VLOOKUP($B6,'Historias de usuario'!$A$6:$P$25,15,FALSE)="","",VLOOKUP($B6,'Historias de usuario'!$A$6:$P$25,15,FALSE)),"")) -> Matías y Alexssander
A7: 2 | B7: HU-002 | C7: =IF($B7="","",IFERROR(IF(VLOOKUP($B7,'Historias de usuario'!$A$6:$P$25,2,FALSE)="","",VLOOKUP($B7,'Historias de usuario'!$A$6:$P$25,2,FALSE)),"")) -> EP-01 | D7: =IF($B7="","",IFERROR(IF(VLOOKUP($B7,'Historias de usuario'!$A$6:$P$25,3,FALSE)="","",VLOOKUP($B7,'Historias de usuario'!$A$6:$P$25,3,FALSE)),"")) -> Administración de usuarios | E7: =IF($B7="","",IFERROR(IF(VLOOKUP($B7,'Historias de usuario'!$A$6:$P$25,4,FALSE)="","",VLOOKUP($B7,'Historias de usuario'!$A$6:$P$25,4,FALSE)),"")) -> Administrar usuarios y perfiles | F7: =IF($B7="","",IFERROR(IF(VLOOKUP($B7,'Historias de usuario'!$A$6:$P$25,8,FALSE)="","",VLOOKUP($B7,'Historias de usuario'!$A$6:$P$25,8,FALSE)),"")) -> Como administrador, quiero crear, editar, desactivar y reactivar usuarios asignándoles área, cargo, grupos de autorizadores y permisos directos, para mantener los accesos alineados con las responsabilidades de cada trabajador | G7: =IF($B7="","",IFERROR(IF(VLOOKUP($B7,'Historias de usuario'!$A$6:$P$25,9,FALSE)="","",VLOOKUP($B7,'Historias de usuario'!$A$6:$P$25,9,FALSE)),"")) -> 1. El administrador crea y edita usuarios con área y cargo obligatorios. 2. Un usuario se desactiva o reactiva sin eliminar su historial. 3. Solo el administrador puede ejecutar estas operaciones y un usuario desactivado no puede iniciar sesión. | H7: =IF($B7="","",IFERROR(IF(VLOOKUP($B7,'Historias de usuario'!$A$6:$P$25,10,FALSE)="","",VLOOKUP($B7,'Historias de usuario'!$A$6:$P$25,10,FALSE)),"")) -> Alta | I7: =IF($B7="","",IFERROR(IF(VLOOKUP($B7,'Historias de usuario'!$A$6:$P$25,11,FALSE)="","",VLOOKUP($B7,'Historias de usuario'!$A$6:$P$25,11,FALSE)),"")) -> 8 | J7: =IF($B7="","",IFERROR(IF(VLOOKUP($B7,'Historias de usuario'!$A$6:$P$25,12,FALSE)="","",VLOOKUP($B7,'Historias de usuario'!$A$6:$P$25,12,FALSE)),"")) -> HU-001 | K7: =IF($B7="","",IFERROR(IF(VLOOKUP($B7,'Historias de usuario'!$A$6:$P$25,13,FALSE)="","",VLOOKUP($B7,'Historias de usuario'!$A$6:$P$25,13,FALSE)),"")) -> Propuesto | L7: =IF($B7="","",IFERROR(IF(VLOOKUP($B7,'Historias de usuario'!$A$6:$P$25,14,FALSE)="","",VLOOKUP($B7,'Historias de usuario'!$A$6:$P$25,14,FALSE)),"")) -> Sprint 1 · 2 sem. | M7: =IF($B7="","",IFERROR(IF(VLOOKUP($B7,'Historias de usuario'!$A$6:$P$25,15,FALSE)="","",VLOOKUP($B7,'Historias de usuario'!$A$6:$P$25,15,FALSE)),"")) -> Matías y Alexssander
A8: 3 | B8: HU-003 | C8: =IF($B8="","",IFERROR(IF(VLOOKUP($B8,'Historias de usuario'!$A$6:$P$25,2,FALSE)="","",VLOOKUP($B8,'Historias de usuario'!$A$6:$P$25,2,FALSE)),"")) -> EP-01 | D8: =IF($B8="","",IFERROR(IF(VLOOKUP($B8,'Historias de usuario'!$A$6:$P$25,3,FALSE)="","",VLOOKUP($B8,'Historias de usuario'!$A$6:$P$25,3,FALSE)),"")) -> Permisos y autorizadores | E8: =IF($B8="","",IFERROR(IF(VLOOKUP($B8,'Historias de usuario'!$A$6:$P$25,4,FALSE)="","",VLOOKUP($B8,'Historias de usuario'!$A$6:$P$25,4,FALSE)),"")) -> Configurar permisos y grupos de autorización | F8: =IF($B8="","",IFERROR(IF(VLOOKUP($B8,'Historias de usuario'!$A$6:$P$25,8,FALSE)="","",VLOOKUP($B8,'Historias de usuario'!$A$6:$P$25,8,FALSE)),"")) -> Como administrador, quiero definir permisos por área, por cargo y directos por usuario, además de los integrantes de los grupos de autorizadores de cada proceso, para controlar qué funciones, datos y decisiones corresponden a cada usuario | G8: =IF($B8="","",IFERROR(IF(VLOOKUP($B8,'Historias de usuario'!$A$6:$P$25,9,FALSE)="","",VLOOKUP($B8,'Historias de usuario'!$A$6:$P$25,9,FALSE)),"")) -> 1. Los permisos efectivos suman los permisos directos, del área y del cargo. 2. Cada operación valida los permisos en el servidor. 3. Es posible modificar los integrantes de los grupos de cada proceso, siempre con al menos un integrante activo. 4. Solo el administrador gestiona permisos y grupos. | H8: =IF($B8="","",IFERROR(IF(VLOOKUP($B8,'Historias de usuario'!$A$6:$P$25,10,FALSE)="","",VLOOKUP($B8,'Historias de usuario'!$A$6:$P$25,10,FALSE)),"")) -> Alta | I8: =IF($B8="","",IFERROR(IF(VLOOKUP($B8,'Historias de usuario'!$A$6:$P$25,11,FALSE)="","",VLOOKUP($B8,'Historias de usuario'!$A$6:$P$25,11,FALSE)),"")) -> 8 | J8: =IF($B8="","",IFERROR(IF(VLOOKUP($B8,'Historias de usuario'!$A$6:$P$25,12,FALSE)="","",VLOOKUP($B8,'Historias de usuario'!$A$6:$P$25,12,FALSE)),"")) -> HU-002 | K8: =IF($B8="","",IFERROR(IF(VLOOKUP($B8,'Historias de usuario'!$A$6:$P$25,13,FALSE)="","",VLOOKUP($B8,'Historias de usuario'!$A$6:$P$25,13,FALSE)),"")) -> Propuesto | L8: =IF($B8="","",IFERROR(IF(VLOOKUP($B8,'Historias de usuario'!$A$6:$P$25,14,FALSE)="","",VLOOKUP($B8,'Historias de usuario'!$A$6:$P$25,14,FALSE)),"")) -> Sprint 1 · 2 sem. | M8: =IF($B8="","",IFERROR(IF(VLOOKUP($B8,'Historias de usuario'!$A$6:$P$25,15,FALSE)="","",VLOOKUP($B8,'Historias de usuario'!$A$6:$P$25,15,FALSE)),"")) -> Matías y Alexssander
A9: 4 | B9: HU-004 | C9: =IF($B9="","",IFERROR(IF(VLOOKUP($B9,'Historias de usuario'!$A$6:$P$25,2,FALSE)="","",VLOOKUP($B9,'Historias de usuario'!$A$6:$P$25,2,FALSE)),"")) -> EP-01 | D9: =IF($B9="","",IFERROR(IF(VLOOKUP($B9,'Historias de usuario'!$A$6:$P$25,3,FALSE)="","",VLOOKUP($B9,'Historias de usuario'!$A$6:$P$25,3,FALSE)),"")) -> Contexto de empresa y vendedor | E9: =IF($B9="","",IFERROR(IF(VLOOKUP($B9,'Historias de usuario'!$A$6:$P$25,4,FALSE)="","",VLOOKUP($B9,'Historias de usuario'!$A$6:$P$25,4,FALSE)),"")) -> Configurar empresas, vendedores y comisiones | F9: =IF($B9="","",IFERROR(IF(VLOOKUP($B9,'Historias de usuario'!$A$6:$P$25,8,FALSE)="","",VLOOKUP($B9,'Historias de usuario'!$A$6:$P$25,8,FALSE)),"")) -> Como administrador, quiero asociar SlpCode y escala de comisión por empresa a vendedores y asistentes, para asegurar que cada operación use la empresa y el vendedor correctos | G9: =IF($B9="","",IFERROR(IF(VLOOKUP($B9,'Historias de usuario'!$A$6:$P$25,9,FALSE)="","",VLOOKUP($B9,'Historias de usuario'!$A$6:$P$25,9,FALSE)),"")) -> 1. Cada SlpCode queda asociado a Marsella o Asland y a los usuarios autorizados. 2. Se asigna una escala de comisión o se usa la escala predeterminada. 3. El selector de empresa solo aparece a usuarios con códigos en ambas empresas. 4. Al cambiar la empresa activa, consultas, documentos, solicitudes y casos usan ese contexto y su color identificador. | H9: =IF($B9="","",IFERROR(IF(VLOOKUP($B9,'Historias de usuario'!$A$6:$P$25,10,FALSE)="","",VLOOKUP($B9,'Historias de usuario'!$A$6:$P$25,10,FALSE)),"")) -> Alta | I9: =IF($B9="","",IFERROR(IF(VLOOKUP($B9,'Historias de usuario'!$A$6:$P$25,11,FALSE)="","",VLOOKUP($B9,'Historias de usuario'!$A$6:$P$25,11,FALSE)),"")) -> 8 | J9: =IF($B9="","",IFERROR(IF(VLOOKUP($B9,'Historias de usuario'!$A$6:$P$25,12,FALSE)="","",VLOOKUP($B9,'Historias de usuario'!$A$6:$P$25,12,FALSE)),"")) -> HU-002, HU-003 | K9: =IF($B9="","",IFERROR(IF(VLOOKUP($B9,'Historias de usuario'!$A$6:$P$25,13,FALSE)="","",VLOOKUP($B9,'Historias de usuario'!$A$6:$P$25,13,FALSE)),"")) -> Propuesto | L9: =IF($B9="","",IFERROR(IF(VLOOKUP($B9,'Historias de usuario'!$A$6:$P$25,14,FALSE)="","",VLOOKUP($B9,'Historias de usuario'!$A$6:$P$25,14,FALSE)),"")) -> Sprint 1 · 2 sem. | M9: =IF($B9="","",IFERROR(IF(VLOOKUP($B9,'Historias de usuario'!$A$6:$P$25,15,FALSE)="","",VLOOKUP($B9,'Historias de usuario'!$A$6:$P$25,15,FALSE)),"")) -> Matías y Alexssander
A10: 5 | B10: HU-005 | C10: =IF($B10="","",IFERROR(IF(VLOOKUP($B10,'Historias de usuario'!$A$6:$P$25,2,FALSE)="","",VLOOKUP($B10,'Historias de usuario'!$A$6:$P$25,2,FALSE)),"")) -> EP-02 | D10: =IF($B10="","",IFERROR(IF(VLOOKUP($B10,'Historias de usuario'!$A$6:$P$25,3,FALSE)="","",VLOOKUP($B10,'Historias de usuario'!$A$6:$P$25,3,FALSE)),"")) -> Solicitud de códigos | E10: =IF($B10="","",IFERROR(IF(VLOOKUP($B10,'Historias de usuario'!$A$6:$P$25,4,FALSE)="","",VLOOKUP($B10,'Historias de usuario'!$A$6:$P$25,4,FALSE)),"")) -> Crear y enviar solicitudes de código | F10: =IF($B10="","",IFERROR(IF(VLOOKUP($B10,'Historias de usuario'!$A$6:$P$25,8,FALSE)="","",VLOOKUP($B10,'Historias de usuario'!$A$6:$P$25,8,FALSE)),"")) -> Como vendedor autorizado, quiero crear solicitudes de creación, activación o modificación de artículos con sus respaldos, para enviar información completa al grupo autorizador correspondiente | G10: =IF($B10="","",IFERROR(IF(VLOOKUP($B10,'Historias de usuario'!$A$6:$P$25,9,FALSE)="","",VLOOKUP($B10,'Historias de usuario'!$A$6:$P$25,9,FALSE)),"")) -> 1. La solicitud se crea en estado Pendiente y queda asociada al usuario y empresa activa. 2. Permite incluir uno o más productos según el tipo de solicitud. 3. Exige el respaldo de cotización según su tipo y permite, para creaciones, un documento y una imagen por producto en los formatos permitidos. 4. Al enviarla, ingresa a la bandeja del grupo autorizador correcto. | H10: =IF($B10="","",IFERROR(IF(VLOOKUP($B10,'Historias de usuario'!$A$6:$P$25,10,FALSE)="","",VLOOKUP($B10,'Historias de usuario'!$A$6:$P$25,10,FALSE)),"")) -> Alta | I10: =IF($B10="","",IFERROR(IF(VLOOKUP($B10,'Historias de usuario'!$A$6:$P$25,11,FALSE)="","",VLOOKUP($B10,'Historias de usuario'!$A$6:$P$25,11,FALSE)),"")) -> 8 | J10: =IF($B10="","",IFERROR(IF(VLOOKUP($B10,'Historias de usuario'!$A$6:$P$25,12,FALSE)="","",VLOOKUP($B10,'Historias de usuario'!$A$6:$P$25,12,FALSE)),"")) -> HU-003, HU-004 | K10: =IF($B10="","",IFERROR(IF(VLOOKUP($B10,'Historias de usuario'!$A$6:$P$25,13,FALSE)="","",VLOOKUP($B10,'Historias de usuario'!$A$6:$P$25,13,FALSE)),"")) -> Propuesto | L10: =IF($B10="","",IFERROR(IF(VLOOKUP($B10,'Historias de usuario'!$A$6:$P$25,14,FALSE)="","",VLOOKUP($B10,'Historias de usuario'!$A$6:$P$25,14,FALSE)),"")) -> Sprint 2 · 2 sem. | M10: =IF($B10="","",IFERROR(IF(VLOOKUP($B10,'Historias de usuario'!$A$6:$P$25,15,FALSE)="","",VLOOKUP($B10,'Historias de usuario'!$A$6:$P$25,15,FALSE)),"")) -> Millaray y Matías
A11: 6 | B11: HU-006 | C11: =IF($B11="","",IFERROR(IF(VLOOKUP($B11,'Historias de usuario'!$A$6:$P$25,2,FALSE)="","",VLOOKUP($B11,'Historias de usuario'!$A$6:$P$25,2,FALSE)),"")) -> EP-02 | D11: =IF($B11="","",IFERROR(IF(VLOOKUP($B11,'Historias de usuario'!$A$6:$P$25,3,FALSE)="","",VLOOKUP($B11,'Historias de usuario'!$A$6:$P$25,3,FALSE)),"")) -> Resolución de solicitudes | E11: =IF($B11="","",IFERROR(IF(VLOOKUP($B11,'Historias de usuario'!$A$6:$P$25,4,FALSE)="","",VLOOKUP($B11,'Historias de usuario'!$A$6:$P$25,4,FALSE)),"")) -> Aprobar o rechazar solicitudes | F11: =IF($B11="","",IFERROR(IF(VLOOKUP($B11,'Historias de usuario'!$A$6:$P$25,8,FALSE)="","",VLOOKUP($B11,'Historias de usuario'!$A$6:$P$25,8,FALSE)),"")) -> Como autorizador, quiero aprobar, rechazar o pedir corrección de una solicitud de la bandeja compartida, para resolverla con un responsable y una decisión trazable | G11: =IF($B11="","",IFERROR(IF(VLOOKUP($B11,'Historias de usuario'!$A$6:$P$25,9,FALSE)="","",VLOOKUP($B11,'Historias de usuario'!$A$6:$P$25,9,FALSE)),"")) -> 1. Solo el grupo autorizador del tipo de solicitud puede verla y resolverla. 2. Quien resuelve la solicitud queda registrado como responsable. 3. El rechazo exige un motivo visible para el solicitante. 4. La solicitud aprobada no admite edición y conserva usuario, fecha, hora y comentario de la resolución. | H11: =IF($B11="","",IFERROR(IF(VLOOKUP($B11,'Historias de usuario'!$A$6:$P$25,10,FALSE)="","",VLOOKUP($B11,'Historias de usuario'!$A$6:$P$25,10,FALSE)),"")) -> Alta | I11: =IF($B11="","",IFERROR(IF(VLOOKUP($B11,'Historias de usuario'!$A$6:$P$25,11,FALSE)="","",VLOOKUP($B11,'Historias de usuario'!$A$6:$P$25,11,FALSE)),"")) -> 5 | J11: =IF($B11="","",IFERROR(IF(VLOOKUP($B11,'Historias de usuario'!$A$6:$P$25,12,FALSE)="","",VLOOKUP($B11,'Historias de usuario'!$A$6:$P$25,12,FALSE)),"")) -> HU-005 | K11: =IF($B11="","",IFERROR(IF(VLOOKUP($B11,'Historias de usuario'!$A$6:$P$25,13,FALSE)="","",VLOOKUP($B11,'Historias de usuario'!$A$6:$P$25,13,FALSE)),"")) -> Propuesto | L11: =IF($B11="","",IFERROR(IF(VLOOKUP($B11,'Historias de usuario'!$A$6:$P$25,14,FALSE)="","",VLOOKUP($B11,'Historias de usuario'!$A$6:$P$25,14,FALSE)),"")) -> Sprint 2 · 2 sem. | M11: =IF($B11="","",IFERROR(IF(VLOOKUP($B11,'Historias de usuario'!$A$6:$P$25,15,FALSE)="","",VLOOKUP($B11,'Historias de usuario'!$A$6:$P$25,15,FALSE)),"")) -> Millaray y Matías
A12: 7 | B12: HU-007 | C12: =IF($B12="","",IFERROR(IF(VLOOKUP($B12,'Historias de usuario'!$A$6:$P$25,2,FALSE)="","",VLOOKUP($B12,'Historias de usuario'!$A$6:$P$25,2,FALSE)),"")) -> EP-02 | D12: =IF($B12="","",IFERROR(IF(VLOOKUP($B12,'Historias de usuario'!$A$6:$P$25,3,FALSE)="","",VLOOKUP($B12,'Historias de usuario'!$A$6:$P$25,3,FALSE)),"")) -> Seguimiento de solicitudes | E12: =IF($B12="","",IFERROR(IF(VLOOKUP($B12,'Historias de usuario'!$A$6:$P$25,4,FALSE)="","",VLOOKUP($B12,'Historias de usuario'!$A$6:$P$25,4,FALSE)),"")) -> Corregir, reenviar y consultar solicitudes | F12: =IF($B12="","",IFERROR(IF(VLOOKUP($B12,'Historias de usuario'!$A$6:$P$25,8,FALSE)="","",VLOOKUP($B12,'Historias de usuario'!$A$6:$P$25,8,FALSE)),"")) -> Como vendedor solicitante, quiero corregir y reenviar solicitudes rechazadas, además de consultar y filtrar su seguimiento, para resolver observaciones y conocer el estado de cada gestión | G12: =IF($B12="","",IFERROR(IF(VLOOKUP($B12,'Historias de usuario'!$A$6:$P$25,9,FALSE)="","",VLOOKUP($B12,'Historias de usuario'!$A$6:$P$25,9,FALSE)),"")) -> 1. Solo el creador puede corregir y reenviar una solicitud rechazada. 2. El reenvío vuelve a estado Pendiente y a la bandeja del grupo autorizador. 3. El usuario consulta estado, responsable, fecha y comentario. 4. Los filtros por estado, fecha, área y responsable devuelven resultados acordes con sus permisos. | H12: =IF($B12="","",IFERROR(IF(VLOOKUP($B12,'Historias de usuario'!$A$6:$P$25,10,FALSE)="","",VLOOKUP($B12,'Historias de usuario'!$A$6:$P$25,10,FALSE)),"")) -> Alta | I12: =IF($B12="","",IFERROR(IF(VLOOKUP($B12,'Historias de usuario'!$A$6:$P$25,11,FALSE)="","",VLOOKUP($B12,'Historias de usuario'!$A$6:$P$25,11,FALSE)),"")) -> 8 | J12: =IF($B12="","",IFERROR(IF(VLOOKUP($B12,'Historias de usuario'!$A$6:$P$25,12,FALSE)="","",VLOOKUP($B12,'Historias de usuario'!$A$6:$P$25,12,FALSE)),"")) -> HU-006 | K12: =IF($B12="","",IFERROR(IF(VLOOKUP($B12,'Historias de usuario'!$A$6:$P$25,13,FALSE)="","",VLOOKUP($B12,'Historias de usuario'!$A$6:$P$25,13,FALSE)),"")) -> Propuesto | L12: =IF($B12="","",IFERROR(IF(VLOOKUP($B12,'Historias de usuario'!$A$6:$P$25,14,FALSE)="","",VLOOKUP($B12,'Historias de usuario'!$A$6:$P$25,14,FALSE)),"")) -> Sprint 2 · 2 sem. | M12: =IF($B12="","",IFERROR(IF(VLOOKUP($B12,'Historias de usuario'!$A$6:$P$25,15,FALSE)="","",VLOOKUP($B12,'Historias de usuario'!$A$6:$P$25,15,FALSE)),"")) -> Millaray y Matías
A13: 8 | B13: HU-012 | C13: =IF($B13="","",IFERROR(IF(VLOOKUP($B13,'Historias de usuario'!$A$6:$P$25,2,FALSE)="","",VLOOKUP($B13,'Historias de usuario'!$A$6:$P$25,2,FALSE)),"")) -> EP-04 | D13: =IF($B13="","",IFERROR(IF(VLOOKUP($B13,'Historias de usuario'!$A$6:$P$25,3,FALSE)="","",VLOOKUP($B13,'Historias de usuario'!$A$6:$P$25,3,FALSE)),"")) -> Avisos a autorizadores | E13: =IF($B13="","",IFERROR(IF(VLOOKUP($B13,'Historias de usuario'!$A$6:$P$25,4,FALSE)="","",VLOOKUP($B13,'Historias de usuario'!$A$6:$P$25,4,FALSE)),"")) -> Notificar pendientes y recordatorios | F13: =IF($B13="","",IFERROR(IF(VLOOKUP($B13,'Historias de usuario'!$A$6:$P$25,8,FALSE)="","",VLOOKUP($B13,'Historias de usuario'!$A$6:$P$25,8,FALSE)),"")) -> Como autorizador, quiero recibir avisos de los procesos pendientes y recordatorios cuando superen una hora, para atender oportunamente las decisiones que me corresponden | G13: =IF($B13="","",IFERROR(IF(VLOOKUP($B13,'Historias de usuario'!$A$6:$P$25,9,FALSE)="","",VLOOKUP($B13,'Historias de usuario'!$A$6:$P$25,9,FALSE)),"")) -> 1. Al enviar un proceso, se notifica únicamente a los destinatarios autorizados. 2. La notificación identifica categoría, emisor, nivel y enlace al proceso. 3. Después de una hora pendiente se genera un recordatorio automático. 4. El usuario no puede ver notificaciones ajenas. | H13: =IF($B13="","",IFERROR(IF(VLOOKUP($B13,'Historias de usuario'!$A$6:$P$25,10,FALSE)="","",VLOOKUP($B13,'Historias de usuario'!$A$6:$P$25,10,FALSE)),"")) -> Alta | I13: =IF($B13="","",IFERROR(IF(VLOOKUP($B13,'Historias de usuario'!$A$6:$P$25,11,FALSE)="","",VLOOKUP($B13,'Historias de usuario'!$A$6:$P$25,11,FALSE)),"")) -> 5 | J13: =IF($B13="","",IFERROR(IF(VLOOKUP($B13,'Historias de usuario'!$A$6:$P$25,12,FALSE)="","",VLOOKUP($B13,'Historias de usuario'!$A$6:$P$25,12,FALSE)),"")) -> HU-005, HU-006 | K13: =IF($B13="","",IFERROR(IF(VLOOKUP($B13,'Historias de usuario'!$A$6:$P$25,13,FALSE)="","",VLOOKUP($B13,'Historias de usuario'!$A$6:$P$25,13,FALSE)),"")) -> Propuesto | L13: =IF($B13="","",IFERROR(IF(VLOOKUP($B13,'Historias de usuario'!$A$6:$P$25,14,FALSE)="","",VLOOKUP($B13,'Historias de usuario'!$A$6:$P$25,14,FALSE)),"")) -> Sprint 2 · 2 sem. | M13: =IF($B13="","",IFERROR(IF(VLOOKUP($B13,'Historias de usuario'!$A$6:$P$25,15,FALSE)="","",VLOOKUP($B13,'Historias de usuario'!$A$6:$P$25,15,FALSE)),"")) -> Millaray y Matías
A14: 9 | B14: HU-015 | C14: =IF($B14="","",IFERROR(IF(VLOOKUP($B14,'Historias de usuario'!$A$6:$P$25,2,FALSE)="","",VLOOKUP($B14,'Historias de usuario'!$A$6:$P$25,2,FALSE)),"")) -> EP-05 | D14: =IF($B14="","",IFERROR(IF(VLOOKUP($B14,'Historias de usuario'!$A$6:$P$25,3,FALSE)="","",VLOOKUP($B14,'Historias de usuario'!$A$6:$P$25,3,FALSE)),"")) -> Lectura desde SAP | E14: =IF($B14="","",IFERROR(IF(VLOOKUP($B14,'Historias de usuario'!$A$6:$P$25,4,FALSE)="","",VLOOKUP($B14,'Historias de usuario'!$A$6:$P$25,4,FALSE)),"")) -> Consultar SAP mediante una API segura | F14: =IF($B14="","",IFERROR(IF(VLOOKUP($B14,'Historias de usuario'!$A$6:$P$25,8,FALSE)="","",VLOOKUP($B14,'Historias de usuario'!$A$6:$P$25,8,FALSE)),"")) -> Como usuario autorizado de la plataforma, quiero obtener productos, clientes, stock y datos permitidos mediante la API de lectura, para trabajar desde la web sin modificar directamente la información oficial del ERP | G14: =IF($B14="","",IFERROR(IF(VLOOKUP($B14,'Historias de usuario'!$A$6:$P$25,9,FALSE)="","",VLOOKUP($B14,'Historias de usuario'!$A$6:$P$25,9,FALSE)),"")) -> 1. La API consulta SAP HANA exclusivamente con un usuario de solo lectura y responde JSON. 2. Cada petición exige una firma válida; una firma inválida se rechaza. 3. Las credenciales se mantienen fuera del código. 4. Los listados se paginan, aplican tiempo límite y reintentos acotados, y las consultas normales responden en menos de 3 segundos. | H14: =IF($B14="","",IFERROR(IF(VLOOKUP($B14,'Historias de usuario'!$A$6:$P$25,10,FALSE)="","",VLOOKUP($B14,'Historias de usuario'!$A$6:$P$25,10,FALSE)),"")) -> Alta | I14: =IF($B14="","",IFERROR(IF(VLOOKUP($B14,'Historias de usuario'!$A$6:$P$25,11,FALSE)="","",VLOOKUP($B14,'Historias de usuario'!$A$6:$P$25,11,FALSE)),"")) -> 8 | J14: =IF($B14="","",IFERROR(IF(VLOOKUP($B14,'Historias de usuario'!$A$6:$P$25,12,FALSE)="","",VLOOKUP($B14,'Historias de usuario'!$A$6:$P$25,12,FALSE)),"")) -> HU-003, HU-004 | K14: =IF($B14="","",IFERROR(IF(VLOOKUP($B14,'Historias de usuario'!$A$6:$P$25,13,FALSE)="","",VLOOKUP($B14,'Historias de usuario'!$A$6:$P$25,13,FALSE)),"")) -> Propuesto | L14: =IF($B14="","",IFERROR(IF(VLOOKUP($B14,'Historias de usuario'!$A$6:$P$25,14,FALSE)="","",VLOOKUP($B14,'Historias de usuario'!$A$6:$P$25,14,FALSE)),"")) -> Sprint 3 · 2 sem. | M14: =IF($B14="","",IFERROR(IF(VLOOKUP($B14,'Historias de usuario'!$A$6:$P$25,15,FALSE)="","",VLOOKUP($B14,'Historias de usuario'!$A$6:$P$25,15,FALSE)),"")) -> Alexssander y Matías
A15: 10 | B15: HU-008 | C15: =IF($B15="","",IFERROR(IF(VLOOKUP($B15,'Historias de usuario'!$A$6:$P$25,2,FALSE)="","",VLOOKUP($B15,'Historias de usuario'!$A$6:$P$25,2,FALSE)),"")) -> EP-03 | D15: =IF($B15="","",IFERROR(IF(VLOOKUP($B15,'Historias de usuario'!$A$6:$P$25,3,FALSE)="","",VLOOKUP($B15,'Historias de usuario'!$A$6:$P$25,3,FALSE)),"")) -> Consultas comerciales | E15: =IF($B15="","",IFERROR(IF(VLOOKUP($B15,'Historias de usuario'!$A$6:$P$25,4,FALSE)="","",VLOOKUP($B15,'Historias de usuario'!$A$6:$P$25,4,FALSE)),"")) -> Consultar productos, stock y clientes | F15: =IF($B15="","",IFERROR(IF(VLOOKUP($B15,'Historias de usuario'!$A$6:$P$25,8,FALSE)="","",VLOOKUP($B15,'Historias de usuario'!$A$6:$P$25,8,FALSE)),"")) -> Como vendedor o asistente de vendedor, quiero consultar productos, stock, clientes, crédito y bloqueo en la empresa activa, para tomar decisiones comerciales con información vigente del ERP | G15: =IF($B15="","",IFERROR(IF(VLOOKUP($B15,'Historias de usuario'!$A$6:$P$25,9,FALSE)="","",VLOOKUP($B15,'Historias de usuario'!$A$6:$P$25,9,FALSE)),"")) -> 1. Las consultas muestran datos vigentes del ERP para la empresa activa. 2. El vendedor ve sus clientes y el asistente los de los vendedores asignados. 3. Stock, precios, crédito y bloqueo son de solo lectura y no se duplican como maestros locales. 4. Un cliente bloqueado queda identificado antes de solicitar una orden de venta. | H15: =IF($B15="","",IFERROR(IF(VLOOKUP($B15,'Historias de usuario'!$A$6:$P$25,10,FALSE)="","",VLOOKUP($B15,'Historias de usuario'!$A$6:$P$25,10,FALSE)),"")) -> Alta | I15: =IF($B15="","",IFERROR(IF(VLOOKUP($B15,'Historias de usuario'!$A$6:$P$25,11,FALSE)="","",VLOOKUP($B15,'Historias de usuario'!$A$6:$P$25,11,FALSE)),"")) -> 8 | J15: =IF($B15="","",IFERROR(IF(VLOOKUP($B15,'Historias de usuario'!$A$6:$P$25,12,FALSE)="","",VLOOKUP($B15,'Historias de usuario'!$A$6:$P$25,12,FALSE)),"")) -> HU-004, HU-015 | K15: =IF($B15="","",IFERROR(IF(VLOOKUP($B15,'Historias de usuario'!$A$6:$P$25,13,FALSE)="","",VLOOKUP($B15,'Historias de usuario'!$A$6:$P$25,13,FALSE)),"")) -> Propuesto | L15: =IF($B15="","",IFERROR(IF(VLOOKUP($B15,'Historias de usuario'!$A$6:$P$25,14,FALSE)="","",VLOOKUP($B15,'Historias de usuario'!$A$6:$P$25,14,FALSE)),"")) -> Sprint 3 · 2 sem. | M15: =IF($B15="","",IFERROR(IF(VLOOKUP($B15,'Historias de usuario'!$A$6:$P$25,15,FALSE)="","",VLOOKUP($B15,'Historias de usuario'!$A$6:$P$25,15,FALSE)),"")) -> Alexssander y Millaray
A16: 11 | B16: HU-009 | C16: =IF($B16="","",IFERROR(IF(VLOOKUP($B16,'Historias de usuario'!$A$6:$P$25,2,FALSE)="","",VLOOKUP($B16,'Historias de usuario'!$A$6:$P$25,2,FALSE)),"")) -> EP-03 | D16: =IF($B16="","",IFERROR(IF(VLOOKUP($B16,'Historias de usuario'!$A$6:$P$25,3,FALSE)="","",VLOOKUP($B16,'Historias de usuario'!$A$6:$P$25,3,FALSE)),"")) -> Cotizaciones | E16: =IF($B16="","",IFERROR(IF(VLOOKUP($B16,'Historias de usuario'!$A$6:$P$25,4,FALSE)="","",VLOOKUP($B16,'Historias de usuario'!$A$6:$P$25,4,FALSE)),"")) -> Crear y administrar cotizaciones | F16: =IF($B16="","",IFERROR(IF(VLOOKUP($B16,'Historias de usuario'!$A$6:$P$25,8,FALSE)="","",VLOOKUP($B16,'Historias de usuario'!$A$6:$P$25,8,FALSE)),"")) -> Como vendedor o asistente de vendedor, quiero crear cotizaciones con varias líneas y el vendedor correspondiente, para presentar una oferta comercial consistente con la empresa activa | G16: =IF($B16="","",IFERROR(IF(VLOOKUP($B16,'Historias de usuario'!$A$6:$P$25,9,FALSE)="","",VLOOKUP($B16,'Historias de usuario'!$A$6:$P$25,9,FALSE)),"")) -> 1. La cotización exige un cliente y al menos una línea de producto. 2. El vendedor usa su SlpCode; el asistente elige solo entre los vendedores asignados en la empresa activa. 3. Se registra tanto al creador como al vendedor del documento. 4. La comisión se calcula con la escala del vendedor o con la predeterminada si no tiene una asignada. | H16: =IF($B16="","",IFERROR(IF(VLOOKUP($B16,'Historias de usuario'!$A$6:$P$25,10,FALSE)="","",VLOOKUP($B16,'Historias de usuario'!$A$6:$P$25,10,FALSE)),"")) -> Alta | I16: =IF($B16="","",IFERROR(IF(VLOOKUP($B16,'Historias de usuario'!$A$6:$P$25,11,FALSE)="","",VLOOKUP($B16,'Historias de usuario'!$A$6:$P$25,11,FALSE)),"")) -> 8 | J16: =IF($B16="","",IFERROR(IF(VLOOKUP($B16,'Historias de usuario'!$A$6:$P$25,12,FALSE)="","",VLOOKUP($B16,'Historias de usuario'!$A$6:$P$25,12,FALSE)),"")) -> HU-004, HU-008 | K16: =IF($B16="","",IFERROR(IF(VLOOKUP($B16,'Historias de usuario'!$A$6:$P$25,13,FALSE)="","",VLOOKUP($B16,'Historias de usuario'!$A$6:$P$25,13,FALSE)),"")) -> Propuesto | L16: =IF($B16="","",IFERROR(IF(VLOOKUP($B16,'Historias de usuario'!$A$6:$P$25,14,FALSE)="","",VLOOKUP($B16,'Historias de usuario'!$A$6:$P$25,14,FALSE)),"")) -> Sprint 3 · 2 sem. | M16: =IF($B16="","",IFERROR(IF(VLOOKUP($B16,'Historias de usuario'!$A$6:$P$25,15,FALSE)="","",VLOOKUP($B16,'Historias de usuario'!$A$6:$P$25,15,FALSE)),"")) -> Millaray y Alexssander
A17: 12 | B17: HU-013 | C17: =IF($B17="","",IFERROR(IF(VLOOKUP($B17,'Historias de usuario'!$A$6:$P$25,2,FALSE)="","",VLOOKUP($B17,'Historias de usuario'!$A$6:$P$25,2,FALSE)),"")) -> EP-04 | D17: =IF($B17="","",IFERROR(IF(VLOOKUP($B17,'Historias de usuario'!$A$6:$P$25,3,FALSE)="","",VLOOKUP($B17,'Historias de usuario'!$A$6:$P$25,3,FALSE)),"")) -> Avisos al solicitante | E17: =IF($B17="","",IFERROR(IF(VLOOKUP($B17,'Historias de usuario'!$A$6:$P$25,4,FALSE)="","",VLOOKUP($B17,'Historias de usuario'!$A$6:$P$25,4,FALSE)),"")) -> Informar cambios de estado al solicitante | F17: =IF($B17="","",IFERROR(IF(VLOOKUP($B17,'Historias de usuario'!$A$6:$P$25,8,FALSE)="","",VLOOKUP($B17,'Historias de usuario'!$A$6:$P$25,8,FALSE)),"")) -> Como participante de un proceso, quiero recibir y administrar notificaciones de aprobaciones, rechazos, observaciones y cambios de estado, para saber cuándo debo actuar y acceder directamente al proceso | G17: =IF($B17="","",IFERROR(IF(VLOOKUP($B17,'Historias de usuario'!$A$6:$P$25,9,FALSE)="","",VLOOKUP($B17,'Historias de usuario'!$A$6:$P$25,9,FALSE)),"")) -> 1. Cada cambio relevante genera una notificación al participante correspondiente. 2. Las campanas diferencian avisos generales y autorizaciones de órdenes de venta. 3. La página de notificaciones permite abrir, marcar como leída, marcar todas y eliminar una o todas. 4. Se registra la fecha de lectura y cada enlace abre el proceso de origen. | H17: =IF($B17="","",IFERROR(IF(VLOOKUP($B17,'Historias de usuario'!$A$6:$P$25,10,FALSE)="","",VLOOKUP($B17,'Historias de usuario'!$A$6:$P$25,10,FALSE)),"")) -> Alta | I17: =IF($B17="","",IFERROR(IF(VLOOKUP($B17,'Historias de usuario'!$A$6:$P$25,11,FALSE)="","",VLOOKUP($B17,'Historias de usuario'!$A$6:$P$25,11,FALSE)),"")) -> 5 | J17: =IF($B17="","",IFERROR(IF(VLOOKUP($B17,'Historias de usuario'!$A$6:$P$25,12,FALSE)="","",VLOOKUP($B17,'Historias de usuario'!$A$6:$P$25,12,FALSE)),"")) -> HU-006, HU-012 | K17: =IF($B17="","",IFERROR(IF(VLOOKUP($B17,'Historias de usuario'!$A$6:$P$25,13,FALSE)="","",VLOOKUP($B17,'Historias de usuario'!$A$6:$P$25,13,FALSE)),"")) -> Propuesto | L17: =IF($B17="","",IFERROR(IF(VLOOKUP($B17,'Historias de usuario'!$A$6:$P$25,14,FALSE)="","",VLOOKUP($B17,'Historias de usuario'!$A$6:$P$25,14,FALSE)),"")) -> Sprint 3 · 2 sem. | M17: =IF($B17="","",IFERROR(IF(VLOOKUP($B17,'Historias de usuario'!$A$6:$P$25,15,FALSE)="","",VLOOKUP($B17,'Historias de usuario'!$A$6:$P$25,15,FALSE)),"")) -> Millaray y Matías
... A25: 20 | B25: HU-020 | C25: =IF($B25="","",IFERROR(IF(VLOOKUP($B25,'Historias de usuario'!$A$6:$P$25,2,FALSE)="","",VLOOKUP($B25,'Historias de usuario'!$A$6:$P$25,2,FALSE)),"")) -> EP-06 | D25: =IF($B25="","",IFERROR(IF(VLOOKUP($B25,'Historias de usuario'!$A$6:$P$25,3,FALSE)="","",VLOOKUP($B25,'Historias de usuario'!$A$6:$P$25,3,FALSE)),"")) -> Seguimiento y cierre | E25: =IF($B25="","",IFERROR(IF(VLOOKUP($B25,'Historias de usuario'!$A$6:$P$25,4,FALSE)="","",VLOOKUP($B25,'Historias de usuario'!$A$6:$P$25,4,FALSE)),"")) -> Gestionar el avance y cierre de posventa | F25: =IF($B25="","",IFERROR(IF(VLOOKUP($B25,'Historias de usuario'!$A$6:$P$25,8,FALSE)="","",VLOOKUP($B25,'Historias de usuario'!$A$6:$P$25,8,FALSE)),"")) -> Como autorizador de posventa, quiero actualizar el caso por sus estados y registrar su resolución final, para mantener el seguimiento hasta un cierre controlado | G25: =IF($B25="","",IFERROR(IF(VLOOKUP($B25,'Historias de usuario'!$A$6:$P$25,9,FALSE)="","",VLOOKUP($B25,'Historias de usuario'!$A$6:$P$25,9,FALSE)),"")) -> 1. El flujo con guía contempla Pendiente, Autorizado, QR enviado, Recepcionado y la ruta de stock o proveedor hasta cierre. 2. El caso con factura de reserva sigue la ruta sin QR ni recepción. 3. Cada cambio notifica al vendedor y autorizador y admite observaciones visibles. 4. Solo el autorizador cierra el caso; un caso cerrado no acepta nuevos cambios. | H25: =IF($B25="","",IFERROR(IF(VLOOKUP($B25,'Historias de usuario'!$A$6:$P$25,10,FALSE)="","",VLOOKUP($B25,'Historias de usuario'!$A$6:$P$25,10,FALSE)),"")) -> Alta | I25: =IF($B25="","",IFERROR(IF(VLOOKUP($B25,'Historias de usuario'!$A$6:$P$25,11,FALSE)="","",VLOOKUP($B25,'Historias de usuario'!$A$6:$P$25,11,FALSE)),"")) -> 8 | J25: =IF($B25="","",IFERROR(IF(VLOOKUP($B25,'Historias de usuario'!$A$6:$P$25,12,FALSE)="","",VLOOKUP($B25,'Historias de usuario'!$A$6:$P$25,12,FALSE)),"")) -> HU-019, HU-014 | K25: =IF($B25="","",IFERROR(IF(VLOOKUP($B25,'Historias de usuario'!$A$6:$P$25,13,FALSE)="","",VLOOKUP($B25,'Historias de usuario'!$A$6:$P$25,13,FALSE)),"")) -> Propuesto | L25: =IF($B25="","",IFERROR(IF(VLOOKUP($B25,'Historias de usuario'!$A$6:$P$25,14,FALSE)="","",VLOOKUP($B25,'Historias de usuario'!$A$6:$P$25,14,FALSE)),"")) -> Sprint 6 · 1 sem. | M25: =IF($B25="","",IFERROR(IF(VLOOKUP($B25,'Historias de usuario'!$A$6:$P$25,15,FALSE)="","",VLOOKUP($B25,'Historias de usuario'!$A$6:$P$25,15,FALSE)),"")) -> Millaray y Alexssander

Sheet Historias de usuario
A2: Historias de usuario
A4: Registre una historia por fila. La frase completa se construye automáticamente con Como, Quiero y Para.
A5: ID HU | B5: ID Épica | C5: Funcionalidad | D5: Título | E5: Como | F5: Quiero | G5: Para | H5: Historia completa | I5: Criterios de aceptación | J5: Prioridad | K5: Estimación SP | L5: Dependencias | M5: Estado | N5: Sprint | O5: Responsable | P5: Observaciones
A6: HU-001 | B6: EP-01 | C6: Acceso seguro | D6: Autenticarse en la plataforma | E6: usuario habilitado | F6: iniciar sesión de forma segura y mantener una sesión controlada | G6: acceder únicamente a las funciones autorizadas | H6: =IF(OR(E6="",F6="",G6=""),"","Como "&E6&", quiero "&F6&", para "&G6) -> Como usuario habilitado, quiero iniciar sesión de forma segura y mantener una sesión controlada, para acceder únicamente a las funciones autorizadas | I6: 1. Con credenciales válidas, el usuario activo ingresa a la plataforma. 2. Las credenciales inválidas o de un usuario desactivado impiden el acceso y muestran un mensaje claro. 3. La contraseña se almacena mediante hash, la sesión expira por inactividad y los intentos fallidos quedan auditados. | J6: Alta | K6: 5 | L6: Ninguna | M6: Terminado | N6: Sprint 1 · 2 sem. | O6: Matías y Alexssander | P6: Cubre RF-01; RN-02; RNF-01, RNF-04 y RNF-05.
A7: HU-002 | B7: EP-01 | C7: Administración de usuarios | D7: Administrar usuarios y perfiles | E7: administrador | F7: crear, editar, desactivar y reactivar usuarios asignándoles área, cargo, grupos de autorizadores y permisos directos | G7: mantener los accesos alineados con las responsabilidades de cada trabajador | H7: =IF(OR(E7="",F7="",G7=""),"","Como "&E7&", quiero "&F7&", para "&G7) -> Como administrador, quiero crear, editar, desactivar y reactivar usuarios asignándoles área, cargo, grupos de autorizadores y permisos directos, para mantener los accesos alineados con las responsabilidades de cada trabajador | I7: 1. El administrador crea y edita usuarios con área y cargo obligatorios. 2. Un usuario se desactiva o reactiva sin eliminar su historial. 3. Solo el administrador puede ejecutar estas operaciones y un usuario desactivado no puede iniciar sesión. | J7: Alta | K7: 8 | L7: HU-001 | M7: Terminado | N7: Sprint 1 · 2 sem. | O7: Matías y Alexssander | P7: Cubre RF-02 y RF-04; RN-01, RN-02 y RN-04.
A8: HU-003 | B8: EP-01 | C8: Permisos y autorizadores | D8: Configurar permisos y grupos de autorización | E8: administrador | F8: definir permisos por área, por cargo y directos por usuario, además de los integrantes de los grupos de autorizadores de cada proceso | G8: controlar qué funciones, datos y decisiones corresponden a cada usuario | H8: =IF(OR(E8="",F8="",G8=""),"","Como "&E8&", quiero "&F8&", para "&G8) -> Como administrador, quiero definir permisos por área, por cargo y directos por usuario, además de los integrantes de los grupos de autorizadores de cada proceso, para controlar qué funciones, datos y decisiones corresponden a cada usuario | I8: 1. Los permisos efectivos suman los permisos directos, del área y del cargo. 2. Cada operación valida los permisos en el servidor. 3. Es posible modificar los integrantes de los grupos de cada proceso, siempre con al menos un integrante activo. 4. Solo el administrador gestiona permisos y grupos. | J8: Alta | K8: 8 | L8: HU-002 | M8: Terminado | N8: Sprint 1 · 2 sem. | O8: Matías y Alexssander | P8: Cubre RF-03, RF-05 y RF-29; RN-03 a RN-05; RNF-02.
A9: HU-004 | B9: EP-01 | C9: Contexto de empresa y vendedor | D9: Configurar empresas, vendedores y comisiones | E9: administrador | F9: asociar SlpCode y escala de comisión por empresa a vendedores y asistentes | G9: asegurar que cada operación use la empresa y el vendedor correctos | H9: =IF(OR(E9="",F9="",G9=""),"","Como "&E9&", quiero "&F9&", para "&G9) -> Como administrador, quiero asociar SlpCode y escala de comisión por empresa a vendedores y asistentes, para asegurar que cada operación use la empresa y el vendedor correctos | I9: 1. Cada SlpCode queda asociado a Marsella o Asland y a los usuarios autorizados. 2. Se asigna una escala de comisión o se usa la escala predeterminada. 3. El selector de empresa solo aparece a usuarios con códigos en ambas empresas. 4. Al cambiar la empresa activa, consultas, documentos, solicitudes y casos usan ese contexto y su color identificador. | J9: Alta | K9: 8 | L9: HU-002, HU-003 | M9: Terminado | N9: Sprint 1 · 2 sem. | O9: Matías y Alexssander | P9: Cubre RF-35, RF-36 y RF-37; RN-35 a RN-38.
A10: HU-005 | B10: EP-02 | C10: Solicitud de códigos | D10: Crear y enviar solicitudes de código | E10: vendedor autorizado | F10: crear solicitudes de creación, activación o modificación de artículos con sus respaldos | G10: enviar información completa al grupo autorizador correspondiente | H10: =IF(OR(E10="",F10="",G10=""),"","Como "&E10&", quiero "&F10&", para "&G10) -> Como vendedor autorizado, quiero crear solicitudes de creación, activación o modificación de artículos con sus respaldos, para enviar información completa al grupo autorizador correspondiente | I10: 1. La solicitud se crea en estado Pendiente y queda asociada al usuario y empresa activa. 2. Permite incluir uno o más productos según el tipo de solicitud. 3. Exige el respaldo de cotización según su tipo y permite, para creaciones, un documento y una imagen por producto en los formatos permitidos. 4. Al enviarla, ingresa a la bandeja del grupo autorizador correcto. | J10: Alta | K10: 8 | L10: HU-003, HU-004 | M10: Terminado | N10: Sprint 2 · 2 sem. | O10: Millaray y Matías | P10: Cubre RF-06 y RF-39; RN-06, RN-07, RN-11 y RN-40.
A11: HU-006 | B11: EP-02 | C11: Resolución de solicitudes | D11: Aprobar o rechazar solicitudes | E11: autorizador | F11: aprobar, rechazar o pedir corrección de una solicitud de la bandeja compartida | G11: resolverla con un responsable y una decisión trazable | H11: =IF(OR(E11="",F11="",G11=""),"","Como "&E11&", quiero "&F11&", para "&G11) -> Como autorizador, quiero aprobar, rechazar o pedir corrección de una solicitud de la bandeja compartida, para resolverla con un responsable y una decisión trazable | I11: 1. Solo el grupo autorizador del tipo de solicitud puede verla y resolverla. 2. Quien resuelve la solicitud queda registrado como responsable. 3. El rechazo exige un motivo visible para el solicitante. 4. La solicitud aprobada no admite edición y conserva usuario, fecha, hora y comentario de la resolución. | J11: Alta | K11: 5 | L11: HU-005 | M11: Terminado | N11: Sprint 2 · 2 sem. | O11: Millaray y Matías | P11: Cubre RF-07; RN-07, RN-08 y RN-10. El envío posterior al ERP depende de HU-016.
A12: HU-007 | B12: EP-02 | C12: Seguimiento de solicitudes | D12: Corregir, reenviar y consultar solicitudes | E12: vendedor solicitante | F12: corregir y reenviar solicitudes rechazadas, además de consultar y filtrar su seguimiento | G12: resolver observaciones y conocer el estado de cada gestión | H12: =IF(OR(E12="",F12="",G12=""),"","Como "&E12&", quiero "&F12&", para "&G12) -> Como vendedor solicitante, quiero corregir y reenviar solicitudes rechazadas, además de consultar y filtrar su seguimiento, para resolver observaciones y conocer el estado de cada gestión | I12: 1. Solo el creador puede corregir y reenviar una solicitud rechazada. 2. El reenvío vuelve a estado Pendiente y a la bandeja del grupo autorizador. 3. El usuario consulta estado, responsable, fecha y comentario. 4. Los filtros por estado, fecha, área y responsable devuelven resultados acordes con sus permisos. | J12: Alta | K12: 8 | L12: HU-006 | M12: Terminado | N12: Sprint 2 · 2 sem. | O12: Millaray y Matías | P12: Cubre RF-08, RF-09 y RF-10; RN-08 a RN-10.
A13: HU-008 | B13: EP-03 | C13: Consultas comerciales | D13: Consultar productos, stock y clientes | E13: vendedor o asistente de vendedor | F13: consultar productos, stock, clientes, crédito y bloqueo en la empresa activa | G13: tomar decisiones comerciales con información vigente del ERP | H13: =IF(OR(E13="",F13="",G13=""),"","Como "&E13&", quiero "&F13&", para "&G13) -> Como vendedor o asistente de vendedor, quiero consultar productos, stock, clientes, crédito y bloqueo en la empresa activa, para tomar decisiones comerciales con información vigente del ERP | I13: 1. Las consultas muestran datos vigentes del ERP para la empresa activa. 2. El vendedor ve sus clientes y el asistente los de los vendedores asignados. 3. Stock, precios, crédito y bloqueo son de solo lectura y no se duplican como maestros locales. 4. Un cliente bloqueado queda identificado antes de solicitar una orden de venta. | J13: Alta | K13: 8 | L13: HU-004, HU-015 | M13: Propuesto | N13: Sprint 3 · 2 sem. | O13: Alexssander y Millaray | P13: Cubre RF-11 y RF-12; RN-13, RN-16 y RN-17; RNF-13.
A14: HU-009 | B14: EP-03 | C14: Cotizaciones | D14: Crear y administrar cotizaciones | E14: vendedor o asistente de vendedor | F14: crear cotizaciones con varias líneas y el vendedor correspondiente | G14: presentar una oferta comercial consistente con la empresa activa | H14: =IF(OR(E14="",F14="",G14=""),"","Como "&E14&", quiero "&F14&", para "&G14) -> Como vendedor o asistente de vendedor, quiero crear cotizaciones con varias líneas y el vendedor correspondiente, para presentar una oferta comercial consistente con la empresa activa | I14: 1. La cotización exige un cliente y al menos una línea de producto. 2. El vendedor usa su SlpCode; el asistente elige solo entre los vendedores asignados en la empresa activa. 3. Se registra tanto al creador como al vendedor del documento. 4. La comisión se calcula con la escala del vendedor o con la predeterminada si no tiene una asignada. | J14: Alta | K14: 8 | L14: HU-004, HU-008 | M14: Propuesto | N14: Sprint 3 · 2 sem. | O14: Millaray y Alexssander | P14: Cubre RF-13 y RF-38; RN-12, RN-16 y RN-37 a RN-39.
A15: HU-010 | B15: EP-03 | C15: Conversión comercial | D15: Emitir la cotización y solicitar la orden de venta | E15: vendedor | F15: descargar la cotización y convertir una cotización aceptada en solicitud de orden de venta | G15: continuar el proceso comercial sin volver a ingresar sus datos | H15: =IF(OR(E15="",F15="",G15=""),"","Como "&E15&", quiero "&F15&", para "&G15) -> Como vendedor, quiero descargar la cotización y convertir una cotización aceptada en solicitud de orden de venta, para continuar el proceso comercial sin volver a ingresar sus datos | I15: 1. La cotización puede generarse en un formato imprimible o descargable. 2. Solo una cotización abierta y aceptada puede convertirse. 3. La solicitud hereda cliente, líneas y condiciones, y conserva el vínculo con la cotización. 4. Se impide continuar si el cliente está bloqueado. | J15: Alta | K15: 5 | L15: HU-009 | M15: Propuesto | N15: Sprint 4 · 2 sem. | O15: Millaray y Alexssander | P15: Cubre RF-14 y RF-16; RN-13 a RN-15.
A16: HU-011 | B16: EP-03 | C16: Órdenes de venta | D16: Autorizar, enviar y seguir órdenes de venta | E16: autorizador comercial | F16: aprobar las solicitudes que correspondan y enviar la orden de venta al ERP | G16: crear únicamente documentos validados y mantener su trazabilidad | H16: =IF(OR(E16="",F16="",G16=""),"","Como "&E16&", quiero "&F16&", para "&G16) -> Como autorizador comercial, quiero aprobar las solicitudes que correspondan y enviar la orden de venta al ERP, para crear únicamente documentos validados y mantener su trazabilidad | I16: 1. Toda orden requiere autorización previa y, si alguna línea tiene un margen inferior al mínimo definido, también la de Gerencia. 2. Solo un rol autorizado puede aprobar el envío. 3. El ERP recibe exactamente el documento autorizado y devuelve un resultado e identificador. 4. El usuario consulta el estado, vínculo y trazabilidad del documento enviado. | J16: Alta | K16: 8 | L16: HU-010, HU-016, HU-017 | M16: Propuesto | N16: Sprint 4 · 2 sem. | O16: Alexssander y Matías | P16: Cubre RF-15 y RF-31; RN-18, RN-25 y RNF-14.
A17: HU-012 | B17: EP-04 | C17: Avisos a autorizadores | D17: Notificar pendientes y recordatorios | E17: autorizador | F17: recibir avisos de los procesos pendientes y recordatorios cuando superen una hora | G17: atender oportunamente las decisiones que me corresponden | H17: =IF(OR(E17="",F17="",G17=""),"","Como "&E17&", quiero "&F17&", para "&G17) -> Como autorizador, quiero recibir avisos de los procesos pendientes y recordatorios cuando superen una hora, para atender oportunamente las decisiones que me corresponden | I17: 1. Al enviar un proceso, se notifica únicamente a los destinatarios autorizados. 2. La notificación identifica categoría, emisor, nivel y enlace al proceso. 3. Después de una hora pendiente se genera un recordatorio automático. 4. El usuario no puede ver notificaciones ajenas. | J17: Alta | K17: 5 | L17: HU-005, HU-006 | M17: Terminado | N17: Sprint 2 · 2 sem. | O17: Millaray y Matías | P17: Cubre RF-17; RN-20, RN-21 y RN-22.
... A25: HU-020 | B25: EP-06 | C25: Seguimiento y cierre | D25: Gestionar el avance y cierre de posventa | E25: autorizador de posventa | F25: actualizar el caso por sus estados y registrar su resolución final | G25: mantener el seguimiento hasta un cierre controlado | H25: =IF(OR(E25="",F25="",G25=""),"","Como "&E25&", quiero "&F25&", para "&G25) -> Como autorizador de posventa, quiero actualizar el caso por sus estados y registrar su resolución final, para mantener el seguimiento hasta un cierre controlado | I25: 1. El flujo con guía contempla Pendiente, Autorizado, QR enviado, Recepcionado y la ruta de stock o proveedor hasta cierre. 2. El caso con factura de reserva sigue la ruta sin QR ni recepción. 3. Cada cambio notifica al vendedor y autorizador y admite observaciones visibles. 4. Solo el autorizador cierra el caso; un caso cerrado no acepta nuevos cambios. | J25: Alta | K25: 8 | L25: HU-019, HU-014 | M25: Propuesto | N25: Sprint 6 · 1 sem. | O25: Millaray y Alexssander | P25: Cubre RF-30 y RF-34; RN-31, RN-32 y RN-34.

Sheet Épicas y funciones
A2: Épicas y funcionalidades
A4: Cada épica representa un bloque grande de valor y agrupa funcionalidades e historias relacionadas.
A5: ID Épica | B5: Épica o módulo | C5: Problema u oportunidad | D5: Objetivo y valor esperado | E5: Usuarios | F5: Funcionalidades incluidas | G5: Fuera de alcance | H5: Dependencias | I5: Prioridad | J5: Tamaño | K5: Criterio de término | L5: Estado | M5: Responsable
A6: EP-01 | B6: Gestión de usuarios roles y permisos | C6: Los accesos deben corresponder a la responsabilidad y empresa de cada trabajador. | D6: Proteger la plataforma y asegurar que cada usuario opere con el perfil, empresa y vendedor correctos. | E6: Administrador, vendedores, asistentes, autorizadores y jefatura | F6: Autenticación; usuarios; áreas; cargos; roles; permisos; grupos autorizadores; SlpCode; escalas; selector de empresa | G6: Inicio de sesión externo, Active Directory y administración de SAP | H6: Definiciones organizacionales de perfiles, empresas y escalas | I6: Alta | J6: L | K6: HU-001 a HU-004 aceptadas; permisos validados en servidor y trazabilidad de accesos comprobada. | L6: En análisis | M6: Matías y Alexssander
A7: EP-02 | B7: Solicitudes y autorizaciones | C7: Las solicitudes de códigos requieren respaldos, revisión y seguimiento centralizados. | D7: Reducir reprocesos y hacer visible la creación, activación o modificación de artículos desde su envío hasta la resolución. | E7: Vendedores, asistentes, grupos autorizadores y jefatura | F7: Creación; adjuntos; bandeja; aprobación/rechazo; corrección; reenvío; búsqueda; seguimiento | G7: Solicitudes distintas de códigos de artículo | H7: EP-01, EP-04 y escritura controlada de EP-05 | I7: Alta | J7: L | K7: HU-005 a HU-007 aceptadas; estados, reglas de adjuntos, permisos y resolución trazable verificados. | L7: En análisis | M7: Millaray y Matías
A8: EP-03 | B8: Gestión comercial cotizaciones y órdenes de venta | C8: La gestión comercial necesita datos vigentes y documentos consistentes sin repetir ingresos. | D8: Centralizar consultas, cotizaciones y órdenes de venta, aplicando vendedor, comisión, autorización e integración correctos. | E8: Vendedores, asistentes, autorizadores comerciales y jefatura | F8: Productos; stock; clientes; crédito; cotizaciones; descarga; conversión; órdenes; comisiones; trazabilidad SAP | G8: Contabilidad completa, facturación, compras y logística integral | H8: EP-01, EP-04 y EP-05 | I8: Alta | J8: XL | K8: HU-008 a HU-011 aceptadas; documentos y restricciones comerciales probados de extremo a extremo. | L8: En análisis | M8: Alexssander y Millaray
A9: EP-04 | B9: Notificaciones y trazabilidad | C9: Los participantes necesitan conocer pendientes, decisiones y responsables sin depender de correos separados. | D9: Entregar avisos oportunos y una trazabilidad común para todos los procesos incorporados. | E9: Solicitantes, autorizadores, jefatura y demás participantes | F9: Campanas; página de notificaciones; recordatorios; enlaces; lectura/eliminación; historial de estados | G9: Correo, SMS y notificaciones fuera de la plataforma | H9: Eventos generados por EP-02, EP-03 y EP-06; permisos de EP-01 | I9: Alta | J9: M | K9: HU-012 a HU-014 aceptadas; privacidad, recordatorios e historial verificados en los procesos integrados. | L9: En análisis | M9: Millaray y Matías
A10: EP-05 | B10: Integración con SAP Business One | C10: La plataforma debe consultar y escribir en SAP por vías controladas, seguras y trazables. | D10: Canalizar lecturas por API sobre HANA y escrituras autorizadas por Service Layer sin duplicidad ni operaciones parciales. | E10: Usuarios de negocio, responsables de operación y administradores | F10: API de lectura; firma; paginación; Service Layer; registro de resultados; errores; reintentos | G10: Escritura directa en HANA, exposición a Internet y reemplazo de SAP | H10: SAP HANA; Service Layer; red corporativa; licenciamiento y credenciales autorizadas | I10: Alta | J10: L | K10: HU-015 a HU-017 aceptadas; seguridad, rendimiento, integridad e idempotencia comprobados. | L10: En análisis | M10: Alexssander y Matías
A11: EP-06 | B11: Gestión de Posventa | C11: Los casos posteriores a la venta necesitan evidencias, evaluación, autorización y seguimiento hasta su cierre. | D11: Centralizar la posventa y ofrecer visibilidad de cada caso, comprobante y decisión a los participantes autorizados. | E11: Vendedores, asistentes, autorizador de posventa, bodega y jefatura | F11: Tipos de caso; respaldo; evidencias; condiciones; rechazo/corrección; QR; estados; recepción; rutas; cierre | G11: Portal externo de clientes/proveedores y contabilización directa de notas de crédito o débito | H11: EP-01, EP-04, API de lectura de EP-05 y documentos de referencia de SAP | I11: Alta | J11: XL | K11: HU-018 a HU-020 aceptadas; rutas por guía o factura, QR, permisos, notificaciones y cierre verificados. | L11: En análisis | M11: Millaray y Alexssander

Sheet Product Goal
A2: Product Goal
A4: Defina el objetivo de largo plazo que orientará y ordenará el Product Backlog.
A6: Identificación del producto
A7: Producto | B7: Plataforma Integrada de Gestión GGH
A8: Organización | B8: Grupo Gómez Hermanos
A9: Product Owner | B9: Responsable rotativo del equipo por sprint
A10: Versión | B10: v1.0
A11: Fecha de revisión | B11: 46285
A12: Estado | B12: En revisión
A14: Definición del Product Goal
A15: Problema que resuelve | C15: Procesos internos distribuidos entre SAP Business One, correos, planillas y tareas manuales generan reprocesos, demoras y visibilidad fragmentada. Además, las consultas y gestiones repetitivas deben canalizarse de forma controlada para preservar el rendimiento y la integridad del ERP.
A18: Usuarios principales | C18: Administradores, vendedores, asistentes de vendedor, autorizadores, jefaturas, personal de posventa y bodega; clientes y proveedores se benefician indirectamente del seguimiento de los procesos.
A21: Valor organizacional esperado | C21: Centralización de gestiones, reducción de interacciones directas repetitivas con el ERP, decisiones más rápidas, control por roles, menor reproceso y trazabilidad completa de solicitudes, documentos y casos.
A24: Estado futuro del producto | C24: Los usuarios operan desde una plataforma web interna que valida datos, permisos y autorizaciones antes de consultar o enviar información a SAP Business One. El ERP continúa como fuente oficial y cada proceso conserva su historial verificable.
A27: Product Goal | C27: Consolidar una plataforma web interna para gestionar los seis módulos definidos, canalizando de forma segura las consultas y operaciones con SAP Business One y manteniendo trazabilidad completa de usuarios, decisiones, estados y resultados.
A30: Indicadores de éxito | C30: • Flujos principales completados con permisos correctos. • Procesos con usuario, fecha, estado y comentario trazables. • Consultas normales al ERP bajo 3 segundos. • Envíos sin duplicidad ni registros parciales. • Errores y reintentos registrados. • Casos de prueba y criterios de aceptación aprobados por historia.
A33: Restricciones y dependencias | C33: Disponibilidad de SAP HANA y Service Layer; licenciamiento y accesos autorizados; operación dentro de la red corporativa; Windows Server 2016; datos maestros gestionados por SAP; acceso al ambiente real sujeto a disponibilidad; credenciales fuera del código.
A36: Supuestos | C36: La organización valida reglas, perfiles y límites de autorización; SAP Business One permanece como fuente oficial; las consultas a HANA son de solo lectura; las escrituras se realizan por Service Layer; si el ambiente real no está disponible, se usan servicios simulados con respuestas equivalentes.
A40: Relación entre los elementos
A41: Nivel | B41: Código | C41: Qué representa | D41: Ejemplo GGH | E41: Se divide en | F41: Quién prioriza | G41: Dónde se registra | H41: Resultado
A42: 1 | B42: PG | C42: Objetivo de largo plazo | D42: Mejorar la gestión previa y complementaria a SAP | E42: Épicas | F42: Product Owner | G42: Product Goal | H42: Dirección común
A43: 2 | B43: EP | C43: Bloque grande de valor | D43: Gestión de Posventa | E43: Funcionalidades e historias | F43: Product Owner | G43: Épicas y funciones | H43: Agrupación
A44: 3 | B44: HU | C44: Necesidad de un usuario | D44: Registrar una solicitud de devolución | E44: Tareas técnicas | F44: Product Owner con el equipo | G44: Historias de usuario | H44: Valor verificable
A45: 4 | B45: PB | C45: Lista ordenada de trabajo | D45: HU priorizadas y estimadas | E45: Ítems de Sprint | F45: Product Owner | G45: Product Backlog | H45: Orden de ejecución
A48: Referencias
A49: Scrum Guide 2020: https://scrumguides.org/scrum-guide.html
